Workbook
Name a: List!$A$2:$A$13
Name AdjustmentTypes: List!$L$2:$L$6
Name BudgetCategoryList: List!$I$2:$I$14
Name CashierList: List!$G$2:$G$4
Name CashierLists: List!$G$2:$G$6
Name CategoryList: List!$A$2:$A$13
Name CategoryLists: List!$A$2:$A$17
Name DateList: List!$J$2:$J$32
Name ddmmyyyy: Table8[Date]
Name ECategoryList: List!$F$2:$F$8
Name EPMethod: List!$H$2:$H$3
Name ExpensesCategoryList: List!$F$2:$F$14
Name PaymentMethodList: List!$H$2:$H$5
Name ProductID: List!$K$2:$K$51
Name ProductList: List!$B$2:$B$12
Name ProductNames: List!$B$2:$B$78
Name Statuslist: List!$E$2:$E$3
Name SupplierList: List!$D$2:$D$6
Name UnitofMeasures: List!$C$2:$C$19
Name Uomlist: List!$C$2:$C$18

Sheet User Guide
A1: Sales & Inventory Management System (SIMS PRO) V2.0
A4: Developed by :
A6: Olamilekan Analytics.
A8: Project Overview
A9: This sales & Inventory Management System was developed in Microsoft Excel to help businesses manage products, purchases, sales, inventory, expenses, budgeting and business performance through an interactive
A10: dashboard.
A12: FEATURES
A13: Product Management
A14: Stock Purchase Management
A15: Daily Sales Tracking
A16: Inventory Management
A17: Stock Adjustment
... A86: All Rights Reserved.

Sheet Dashboard
A1: SIMS PRO - Sales & Inventory Management System
B3: Total Products | D3: Total Sales | F3: Total Purchases | H3: Inventory Value | J3: Low Stock Items | L3: Out Of Stock Items
N4: Total Expenses | P4: Net Profit | R4: Total Transactions Today | T4: QTY Sold Today | V4: Revenue Today | X4: Profit Today | Z4: Today Sales | AB4: Yesterday's Sales | AD4: This week's Sales | AF4: This Month's Sales | AH4: Today's Profit | AJ4: Gross Profit | AL4: Net Profit
B5: =COUNTIF('Product Master'!A:A,"P*")-1 -> 15 | D5: =SUM('Daily Sales Entry'!J:J) -> 284700 | F5: =SUM('Stock Purchase'!H:H) -> 1995000 | H5: =SUM(Inventory!Q:Q) -> 1813300 | J5: =COUNTIF(Inventory!R:R,"Low Stock") -> 0 | L5: =COUNTIF(Inventory!R:R,"Out of Stock") -> 0 | N5: =SUM(Expenses!E:E) -> 42500 | P5: =D5-N5 -> 242200 | R5: =SUMPRODUCT(('Daily Sales Entry'!$A$2:$A$1000=TODAY())*('Daily Sales Entry'!$G$2:$G$1000>0)) -> 0 | T5: =SUMIFS('Daily Sales Entry'!G:G,'Daily Sales Entry'!A:A,TODAY()) -> 0 | V5: =SUMIF('Daily Sales Entry'!A:A,TODAY(),'Daily Sales Entry'!L:L) -> 0 | X5: =SUMIF('Daily Sales Entry'!A:A,TODAY(),'Daily Sales Entry'!M:M) -> 0 | Z5: =SUMIFS('Daily Sales Entry'!J:J,'Daily Sales Entry'!A:A,TODAY()) -> 0 | AB5: =SUMIFS('Daily Sales Entry'!J:J,'Daily Sales Entry'!A:A,TODAY()-1) -> 0 | AD5: =SUMIFS('Daily Sales Entry'!J:J,'Daily Sales Entry'!A:A,">="&TODAY()-WEEKDAY(TODAY(),2)+1,'Daily Sales Entry'!A:A,"<"&TODAY()+1) -> 30000 | AF5: =SUMIFS('Daily Sales Entry'!J:J,'Daily Sales Entry'!A:A,">="&EOMONTH(TODAY(),-1)+1,'Daily Sales Entry'!A:A,"<"&EOMONTH(TODAY(),0)+1) -> 0 | AH5: =SUMIFS('Daily Sales Entry'!M:M,'Daily Sales Entry'!A:A,TODAY()) -> 0 | AJ5: =SUM('Daily Sales Entry'!M:M) -> 80300 | AL5: =AJ5-N5 -> 37800
AJ7: Gross Profit Margin | AL7: Net Profit Margin
AJ8: =IFERROR(AJ5/D5,0) -> 0.28205128 | AL8: =IFERROR(AL5/D5,0) -> 0.13277134
B10: Product Name | C10: Total Sold | R10: Status | S10: Count | V10: Date | W10: Day | X10: Sales
B11: Shaki | C11: =SUMIF('Daily Sales Entry'!$D:$D,B11,'Daily Sales Entry'!$G:$G) -> 27 | R11: In Stock | S11: =COUNTIF(Inventory!R:R,"In Stock") -> 15 | V11: =TODAY()-6 -> 46261 | W11: =TEXT(V11,"ddd") -> Thu | X11: =SUMIFS('Daily Sales Entry'!J:J,'Daily Sales Entry'!A:A,V11) -> 0
B12: Moin Moin | C12: =SUMIF('Daily Sales Entry'!$D:$D,B12,'Daily Sales Entry'!$G:$G) -> 19 | R12: Low Stock | S12: =COUNTIF(Inventory!R:R,"Low Stock") -> 0 | V12: =V11+1 -> 46262 | W12: =TEXT(V12,"ddd") -> Fri | X12: =SUMIFS('Daily Sales Entry'!J:J,'Daily Sales Entry'!A:A,V12) -> 0
B13: Beef | C13: =SUMIF('Daily Sales Entry'!$D:$D,B13,'Daily Sales Entry'!$G:$G) -> 16 | R13: Out of Stock | S13: =COUNTIF(Inventory!R:R,"Out of Stock") -> 0 | V13: =V12+1 -> 46263 | W13: =TEXT(V13,"ddd") -> Sat | X13: =SUMIFS('Daily Sales Entry'!J:J,'Daily Sales Entry'!A:A,V13) -> 0
B14: Cow leg | C14: =SUMIF('Daily Sales Entry'!$D:$D,B14,'Daily Sales Entry'!$G:$G) -> 8 | V14: =V13+1 -> 46264 | W14: =TEXT(V14,"ddd") -> Sun | X14: =SUMIFS('Daily Sales Entry'!J:J,'Daily Sales Entry'!A:A,V14) -> 0
B15: Semovita | C15: =SUMIF('Daily Sales Entry'!$D:$D,B15,'Daily Sales Entry'!$G:$G) -> 7 | V15: =V14+1 -> 46265 | W15: =TEXT(V15,"ddd") -> Mon | X15: =SUMIFS('Daily Sales Entry'!J:J,'Daily Sales Entry'!A:A,V15) -> 30000
B16: Chicken Pie | C16: =SUMIF('Daily Sales Entry'!$D:$D,B16,'Daily Sales Entry'!$G:$G) -> 7 | V16: =V15+1 -> 46266 | W16: =TEXT(V16,"ddd") -> Tue | X16: =SUMIFS('Daily Sales Entry'!J:J,'Daily Sales Entry'!A:A,V16) -> 0
B17: Eva Water 0.75Cl | C17: =SUMIF('Daily Sales Entry'!$D:$D,B17,'Daily Sales Entry'!$G:$G) -> 7 | V17: =V16+1 -> 46267 | W17: =TEXT(V17,"ddd") -> Wed | X17: =SUMIFS('Daily Sales Entry'!J:J,'Daily Sales Entry'!A:A,V17) -> 0
B18: Beef Roll | C18: =SUMIF('Daily Sales Entry'!$D:$D,B18,'Daily Sales Entry'!$G:$G) -> 5
B19: Pet Lucozade Boost | C19: =SUMIF('Daily Sales Entry'!$D:$D,B19,'Daily Sales Entry'!$G:$G) -> 5
B20: Eba | C20: =SUMIF('Daily Sales Entry'!$D:$D,B20,'Daily Sales Entry'!$G:$G) -> 3
B21: Meat Pie | C21: =SUMIF('Daily Sales Entry'!$D:$D,B21,'Daily Sales Entry'!$G:$G) -> 3
B22: Ofada Rice New | C22: =SUMIF('Daily Sales Entry'!$D:$D,B22,'Daily Sales Entry'!$G:$G) -> 0 | J22: RECENT SALES | N22: LOW STOCK ALERT
B23: Tanta Roll | C23: =SUMIF('Daily Sales Entry'!$D:$D,B23,'Daily Sales Entry'!$G:$G) -> 0 | I23: Sales ID | J23: Product | K23: QTY | L23: Amount | N23: Product Name | O23: Current Stock | P23: Reorder Level | Q23: Status | S23: Category | T23: Total Sales
B24: Doughnut | C24: =SUMIF('Daily Sales Entry'!$D:$D,B24,'Daily Sales Entry'!$G:$G) -> 0 | I24: ='Daily Sales Entry'!B10 -> 4 | J24: ='Daily Sales Entry'!D10 -> Shaki | K24: ='Daily Sales Entry'!G10 -> 15 | L24: ='Daily Sales Entry'!J10 -> 18000 | N24: Shaki | O24: =IF(N24="","",IFERROR(VLOOKUP(N24,Inventory!$B:$R,12,FALSE),0)) -> 21 | P24: =IF(N24="","",IFERROR(VLOOKUP(N24,Inventory!$B:$R,15,FALSE),0)) -> 20 | Q24: =IF(N24="","",IFERROR(IF(O24=0,"Out of Stock",IF(O24<=P24,"Low Stock","In Stock")),"Out of Stock")) -> In Stock | S24: Food | T24: =SUMIF('Daily Sales Entry'!$E:$E,S24,'Daily Sales Entry'!$G:$G) -> 80
B25: Beef Burger | C25: =SUMIF('Daily Sales Entry'!$D:$D,B25,'Daily Sales Entry'!$G:$G) -> 0 | I25: ='Daily Sales Entry'!B11 -> 4 | J25: ='Daily Sales Entry'!D11 -> Moin Moin | K25: ='Daily Sales Entry'!G11 -> 13 | L25: ='Daily Sales Entry'!J11 -> 10400 | N25: Beef | O25: =IF(N25="","",IFERROR(VLOOKUP(N25,Inventory!$B:$R,12,FALSE),0)) -> 69 | P25: =IF(N25="","",IFERROR(VLOOKUP(N25,Inventory!$B:$R,15,FALSE),0)) -> 20 | Q25: =IF(N25="","",IFERROR(IF(O25=0,"Out of Stock",IF(O25<=P25,"Low Stock","In Stock")),"Out of Stock")) -> In Stock | S25: Snacks | T25: =SUMIF('Daily Sales Entry'!$E:$E,S25,'Daily Sales Entry'!$G:$G) -> 20
B26: Scotch Egg | C26: =SUMIF('Daily Sales Entry'!$D:$D,B26,'Daily Sales Entry'!$G:$G) -> 0 | I26: ='Daily Sales Entry'!B5 -> 1 | J26: ='Daily Sales Entry'!D5 -> Semovita | K26: ='Daily Sales Entry'!G5 -> 7 | L26: ='Daily Sales Entry'!J5 -> 4900 | N26: Semovita | O26: =IF(N26="","",IFERROR(VLOOKUP(N26,Inventory!$B:$R,12,FALSE),0)) -> 43 | P26: =IF(N26="","",IFERROR(VLOOKUP(N26,Inventory!$B:$R,15,FALSE),0)) -> 20 | Q26: =IF(N26="","",IFERROR(IF(O26=0,"Out of Stock",IF(O26<=P26,"Low Stock","In Stock")),"Out of Stock")) -> In Stock | S26: Drinks | T26: =SUMIF('Daily Sales Entry'!$E:$E,S26,'Daily Sales Entry'!$G:$G) -> 27
B27: Ppg Chicken | C27: =SUMIF('Daily Sales Entry'!$D:$D,B27,'Daily Sales Entry'!$G:$G) -> 0 | I27: ='Daily Sales Entry'!B7 -> 1 | J27: ='Daily Sales Entry'!D7 -> Moin Moin | K27: ='Daily Sales Entry'!G7 -> 6 | L27: ='Daily Sales Entry'!J7 -> 4800 | N27: Cow leg | O27: =IF(N27="","",IFERROR(VLOOKUP(N27,Inventory!$B:$R,12,FALSE),0)) -> 42 | P27: =IF(N27="","",IFERROR(VLOOKUP(N27,Inventory!$B:$R,15,FALSE),0)) -> 20 | Q27: =IF(N27="","",IFERROR(IF(O27=0,"Out of Stock",IF(O27<=P27,"Low Stock","In Stock")),"Out of Stock")) -> In Stock | S27: Beverages | T27: =SUMIF('Daily Sales Entry'!$E:$E,S27,'Daily Sales Entry'!$G:$G) -> 0
B28: Roasted Chicken | C28: =SUMIF('Daily Sales Entry'!$D:$D,B28,'Daily Sales Entry'!$G:$G) -> 0 | I28: ='Daily Sales Entry'!B9 -> 3 | J28: ='Daily Sales Entry'!D9 -> Beef | K28: ='Daily Sales Entry'!G9 -> 6 | L28: ='Daily Sales Entry'!J9 -> 6000 | N28: Eba | O28: =IF(N28="","",IFERROR(VLOOKUP(N28,Inventory!$B:$R,12,FALSE),0)) -> 47 | P28: =IF(N28="","",IFERROR(VLOOKUP(N28,Inventory!$B:$R,15,FALSE),0)) -> 20 | Q28: =IF(N28="","",IFERROR(IF(O28=0,"Out of Stock",IF(O28<=P28,"Low Stock","In Stock")),"Out of Stock")) -> In Stock | S28: Clothing | T28: =SUMIF('Daily Sales Entry'!$E:$E,S28,'Daily Sales Entry'!$G:$G) -> 0
B29: Chicken Salad | C29: =SUMIF('Daily Sales Entry'!$D:$D,B29,'Daily Sales Entry'!$G:$G) -> 0 | I29: ='Daily Sales Entry'!B2 -> 1 | J29: ='Daily Sales Entry'!D2 -> Beef | K29: ='Daily Sales Entry'!G2 -> 5 | L29: ='Daily Sales Entry'!J2 -> 5000 | N29: Moin Moin | O29: =IF(N29="","",IFERROR(VLOOKUP(N29,Inventory!$B:$R,12,FALSE),0)) -> 31 | P29: =IF(N29="","",IFERROR(VLOOKUP(N29,Inventory!$B:$R,15,FALSE),0)) -> 20 | Q29: =IF(N29="","",IFERROR(IF(O29=0,"Out of Stock",IF(O29<=P29,"Low Stock","In Stock")),"Out of Stock")) -> In Stock | S29: Cosmetics | T29: =SUMIF('Daily Sales Entry'!$E:$E,S29,'Daily Sales Entry'!$G:$G) -> 0
B30: Vegetable Salad | C30: =SUMIF('Daily Sales Entry'!$D:$D,B30,'Daily Sales Entry'!$G:$G) -> 0 | I30: ='Daily Sales Entry'!B3 -> 1 | J30: ='Daily Sales Entry'!D3 -> Shaki | K30: ='Daily Sales Entry'!G3 -> 4 | L30: ='Daily Sales Entry'!J3 -> 4800 | N30: Salad Pack | O30: =IF(N30="","",IFERROR(VLOOKUP(N30,Inventory!$B:$R,12,FALSE),0)) -> 0 | P30: =IF(N30="","",IFERROR(VLOOKUP(N30,Inventory!$B:$R,15,FALSE),0)) -> 0 | Q30: =IF(N30="","",IFERROR(IF(O30=0,"Out of Stock",IF(O30<=P30,"Low Stock","In Stock")),"Out of Stock")) -> Out of Stock | S30: Electronics | T30: =SUMIF('Daily Sales Entry'!$E:$E,S30,'Daily Sales Entry'!$G:$G) -> 0
B31: Scramble Egg | C31: =SUMIF('Daily Sales Entry'!$D:$D,B31,'Daily Sales Entry'!$G:$G) -> 0 | I31: ='Daily Sales Entry'!B4 -> 1 | J31: ='Daily Sales Entry'!D4 -> Cow leg | K31: ='Daily Sales Entry'!G4 -> 4 | L31: ='Daily Sales Entry'!J4 -> 6000 | N31: Schweppes Can 33Cl | O31: =IF(N31="","",IFERROR(VLOOKUP(N31,Inventory!$B:$R,12,FALSE),0)) -> 0 | P31: =IF(N31="","",IFERROR(VLOOKUP(N31,Inventory!$B:$R,15,FALSE),0)) -> 0 | Q31: =IF(N31="","",IFERROR(IF(O31=0,"Out of Stock",IF(O31<=P31,"Low Stock","In Stock")),"Out of Stock")) -> Out of Stock | S31: Frozen Foods | T31: =SUMIF('Daily Sales Entry'!$E:$E,S31,'Daily Sales Entry'!$G:$G) -> 0
B32: Cup Cake | C32: =SUMIF('Daily Sales Entry'!$D:$D,B32,'Daily Sales Entry'!$G:$G) -> 0 | I32: ='Daily Sales Entry'!B8 -> 2 | J32: ='Daily Sales Entry'!D8 -> Cow leg | K32: ='Daily Sales Entry'!G8 -> 4 | L32: ='Daily Sales Entry'!J8 -> 6000 | N32: Coke Pet Light 50cl | O32: =IF(N32="","",IFERROR(VLOOKUP(N32,Inventory!$B:$R,12,FALSE),0)) -> 0 | P32: =IF(N32="","",IFERROR(VLOOKUP(N32,Inventory!$B:$R,15,FALSE),0)) -> 0 | Q32: =IF(N32="","",IFERROR(IF(O32=0,"Out of Stock",IF(O32<=P32,"Low Stock","In Stock")),"Out of Stock")) -> Out of Stock | S32: Furniture | T32: =SUMIF('Daily Sales Entry'!$E:$E,S32,'Daily Sales Entry'!$G:$G) -> 0
B33: Fruit Cake | C33: =SUMIF('Daily Sales Entry'!$D:$D,B33,'Daily Sales Entry'!$G:$G) -> 0 | I33: ='Daily Sales Entry'!B6 -> 1 | J33: ='Daily Sales Entry'!D6 -> Eba | K33: ='Daily Sales Entry'!G6 -> 3 | L33: ='Daily Sales Entry'!J6 -> 1500 | N33: Teem Lemon Pet | O33: =IF(N33="","",IFERROR(VLOOKUP(N33,Inventory!$B:$R,12,FALSE),0)) -> 0 | P33: =IF(N33="","",IFERROR(VLOOKUP(N33,Inventory!$B:$R,15,FALSE),0)) -> 0 | Q33: =IF(N33="","",IFERROR(IF(O33=0,"Out of Stock",IF(O33<=P33,"Low Stock","In Stock")),"Out of Stock")) -> Out of Stock | S33: Groceries | T33: =SUMIF('Daily Sales Entry'!$E:$E,S33,'Daily Sales Entry'!$G:$G) -> 0
B34: 10 CELEBRATION CAKE | C34: =SUMIF('Daily Sales Entry'!$D:$D,B34,'Daily Sales Entry'!$G:$G) -> 0 | I34: ='Daily Sales Entry'!B12 -> 5 | J34: ='Daily Sales Entry'!D12 -> Meat Pie | K34: ='Daily Sales Entry'!G12 -> 3 | L34: ='Daily Sales Entry'!J12 -> 2700 | N34: FAB Energy Drinks | O34: =IF(N34="","",IFERROR(VLOOKUP(N34,Inventory!$B:$R,12,FALSE),0)) -> 45 | P34: =IF(N34="","",IFERROR(VLOOKUP(N34,Inventory!$B:$R,15,FALSE),0)) -> 20 | Q34: =IF(N34="","",IFERROR(IF(O34=0,"Out of Stock",IF(O34<=P34,"Low Stock","In Stock")),"Out of Stock")) -> In Stock | S34: Office Supplies | T34: =SUMIF('Daily Sales Entry'!$E:$E,S34,'Daily Sales Entry'!$G:$G) -> 0
B35: 8 CELEBRATION CAKE | C35: =SUMIF('Daily Sales Entry'!$D:$D,B35,'Daily Sales Entry'!$G:$G) -> 0 | I35: ='Daily Sales Entry'!B13 -> 5 | J35: ='Daily Sales Entry'!D13 -> Chicken Pie | K35: ='Daily Sales Entry'!G13 -> 7 | L35: ='Daily Sales Entry'!J13 -> 7000 | N35: Lucozade Sport Pet 50cl | O35: =IF(N35="","",IFERROR(VLOOKUP(N35,Inventory!$B:$R,12,FALSE),0)) -> 45 | P35: =IF(N35="","",IFERROR(VLOOKUP(N35,Inventory!$B:$R,15,FALSE),0)) -> 20 | Q35: =IF(N35="","",IFERROR(IF(O35=0,"Out of Stock",IF(O35<=P35,"Low Stock","In Stock")),"Out of Stock")) -> In Stock | S35: Pharmaceuticals | T35: =SUMIF('Daily Sales Entry'!$E:$E,S35,'Daily Sales Entry'!$G:$G) -> 0
B36: 6 CELEBRATION CAKE | C36: =SUMIF('Daily Sales Entry'!$D:$D,B36,'Daily Sales Entry'!$G:$G) -> 0 | I36: ='Daily Sales Entry'!B14 -> 5 | J36: ='Daily Sales Entry'!D14 -> Beef Roll | K36: ='Daily Sales Entry'!G14 -> 5 | L36: ='Daily Sales Entry'!J14 -> 3500 | N36: Pet Lucozade Boost | O36: =IF(N36="","",IFERROR(VLOOKUP(N36,Inventory!$B:$R,12,FALSE),0)) -> 65 | P36: =IF(N36="","",IFERROR(VLOOKUP(N36,Inventory!$B:$R,15,FALSE),0)) -> 10 | Q36: =IF(N36="","",IFERROR(IF(O36=0,"Out of Stock",IF(O36<=P36,"Low Stock","In Stock")),"Out of Stock")) -> In Stock | S36: Stationery | T36: =SUMIF('Daily Sales Entry'!$E:$E,S36,'Daily Sales Entry'!$G:$G) -> 0
B37: MoinMoin Elewe | C37: =SUMIF('Daily Sales Entry'!$D:$D,B37,'Daily Sales Entry'!$G:$G) -> 0 | I37: ='Daily Sales Entry'!B15 -> 6 | J37: ='Daily Sales Entry'!D15 -> Pet Lucozade Boost | K37: ='Daily Sales Entry'!G15 -> 5 | L37: ='Daily Sales Entry'!J15 -> 100000 | N37: Eva Water 0.75Cl | O37: =IF(N37="","",IFERROR(VLOOKUP(N37,Inventory!$B:$R,12,FALSE),0)) -> 63 | P37: =IF(N37="","",IFERROR(VLOOKUP(N37,Inventory!$B:$R,15,FALSE),0)) -> 10 | Q37: =IF(N37="","",IFERROR(IF(O37=0,"Out of Stock",IF(O37<=P37,"Low Stock","In Stock")),"Out of Stock")) -> In Stock | S37: Household items | T37: =SUMIF('Daily Sales Entry'!$E:$E,S37,'Daily Sales Entry'!$G:$G) -> 0
B38: Sunshine Loaf-Sliced | C38: =SUMIF('Daily Sales Entry'!$D:$D,B38,'Daily Sales Entry'!$G:$G) -> 0 | I38: ='Daily Sales Entry'!B16 -> 6 | J38: ='Daily Sales Entry'!D16 -> Eva Water 0.75Cl | K38: ='Daily Sales Entry'!G16 -> 7 | L38: ='Daily Sales Entry'!J16 -> 59500 | N38: Ponmo | O38: =IF(N38="","",IFERROR(VLOOKUP(N38,Inventory!$B:$R,12,FALSE),0)) -> 0 | P38: =IF(N38="","",IFERROR(VLOOKUP(N38,Inventory!$B:$R,15,FALSE),0)) -> 0 | Q38: =IF(N38="","",IFERROR(IF(O38=0,"Out of Stock",IF(O38<=P38,"Low Stock","In Stock")),"Out of Stock")) -> Out of Stock | S38: Cakes | T38: =SUMIF('Daily Sales Entry'!$E:$E,S38,'Daily Sales Entry'!$G:$G) -> 0
B39: Fruit Bread Loaf | C39: =SUMIF('Daily Sales Entry'!$D:$D,B39,'Daily Sales Entry'!$G:$G) -> 0 | I39: ='Daily Sales Entry'!B17 -> 6 | J39: ='Daily Sales Entry'!D17 -> Beef | K39: ='Daily Sales Entry'!G17 -> 5 | L39: ='Daily Sales Entry'!J17 -> 5000 | N39: Meat Pie | O39: =IF(N39="","",IFERROR(VLOOKUP(N39,Inventory!$B:$R,12,FALSE),0)) -> 47 | P39: =IF(N39="","",IFERROR(VLOOKUP(N39,Inventory!$B:$R,15,FALSE),0)) -> 20 | Q39: =IF(N39="","",IFERROR(IF(O39=0,"Out of Stock",IF(O39<=P39,"Low Stock","In Stock")),"Out of Stock")) -> In Stock | S39: Soup | T39: =SUMIF('Daily Sales Entry'!$E:$E,S39,'Daily Sales Entry'!$G:$G) -> 0
B40: Efo-Riro Soup 2 | C40: =SUMIF('Daily Sales Entry'!$D:$D,B40,'Daily Sales Entry'!$G:$G) -> 0 | I40: ='Daily Sales Entry'!B18 -> 6 | J40: ='Daily Sales Entry'!D18 -> Shaki | K40: ='Daily Sales Entry'!G18 -> 8 | L40: ='Daily Sales Entry'!J18 -> 9600 | N40: Chicken Pie | O40: =IF(N40="","",IFERROR(VLOOKUP(N40,Inventory!$B:$R,12,FALSE),0)) -> 43 | P40: =IF(N40="","",IFERROR(VLOOKUP(N40,Inventory!$B:$R,15,FALSE),0)) -> 20 | Q40: =IF(N40="","",IFERROR(IF(O40=0,"Out of Stock",IF(O40<=P40,"Low Stock","In Stock")),"Out of Stock")) -> In Stock
B41: Egusi Soup 2 | C41: =SUMIF('Daily Sales Entry'!$D:$D,B41,'Daily Sales Entry'!$G:$G) -> 0 | I41: ='Daily Sales Entry'!B19 -> 7 | J41: ='Daily Sales Entry'!D19 -> Lucozade Sport Pet 50cl | K41: ='Daily Sales Entry'!G19 -> 5 | L41: ='Daily Sales Entry'!J19 -> 7500 | N41: Beef Roll | O41: =IF(N41="","",IFERROR(VLOOKUP(N41,Inventory!$B:$R,12,FALSE),0)) -> 45 | P41: =IF(N41="","",IFERROR(VLOOKUP(N41,Inventory!$B:$R,15,FALSE),0)) -> 20 | Q41: =IF(N41="","",IFERROR(IF(O41=0,"Out of Stock",IF(O41<=P41,"Low Stock","In Stock")),"Out of Stock")) -> In Stock
B42: Tantis Fish Ola | C42: =SUMIF('Daily Sales Entry'!$D:$D,B42,'Daily Sales Entry'!$G:$G) -> 0 | I42: ='Daily Sales Entry'!B20 -> 7 | J42: ='Daily Sales Entry'!D20 -> FAB Energy Drinks | K42: ='Daily Sales Entry'!G20 -> 5 | L42: ='Daily Sales Entry'!J20 -> 7500 | N42: Tanta Roll | O42: =IF(N42="","",IFERROR(VLOOKUP(N42,Inventory!$B:$R,12,FALSE),0)) -> 0 | P42: =IF(N42="","",IFERROR(VLOOKUP(N42,Inventory!$B:$R,15,FALSE),0)) -> 0 | Q42: =IF(N42="","",IFERROR(IF(O42=0,"Out of Stock",IF(O42<=P42,"Low Stock","In Stock")),"Out of Stock")) -> Out of Stock
B43: Ponmo | C43: =SUMIF('Daily Sales Entry'!$D:$D,B43,'Daily Sales Entry'!$G:$G) -> 0 | I43: ='Daily Sales Entry'!B21 -> 7 | J43: ='Daily Sales Entry'!D21 -> Chin Chin 224 gms | K43: ='Daily Sales Entry'!G21 -> 5 | L43: ='Daily Sales Entry'!J21 -> 7500 | N43: Doughnut | O43: =IF(N43="","",IFERROR(VLOOKUP(N43,Inventory!$B:$R,12,FALSE),0)) -> 0 | P43: =IF(N43="","",IFERROR(VLOOKUP(N43,Inventory!$B:$R,15,FALSE),0)) -> 0 | Q43: =IF(N43="","",IFERROR(IF(O43=0,"Out of Stock",IF(O43<=P43,"Low Stock","In Stock")),"Out of Stock")) -> Out of Stock
B44: TURKEY (L) | C44: =SUMIF('Daily Sales Entry'!$D:$D,B44,'Daily Sales Entry'!$G:$G) -> 0 | I44: ='Daily Sales Entry'!B22 -> 7 | J44: ='Daily Sales Entry'!D22 -> Malta Guinness 33cl Cans | K44: ='Daily Sales Entry'!G22 -> 5 | L44: ='Daily Sales Entry'!J22 -> 7500 | N44: Beef Burger | O44: =IF(N44="","",IFERROR(VLOOKUP(N44,Inventory!$B:$R,12,FALSE),0)) -> 0 | P44: =IF(N44="","",IFERROR(VLOOKUP(N44,Inventory!$B:$R,15,FALSE),0)) -> 0 | Q44: =IF(N44="","",IFERROR(IF(O44=0,"Out of Stock",IF(O44<=P44,"Low Stock","In Stock")),"Out of Stock")) -> Out of Stock
B45: Jollof Rice New | C45: =SUMIF('Daily Sales Entry'!$D:$D,B45,'Daily Sales Entry'!$G:$G) -> 0 | I45: ='Daily Sales Entry'!B23 -> 0 | J45: ='Daily Sales Entry'!D23 -> 0 | K45: ='Daily Sales Entry'!G23 -> 0 | L45: ='Daily Sales Entry'!J23 -> 0 | N45: Scotch Egg | O45: =IF(N45="","",IFERROR(VLOOKUP(N45,Inventory!$B:$R,12,FALSE),0)) -> 0 | P45: =IF(N45="","",IFERROR(VLOOKUP(N45,Inventory!$B:$R,15,FALSE),0)) -> 0 | Q45: =IF(N45="","",IFERROR(IF(O45=0,"Out of Stock",IF(O45<=P45,"Low Stock","In Stock")),"Out of Stock")) -> Out of Stock
B46: Fried Rice New | C46: =SUMIF('Daily Sales Entry'!$D:$D,B46,'Daily Sales Entry'!$G:$G) -> 0 | I46: ='Daily Sales Entry'!B24 -> 0 | J46: ='Daily Sales Entry'!D24 -> 0 | K46: ='Daily Sales Entry'!G24 -> 0 | L46: ='Daily Sales Entry'!J24 -> 0 | N46: Ppg Chicken | O46: =IF(N46="","",IFERROR(VLOOKUP(N46,Inventory!$B:$R,12,FALSE),0)) -> 0 | P46: =IF(N46="","",IFERROR(VLOOKUP(N46,Inventory!$B:$R,15,FALSE),0)) -> 0 | Q46: =IF(N46="","",IFERROR(IF(O46=0,"Out of Stock",IF(O46<=P46,"Low Stock","In Stock")),"Out of Stock")) -> Out of Stock
B47: Efo-Riro Soup New | C47: =SUMIF('Daily Sales Entry'!$D:$D,B47,'Daily Sales Entry'!$G:$G) -> 0 | I47: ='Daily Sales Entry'!B25 -> 0 | J47: ='Daily Sales Entry'!D25 -> 0 | K47: ='Daily Sales Entry'!G25 -> 0 | L47: ='Daily Sales Entry'!J25 -> 0 | N47: Roasted Chicken | O47: =IF(N47="","",IFERROR(VLOOKUP(N47,Inventory!$B:$R,12,FALSE),0)) -> 0 | P47: =IF(N47="","",IFERROR(VLOOKUP(N47,Inventory!$B:$R,15,FALSE),0)) -> 0 | Q47: =IF(N47="","",IFERROR(IF(O47=0,"Out of Stock",IF(O47<=P47,"Low Stock","In Stock")),"Out of Stock")) -> Out of Stock
B48: Egusi Soup New | C48: =SUMIF('Daily Sales Entry'!$D:$D,B48,'Daily Sales Entry'!$G:$G) -> 0 | I48: ='Daily Sales Entry'!B26 -> 0 | J48: ='Daily Sales Entry'!D26 -> 0 | K48: ='Daily Sales Entry'!G26 -> 0 | L48: ='Daily Sales Entry'!J26 -> 0 | N48: Chicken Salad | O48: =IF(N48="","",IFERROR(VLOOKUP(N48,Inventory!$B:$R,12,FALSE),0)) -> 0 | P48: =IF(N48="","",IFERROR(VLOOKUP(N48,Inventory!$B:$R,15,FALSE),0)) -> 0 | Q48: =IF(N48="","",IFERROR(IF(O48=0,"Out of Stock",IF(O48<=P48,"Low Stock","In Stock")),"Out of Stock")) -> Out of Stock
B49: Spaghetti Bolognaise New | C49: =SUMIF('Daily Sales Entry'!$D:$D,B49,'Daily Sales Entry'!$G:$G) -> 0 | I49: ='Daily Sales Entry'!B27 -> 0 | J49: ='Daily Sales Entry'!D27 -> 0 | K49: ='Daily Sales Entry'!G27 -> 0 | L49: ='Daily Sales Entry'!J27 -> 0 | N49: Vegetable Salad | O49: =IF(N49="","",IFERROR(VLOOKUP(N49,Inventory!$B:$R,12,FALSE),0)) -> 0 | P49: =IF(N49="","",IFERROR(VLOOKUP(N49,Inventory!$B:$R,15,FALSE),0)) -> 0 | Q49: =IF(N49="","",IFERROR(IF(O49=0,"Out of Stock",IF(O49<=P49,"Low Stock","In Stock")),"Out of Stock")) -> Out of Stock
B50: Ofada Sauce New | C50: =SUMIF('Daily Sales Entry'!$D:$D,B50,'Daily Sales Entry'!$G:$G) -> 0 | I50: ='Daily Sales Entry'!B28 -> 0 | J50: ='Daily Sales Entry'!D28 -> 0 | K50: ='Daily Sales Entry'!G28 -> 0 | L50: ='Daily Sales Entry'!J28 -> 0 | N50: Scramble Egg | O50: =IF(N50="","",IFERROR(VLOOKUP(N50,Inventory!$B:$R,12,FALSE),0)) -> 0 | P50: =IF(N50="","",IFERROR(VLOOKUP(N50,Inventory!$B:$R,15,FALSE),0)) -> 0 | Q50: =IF(N50="","",IFERROR(IF(O50=0,"Out of Stock",IF(O50<=P50,"Low Stock","In Stock")),"Out of Stock")) -> Out of Stock
B51: Vegetable Salad New | C51: =SUMIF('Daily Sales Entry'!$D:$D,B51,'Daily Sales Entry'!$G:$G) -> 0 | I51: ='Daily Sales Entry'!B29 -> 0 | J51: ='Daily Sales Entry'!D29 -> 0 | K51: ='Daily Sales Entry'!G29 -> 0 | L51: ='Daily Sales Entry'!J29 -> 0 | N51: Cup Cake | O51: =IF(N51="","",IFERROR(VLOOKUP(N51,Inventory!$B:$R,12,FALSE),0)) -> 0 | P51: =IF(N51="","",IFERROR(VLOOKUP(N51,Inventory!$B:$R,15,FALSE),0)) -> 0 | Q51: =IF(N51="","",IFERROR(IF(O51=0,"Out of Stock",IF(O51<=P51,"Low Stock","In Stock")),"Out of Stock")) -> Out of Stock
... B54: T/Away Pack (Africana) | C54: =SUMIF('Daily Sales Entry'!$D:$D,B54,'Daily Sales Entry'!$G:$G) -> 0 | I54: ='Daily Sales Entry'!B32 -> 0 | J54: ='Daily Sales Entry'!D32 -> 0 | K54: ='Daily Sales Entry'!G32 -> 0 | L54: ='Daily Sales Entry'!J32 -> 0 | N54: 8 CELEBRATION CAKE | O54: =IF(N54="","",IFERROR(VLOOKUP(N54,Inventory!$B:$R,12,FALSE),0)) -> 0 | P54: =IF(N54="","",IFERROR(VLOOKUP(N54,Inventory!$B:$R,15,FALSE),0)) -> 0 | Q54: =IF(N54="","",IFERROR(IF(O54=0,"Out of Stock",IF(O54<=P54,"Low Stock","In Stock")),"Out of Stock")) -> Out of Stock
B55: Ragolis Water .75 Cl | C55: =SUMIF('Daily Sales Entry'!$D:$D,B55,'Daily Sales Entry'!$G:$G) -> 0 | N55: 6 CELEBRATION CAKE | O55: =IF(N55="","",IFERROR(VLOOKUP(N55,Inventory!$B:$R,12,FALSE),0)) -> 0 | P55: =IF(N55="","",IFERROR(VLOOKUP(N55,Inventory!$B:$R,15,FALSE),0)) -> 0 | Q55: =IF(N55="","",IFERROR(IF(O55=0,"Out of Stock",IF(O55<=P55,"Low Stock","In Stock")),"Out of Stock")) -> Out of Stock
B56: Coke Can 33Cl | C56: =SUMIF('Daily Sales Entry'!$D:$D,B56,'Daily Sales Entry'!$G:$G) -> 0 | N56: MoinMoin Elewe | O56: =IF(N56="","",IFERROR(VLOOKUP(N56,Inventory!$B:$R,12,FALSE),0)) -> 0 | P56: =IF(N56="","",IFERROR(VLOOKUP(N56,Inventory!$B:$R,15,FALSE),0)) -> 0 | Q56: =IF(N56="","",IFERROR(IF(O56=0,"Out of Stock",IF(O56<=P56,"Low Stock","In Stock")),"Out of Stock")) -> Out of Stock
B57: Schweppes Can 33Cl | C57: =SUMIF('Daily Sales Entry'!$D:$D,B57,'Daily Sales Entry'!$G:$G) -> 0 | N57: Sunshine Loaf-Sliced | O57: =IF(N57="","",IFERROR(VLOOKUP(N57,Inventory!$B:$R,12,FALSE),0)) -> 0 | P57: =IF(N57="","",IFERROR(VLOOKUP(N57,Inventory!$B:$R,15,FALSE),0)) -> 0 | Q57: =IF(N57="","",IFERROR(IF(O57=0,"Out of Stock",IF(O57<=P57,"Low Stock","In Stock")),"Out of Stock")) -> Out of Stock
B58: Chivita Orange 1Ltr | C58: =SUMIF('Daily Sales Entry'!$D:$D,B58,'Daily Sales Entry'!$G:$G) -> 0 | N58: Fruit Bread Loaf | O58: =IF(N58="","",IFERROR(VLOOKUP(N58,Inventory!$B:$R,12,FALSE),0)) -> 0 | P58: =IF(N58="","",IFERROR(VLOOKUP(N58,Inventory!$B:$R,15,FALSE),0)) -> 0 | Q58: =IF(N58="","",IFERROR(IF(O58=0,"Out of Stock",IF(O58<=P58,"Low Stock","In Stock")),"Out of Stock")) -> Out of Stock
B59: Five Alive Orange 1 Ltr | C59: =SUMIF('Daily Sales Entry'!$D:$D,B59,'Daily Sales Entry'!$G:$G) -> 0 | N59: Efo-Riro Soup 2 | O59: =IF(N59="","",IFERROR(VLOOKUP(N59,Inventory!$B:$R,12,FALSE),0)) -> 0 | P59: =IF(N59="","",IFERROR(VLOOKUP(N59,Inventory!$B:$R,15,FALSE),0)) -> 0 | Q59: =IF(N59="","",IFERROR(IF(O59=0,"Out of Stock",IF(O59<=P59,"Low Stock","In Stock")),"Out of Stock")) -> Out of Stock
B60: Chi Exotic Orange 1 Ltr | C60: =SUMIF('Daily Sales Entry'!$D:$D,B60,'Daily Sales Entry'!$G:$G) -> 0 | N60: Egusi Soup 2 | O60: =IF(N60="","",IFERROR(VLOOKUP(N60,Inventory!$B:$R,12,FALSE),0)) -> 0 | P60: =IF(N60="","",IFERROR(VLOOKUP(N60,Inventory!$B:$R,15,FALSE),0)) -> 0 | Q60: =IF(N60="","",IFERROR(IF(O60=0,"Out of Stock",IF(O60<=P60,"Low Stock","In Stock")),"Out of Stock")) -> Out of Stock
B61: Coke Pet 50Cl | C61: =SUMIF('Daily Sales Entry'!$D:$D,B61,'Daily Sales Entry'!$G:$G) -> 0 | N61: Tantis Fish Ola | O61: =IF(N61="","",IFERROR(VLOOKUP(N61,Inventory!$B:$R,12,FALSE),0)) -> 0 | P61: =IF(N61="","",IFERROR(VLOOKUP(N61,Inventory!$B:$R,15,FALSE),0)) -> 0 | Q61: =IF(N61="","",IFERROR(IF(O61=0,"Out of Stock",IF(O61<=P61,"Low Stock","In Stock")),"Out of Stock")) -> Out of Stock
B62: Fanta PET 50Cl | C62: =SUMIF('Daily Sales Entry'!$D:$D,B62,'Daily Sales Entry'!$G:$G) -> 0 | N62: TURKEY (L) | O62: =IF(N62="","",IFERROR(VLOOKUP(N62,Inventory!$B:$R,12,FALSE),0)) -> 0 | P62: =IF(N62="","",IFERROR(VLOOKUP(N62,Inventory!$B:$R,15,FALSE),0)) -> 0 | Q62: =IF(N62="","",IFERROR(IF(O62=0,"Out of Stock",IF(O62<=P62,"Low Stock","In Stock")),"Out of Stock")) -> Out of Stock
B63: Pepsi PET 50Cl | C63: =SUMIF('Daily Sales Entry'!$D:$D,B63,'Daily Sales Entry'!$G:$G) -> 0 | N63: Jollof Rice New | O63: =IF(N63="","",IFERROR(VLOOKUP(N63,Inventory!$B:$R,12,FALSE),0)) -> 0 | P63: =IF(N63="","",IFERROR(VLOOKUP(N63,Inventory!$B:$R,15,FALSE),0)) -> 0 | Q63: =IF(N63="","",IFERROR(IF(O63=0,"Out of Stock",IF(O63<=P63,"Low Stock","In Stock")),"Out of Stock")) -> Out of Stock
B64: Limca PET 50Cl | C64: =SUMIF('Daily Sales Entry'!$D:$D,B64,'Daily Sales Entry'!$G:$G) -> 0 | N64: Fried Rice New | O64: =IF(N64="","",IFERROR(VLOOKUP(N64,Inventory!$B:$R,12,FALSE),0)) -> 0 | P64: =IF(N64="","",IFERROR(VLOOKUP(N64,Inventory!$B:$R,15,FALSE),0)) -> 0 | Q64: =IF(N64="","",IFERROR(IF(O64=0,"Out of Stock",IF(O64<=P64,"Low Stock","In Stock")),"Out of Stock")) -> Out of Stock
B65: Vitamilk 300Ml | C65: =SUMIF('Daily Sales Entry'!$D:$D,B65,'Daily Sales Entry'!$G:$G) -> 0 | N65: Efo-Riro Soup New | O65: =IF(N65="","",IFERROR(VLOOKUP(N65,Inventory!$B:$R,12,FALSE),0)) -> 0 | P65: =IF(N65="","",IFERROR(VLOOKUP(N65,Inventory!$B:$R,15,FALSE),0)) -> 0 | Q65: =IF(N65="","",IFERROR(IF(O65=0,"Out of Stock",IF(O65<=P65,"Low Stock","In Stock")),"Out of Stock")) -> Out of Stock
B66: Hollandia Yoghurt Van 1 Ltr | C66: =SUMIF('Daily Sales Entry'!$D:$D,B66,'Daily Sales Entry'!$G:$G) -> 0 | N66: Egusi Soup New | O66: =IF(N66="","",IFERROR(VLOOKUP(N66,Inventory!$B:$R,12,FALSE),0)) -> 0 | P66: =IF(N66="","",IFERROR(VLOOKUP(N66,Inventory!$B:$R,15,FALSE),0)) -> 0 | Q66: =IF(N66="","",IFERROR(IF(O66=0,"Out of Stock",IF(O66<=P66,"Low Stock","In Stock")),"Out of Stock")) -> Out of Stock
... B87: Lucozade Sport Pet 50cl | C87: =SUMIF('Daily Sales Entry'!$D:$D,B87,'Daily Sales Entry'!$G:$G) -> 5 | N87: Sprite PET 50Cl | O87: =IF(N87="","",IFERROR(VLOOKUP(N87,Inventory!$B:$R,12,FALSE),0)) -> 0 | P87: =IF(N87="","",IFERROR(VLOOKUP(N87,Inventory!$B:$R,15,FALSE),0)) -> 0 | Q87: =IF(N87="","",IFERROR(IF(O87=0,"Out of Stock",IF(O87<=P87,"Low Stock","In Stock")),"Out of Stock")) -> Out of Stock
N88: 1 Litre- Vanilla | O88: =IF(N88="","",IFERROR(VLOOKUP(N88,Inventory!$B:$R,12,FALSE),0)) -> 0 | P88: =IF(N88="","",IFERROR(VLOOKUP(N88,Inventory!$B:$R,15,FALSE),0)) -> 0 | Q88: =IF(N88="","",IFERROR(IF(O88=0,"Out of Stock",IF(O88<=P88,"Low Stock","In Stock")),"Out of Stock")) -> Out of Stock
N89: 1 Litre- Peanut | O89: =IF(N89="","",IFERROR(VLOOKUP(N89,Inventory!$B:$R,12,FALSE),0)) -> 0 | P89: =IF(N89="","",IFERROR(VLOOKUP(N89,Inventory!$B:$R,15,FALSE),0)) -> 0 | Q89: =IF(N89="","",IFERROR(IF(O89=0,"Out of Stock",IF(O89<=P89,"Low Stock","In Stock")),"Out of Stock")) -> Out of Stock
N90: Double Pleasure -Vanilla/Straw | O90: =IF(N90="","",IFERROR(VLOOKUP(N90,Inventory!$B:$R,12,FALSE),0)) -> 0 | P90: =IF(N90="","",IFERROR(VLOOKUP(N90,Inventory!$B:$R,15,FALSE),0)) -> 0 | Q90: =IF(N90="","",IFERROR(IF(O90=0,"Out of Stock",IF(O90<=P90,"Low Stock","In Stock")),"Out of Stock")) -> Out of Stock
N91: Double Pleasure -Vanilla/Banan | O91: =IF(N91="","",IFERROR(VLOOKUP(N91,Inventory!$B:$R,12,FALSE),0)) -> 0 | P91: =IF(N91="","",IFERROR(VLOOKUP(N91,Inventory!$B:$R,15,FALSE),0)) -> 0 | Q91: =IF(N91="","",IFERROR(IF(O91=0,"Out of Stock",IF(O91<=P91,"Low Stock","In Stock")),"Out of Stock")) -> Out of Stock
N92: Moi Moi -Vanilla | O92: =IF(N92="","",IFERROR(VLOOKUP(N92,Inventory!$B:$R,12,FALSE),0)) -> 0 | P92: =IF(N92="","",IFERROR(VLOOKUP(N92,Inventory!$B:$R,15,FALSE),0)) -> 0 | Q92: =IF(N92="","",IFERROR(IF(O92=0,"Out of Stock",IF(O92<=P92,"Low Stock","In Stock")),"Out of Stock")) -> Out of Stock
N93: Moi Moi -Strawberry | O93: =IF(N93="","",IFERROR(VLOOKUP(N93,Inventory!$B:$R,12,FALSE),0)) -> 0 | P93: =IF(N93="","",IFERROR(VLOOKUP(N93,Inventory!$B:$R,15,FALSE),0)) -> 0 | Q93: =IF(N93="","",IFERROR(IF(O93=0,"Out of Stock",IF(O93<=P93,"Low Stock","In Stock")),"Out of Stock")) -> Out of Stock
N94: Moi Moi -Banana | O94: =IF(N94="","",IFERROR(VLOOKUP(N94,Inventory!$B:$R,12,FALSE),0)) -> 0 | P94: =IF(N94="","",IFERROR(VLOOKUP(N94,Inventory!$B:$R,15,FALSE),0)) -> 0 | Q94: =IF(N94="","",IFERROR(IF(O94=0,"Out of Stock",IF(O94<=P94,"Low Stock","In Stock")),"Out of Stock")) -> Out of Stock
N95: Moi Moi -Peanut | O95: =IF(N95="","",IFERROR(VLOOKUP(N95,Inventory!$B:$R,12,FALSE),0)) -> 0 | P95: =IF(N95="","",IFERROR(VLOOKUP(N95,Inventory!$B:$R,15,FALSE),0)) -> 0 | Q95: =IF(N95="","",IFERROR(IF(O95=0,"Out of Stock",IF(O95<=P95,"Low Stock","In Stock")),"Out of Stock")) -> Out of Stock
N96: Santana -Vanilla | O96: =IF(N96="","",IFERROR(VLOOKUP(N96,Inventory!$B:$R,12,FALSE),0)) -> 0 | P96: =IF(N96="","",IFERROR(VLOOKUP(N96,Inventory!$B:$R,15,FALSE),0)) -> 0 | Q96: =IF(N96="","",IFERROR(IF(O96=0,"Out of Stock",IF(O96<=P96,"Low Stock","In Stock")),"Out of Stock")) -> Out of Stock
N97: Santana -Peanut | O97: =IF(N97="","",IFERROR(VLOOKUP(N97,Inventory!$B:$R,12,FALSE),0)) -> 0 | P97: =IF(N97="","",IFERROR(VLOOKUP(N97,Inventory!$B:$R,15,FALSE),0)) -> 0 | Q97: =IF(N97="","",IFERROR(IF(O97=0,"Out of Stock",IF(O97<=P97,"Low Stock","In Stock")),"Out of Stock")) -> Out of Stock
N98: Chivita Active 1Ltr | O98: =IF(N98="","",IFERROR(VLOOKUP(N98,Inventory!$B:$R,12,FALSE),0)) -> 0 | P98: =IF(N98="","",IFERROR(VLOOKUP(N98,Inventory!$B:$R,15,FALSE),0)) -> 0 | Q98: =IF(N98="","",IFERROR(IF(O98=0,"Out of Stock",IF(O98<=P98,"Low Stock","In Stock")),"Out of Stock")) -> Out of Stock
D99: Last Updated : 13 August, 2026. | N99: Malta Guinness 33cl Cans | O99: =IF(N99="","",IFERROR(VLOOKUP(N99,Inventory!$B:$R,12,FALSE),0)) -> 45 | P99: =IF(N99="","",IFERROR(VLOOKUP(N99,Inventory!$B:$R,15,FALSE),0)) -> 20 | Q99: =IF(N99="","",IFERROR(IF(O99=0,"Out of Stock",IF(O99<=P99,"Low Stock","In Stock")),"Out of Stock")) -> In Stock
N100: Chin Chin 224 gms | O100: =IF(N100="","",IFERROR(VLOOKUP(N100,Inventory!$B:$R,12,FALSE),0)) -> 45 | P100: =IF(N100="","",IFERROR(VLOOKUP(N100,Inventory!$B:$R,15,FALSE),0)) -> 20 | Q100: =IF(N100="","",IFERROR(IF(O100=0,"Out of Stock",IF(O100<=P100,"Low Stock","In Stock")),"Out of Stock")) -> In Stock
D103: Developed by Olamilekan Analytics. Version 2.0

Sheet Product Master
A1: Product ID | B1: Product Name | C1: Category | D1: Unit of Measure | E1: Cost Price | F1: Selling Price | G1: Profit per Unit | H1: Reorder Level | I1: Status
A2: P0001 | B2: Beef | C2: Food | D2: Piece | E2: 700 | F2: 1000 | G2: =Table1[[#This Row],[Selling Price]]-Table1[[#This Row],[Cost Price]] -> 300 | H2: 20 | I2: Active
A3: P0002 | B3: Shaki | C3: Food | D3: Piece | E3: 900 | F3: 1200 | G3: =Table1[[#This Row],[Selling Price]]-Table1[[#This Row],[Cost Price]] -> 300 | H3: 20 | I3: Active
A4: P0003 | B4: Cow leg | C4: Food | D4: Piece | E4: 1200 | F4: 1500 | G4: =Table1[[#This Row],[Selling Price]]-Table1[[#This Row],[Cost Price]] -> 300 | H4: 20 | I4: Active
A5: P0004 | B5: Semovita | C5: Food | D5: Piece | E5: 400 | F5: 700 | G5: =Table1[[#This Row],[Selling Price]]-Table1[[#This Row],[Cost Price]] -> 300 | H5: 20 | I5: Active
A6: P0005 | B6: Eba | C6: Food | D6: Piece | E6: 200 | F6: 500 | G6: =Table1[[#This Row],[Selling Price]]-Table1[[#This Row],[Cost Price]] -> 300 | H6: 20 | I6: Active
A7: P0006 | B7: Moin Moin | C7: Food | D7: Piece | E7: 500 | F7: 800 | G7: =Table1[[#This Row],[Selling Price]]-Table1[[#This Row],[Cost Price]] -> 300 | H7: 20 | I7: Active
A8: P0007 | B8: Meat Pie | C8: Snacks | D8: Piece | E8: 500 | F8: 900 | G8: =Table1[[#This Row],[Selling Price]]-Table1[[#This Row],[Cost Price]] -> 400 | H8: 20 | I8: Active
A9: P0008 | B9: Chicken Pie | C9: Snacks | D9: Piece | E9: 700 | F9: 1000 | G9: =Table1[[#This Row],[Selling Price]]-Table1[[#This Row],[Cost Price]] -> 300 | H9: 20 | I9: Active
A10: P0009 | B10: Beef Roll | C10: Snacks | D10: Piece | E10: 400 | F10: 700 | G10: =Table1[[#This Row],[Selling Price]]-Table1[[#This Row],[Cost Price]] -> 300 | H10: 20 | I10: Active
A11: P0010 | B11: Pet Lucozade Boost | C11: Drinks | D11: Pack | E11: 17000 | F11: 20000 | G11: =Table1[[#This Row],[Selling Price]]-Table1[[#This Row],[Cost Price]] -> 3000 | H11: 10 | I11: Active
A12: P0011 | B12: Eva Water 0.75Cl | C12: Drinks | D12: Pack | E12: 5000 | F12: 8500 | G12: =Table1[[#This Row],[Selling Price]]-Table1[[#This Row],[Cost Price]] -> 3500 | H12: 10 | I12: Active
A13: P0012 | B13: Lucozade Sport Pet 50cl | C13: Drinks | D13: Pack | E13: 900 | F13: 1500 | G13: =Table1[[#This Row],[Selling Price]]-Table1[[#This Row],[Cost Price]] -> 600 | H13: 20 | I13: Active
... A16: P0015 | B16: Malta Guinness 33cl Cans | C16: Drinks | D16: Pack | E16: 900 | F16: 1500 | G16: =Table1[[#This Row],[Selling Price]]-Table1[[#This Row],[Cost Price]] -> 600 | H16: 20 | I16: Active
G17: =Table1[[#This Row],[Selling Price]]-Table1[[#This Row],[Cost Price]] -> 0 | I17: Inactive
G18: =Table1[[#This Row],[Selling Price]]-Table1[[#This Row],[Cost Price]] -> 0 | I18: Inactive
G19: =Table1[[#This Row],[Selling Price]]-Table1[[#This Row],[Cost Price]] -> 0 | I19: Inactive
G20: =Table1[[#This Row],[Selling Price]]-Table1[[#This Row],[Cost Price]] -> 0 | I20: Inactive
G21: =Table1[[#This Row],[Selling Price]]-Table1[[#This Row],[Cost Price]] -> 0 | I21: Inactive
G22: =Table1[[#This Row],[Selling Price]]-Table1[[#This Row],[Cost Price]] -> 0 | I22: Inactive
G23: =Table1[[#This Row],[Selling Price]]-Table1[[#This Row],[Cost Price]] -> 0 | I23: Inactive
G24: =Table1[[#This Row],[Selling Price]]-Table1[[#This Row],[Cost Price]] -> 0 | I24: Inactive
G25: =Table1[[#This Row],[Selling Price]]-Table1[[#This Row],[Cost Price]] -> 0 | I25: Inactive
G26: =Table1[[#This Row],[Selling Price]]-Table1[[#This Row],[Cost Price]] -> 0 | I26: Inactive
G27: =Table1[[#This Row],[Selling Price]]-Table1[[#This Row],[Cost Price]] -> 0 | I27: Inactive
G28: =Table1[[#This Row],[Selling Price]]-Table1[[#This Row],[Cost Price]] -> 0 | I28: Inactive
... G1028: =Table1[[#This Row],[Selling Price]]-Table1[[#This Row],[Cost Price]] -> 0 | I1028: Inactive

Sheet Daily Sales Entry
A1: DATE | B1: Sales ID | C1: Cashier | D1: Product Name | E1: Category | F1: Unit | G1: QTY SOLD | H1: Selling Price | I1: Cost Price | J1: Total Sales | K1: Discount | L1: Net Sales | M1: Profit
A2: 46252 | B2: 1 | C2: Cashier 1 | D2: Beef | E2: =IF(D2="","",VLOOKUP(D2,'Product Master'!$B:$C,2,FALSE)) -> Food | F2: =IF(D2="","",IFERROR(VLOOKUP(D2,'Product Master'!$B:$G,3,FALSE),"")) -> Piece | G2: 5 | H2: =IF(D2="","",VLOOKUP(D2,'Product Master'!$B:$F,5,FALSE)) -> 1000 | I2: =IFERROR(VLOOKUP(D2,'Product Master'!B:E,4,FALSE),0) -> 700 | J2: =IFERROR(Table3[[#This Row],[QTY SOLD]]*Table3[[#This Row],[Selling Price]],0) -> 5000 | L2: =Table3[[#This Row],[Total Sales]]-Table3[[#This Row],[Discount]] -> 5000 | M2: =Table3[[#This Row],[Net Sales]]-Table3[[#This Row],[Cost Price]]*Table3[[#This Row],[QTY SOLD]] -> 1500
A3: 46252 | B3: 1 | C3: Cashier 1 | D3: Shaki | E3: =IF(D3="","",VLOOKUP(D3,'Product Master'!$B:$C,2,FALSE)) -> Food | F3: =IF(D3="","",IFERROR(VLOOKUP(D3,'Product Master'!$B:$G,3,FALSE),"")) -> Piece | G3: 4 | H3: =IF(D3="","",VLOOKUP(D3,'Product Master'!$B:$F,5,FALSE)) -> 1200 | I3: =IFERROR(VLOOKUP(D3,'Product Master'!B:E,4,FALSE),0) -> 900 | J3: =IFERROR(Table3[[#This Row],[QTY SOLD]]*Table3[[#This Row],[Selling Price]],0) -> 4800 | L3: =Table3[[#This Row],[Total Sales]]-Table3[[#This Row],[Discount]] -> 4800 | M3: =Table3[[#This Row],[Net Sales]]-Table3[[#This Row],[Cost Price]]*Table3[[#This Row],[QTY SOLD]] -> 1200
A4: 46252 | B4: 1 | C4: Cashier 1 | D4: Cow leg | E4: =IF(D4="","",VLOOKUP(D4,'Product Master'!$B:$C,2,FALSE)) -> Food | F4: =IF(D4="","",IFERROR(VLOOKUP(D4,'Product Master'!$B:$G,3,FALSE),"")) -> Piece | G4: 4 | H4: =IF(D4="","",VLOOKUP(D4,'Product Master'!$B:$F,5,FALSE)) -> 1500 | I4: =IFERROR(VLOOKUP(D4,'Product Master'!B:E,4,FALSE),0) -> 1200 | J4: =IFERROR(Table3[[#This Row],[QTY SOLD]]*Table3[[#This Row],[Selling Price]],0) -> 6000 | L4: =Table3[[#This Row],[Total Sales]]-Table3[[#This Row],[Discount]] -> 6000 | M4: =Table3[[#This Row],[Net Sales]]-Table3[[#This Row],[Cost Price]]*Table3[[#This Row],[QTY SOLD]] -> 1200
A5: 46252 | B5: 1 | C5: Cashier 1 | D5: Semovita | E5: =IF(D5="","",VLOOKUP(D5,'Product Master'!$B:$C,2,FALSE)) -> Food | F5: =IF(D5="","",IFERROR(VLOOKUP(D5,'Product Master'!$B:$G,3,FALSE),"")) -> Piece | G5: 7 | H5: =IF(D5="","",VLOOKUP(D5,'Product Master'!$B:$F,5,FALSE)) -> 700 | I5: =IFERROR(VLOOKUP(D5,'Product Master'!B:E,4,FALSE),0) -> 400 | J5: =IFERROR(Table3[[#This Row],[QTY SOLD]]*Table3[[#This Row],[Selling Price]],0) -> 4900 | L5: =Table3[[#This Row],[Total Sales]]-Table3[[#This Row],[Discount]] -> 4900 | M5: =Table3[[#This Row],[Net Sales]]-Table3[[#This Row],[Cost Price]]*Table3[[#This Row],[QTY SOLD]] -> 2100
A6: 46252 | B6: 1 | C6: Cashier 1 | D6: Eba | E6: =IF(D6="","",VLOOKUP(D6,'Product Master'!$B:$C,2,FALSE)) -> Food | F6: =IF(D6="","",IFERROR(VLOOKUP(D6,'Product Master'!$B:$G,3,FALSE),"")) -> Piece | G6: 3 | H6: =IF(D6="","",VLOOKUP(D6,'Product Master'!$B:$F,5,FALSE)) -> 500 | I6: =IFERROR(VLOOKUP(D6,'Product Master'!B:E,4,FALSE),0) -> 200 | J6: =IFERROR(Table3[[#This Row],[QTY SOLD]]*Table3[[#This Row],[Selling Price]],0) -> 1500 | L6: =Table3[[#This Row],[Total Sales]]-Table3[[#This Row],[Discount]] -> 1500 | M6: =Table3[[#This Row],[Net Sales]]-Table3[[#This Row],[Cost Price]]*Table3[[#This Row],[QTY SOLD]] -> 900
A7: 46252 | B7: 1 | C7: Cashier 1 | D7: Moin Moin | E7: =IF(D7="","",VLOOKUP(D7,'Product Master'!$B:$C,2,FALSE)) -> Food | F7: =IF(D7="","",IFERROR(VLOOKUP(D7,'Product Master'!$B:$G,3,FALSE),"")) -> Piece | G7: 6 | H7: =IF(D7="","",VLOOKUP(D7,'Product Master'!$B:$F,5,FALSE)) -> 800 | I7: =IFERROR(VLOOKUP(D7,'Product Master'!B:E,4,FALSE),0) -> 500 | J7: =IFERROR(Table3[[#This Row],[QTY SOLD]]*Table3[[#This Row],[Selling Price]],0) -> 4800 | L7: =Table3[[#This Row],[Total Sales]]-Table3[[#This Row],[Discount]] -> 4800 | M7: =Table3[[#This Row],[Net Sales]]-Table3[[#This Row],[Cost Price]]*Table3[[#This Row],[QTY SOLD]] -> 1800
A8: =A7+1 -> 46253 | B8: 2 | C8: Cashier 3 | D8: Cow leg | E8: =IF(D8="","",VLOOKUP(D8,'Product Master'!$B:$C,2,FALSE)) -> Food | F8: =IF(D8="","",IFERROR(VLOOKUP(D8,'Product Master'!$B:$G,3,FALSE),"")) -> Piece | G8: 4 | H8: =IF(D8="","",VLOOKUP(D8,'Product Master'!$B:$F,5,FALSE)) -> 1500 | I8: =IFERROR(VLOOKUP(D8,'Product Master'!B:E,4,FALSE),0) -> 1200 | J8: =IFERROR(Table3[[#This Row],[QTY SOLD]]*Table3[[#This Row],[Selling Price]],0) -> 6000 | L8: =Table3[[#This Row],[Total Sales]]-Table3[[#This Row],[Discount]] -> 6000 | M8: =Table3[[#This Row],[Net Sales]]-Table3[[#This Row],[Cost Price]]*Table3[[#This Row],[QTY SOLD]] -> 1200
A9: 46251 | B9: 3 | C9: Cashier 5 | D9: Beef | E9: =IF(D9="","",VLOOKUP(D9,'Product Master'!$B:$C,2,FALSE)) -> Food | F9: =IF(D9="","",IFERROR(VLOOKUP(D9,'Product Master'!$B:$G,3,FALSE),"")) -> Piece | G9: 6 | H9: =IF(D9="","",VLOOKUP(D9,'Product Master'!$B:$F,5,FALSE)) -> 1000 | I9: =IFERROR(VLOOKUP(D9,'Product Master'!B:E,4,FALSE),0) -> 700 | J9: =IFERROR(Table3[[#This Row],[QTY SOLD]]*Table3[[#This Row],[Selling Price]],0) -> 6000 | L9: =Table3[[#This Row],[Total Sales]]-Table3[[#This Row],[Discount]] -> 6000 | M9: =Table3[[#This Row],[Net Sales]]-Table3[[#This Row],[Cost Price]]*Table3[[#This Row],[QTY SOLD]] -> 1800
A10: 46255 | B10: 4 | C10: Cashier 3 | D10: Shaki | E10: =IF(D10="","",VLOOKUP(D10,'Product Master'!$B:$C,2,FALSE)) -> Food | F10: =IF(D10="","",IFERROR(VLOOKUP(D10,'Product Master'!$B:$G,3,FALSE),"")) -> Piece | G10: 15 | H10: =IF(D10="","",VLOOKUP(D10,'Product Master'!$B:$F,5,FALSE)) -> 1200 | I10: =IFERROR(VLOOKUP(D10,'Product Master'!B:E,4,FALSE),0) -> 900 | J10: =IFERROR(Table3[[#This Row],[QTY SOLD]]*Table3[[#This Row],[Selling Price]],0) -> 18000 | L10: =Table3[[#This Row],[Total Sales]]-Table3[[#This Row],[Discount]] -> 18000 | M10: =Table3[[#This Row],[Net Sales]]-Table3[[#This Row],[Cost Price]]*Table3[[#This Row],[QTY SOLD]] -> 4500
A11: 46255 | B11: 4 | C11: Cashier 5 | D11: Moin Moin | E11: =IF(D11="","",VLOOKUP(D11,'Product Master'!$B:$C,2,FALSE)) -> Food | F11: =IF(D11="","",IFERROR(VLOOKUP(D11,'Product Master'!$B:$G,3,FALSE),"")) -> Piece | G11: 13 | H11: =IF(D11="","",VLOOKUP(D11,'Product Master'!$B:$F,5,FALSE)) -> 800 | I11: =IFERROR(VLOOKUP(D11,'Product Master'!B:E,4,FALSE),0) -> 500 | J11: =IFERROR(Table3[[#This Row],[QTY SOLD]]*Table3[[#This Row],[Selling Price]],0) -> 10400 | L11: =Table3[[#This Row],[Total Sales]]-Table3[[#This Row],[Discount]] -> 10400 | M11: =Table3[[#This Row],[Net Sales]]-Table3[[#This Row],[Cost Price]]*Table3[[#This Row],[QTY SOLD]] -> 3900
A12: 46255 | B12: 5 | C12: Cashier 3 | D12: Meat Pie | E12: =IF(D12="","",VLOOKUP(D12,'Product Master'!$B:$C,2,FALSE)) -> Snacks | F12: =IF(D12="","",IFERROR(VLOOKUP(D12,'Product Master'!$B:$G,3,FALSE),"")) -> Piece | G12: 3 | H12: =IF(D12="","",VLOOKUP(D12,'Product Master'!$B:$F,5,FALSE)) -> 900 | I12: =IFERROR(VLOOKUP(D12,'Product Master'!B:E,4,FALSE),0) -> 500 | J12: =IFERROR(Table3[[#This Row],[QTY SOLD]]*Table3[[#This Row],[Selling Price]],0) -> 2700 | L12: =Table3[[#This Row],[Total Sales]]-Table3[[#This Row],[Discount]] -> 2700 | M12: =Table3[[#This Row],[Net Sales]]-Table3[[#This Row],[Cost Price]]*Table3[[#This Row],[QTY SOLD]] -> 1200
A13: 46255 | B13: 5 | C13: Cashier 3 | D13: Chicken Pie | E13: =IF(D13="","",VLOOKUP(D13,'Product Master'!$B:$C,2,FALSE)) -> Snacks | F13: =IF(D13="","",IFERROR(VLOOKUP(D13,'Product Master'!$B:$G,3,FALSE),"")) -> Piece | G13: 7 | H13: =IF(D13="","",VLOOKUP(D13,'Product Master'!$B:$F,5,FALSE)) -> 1000 | I13: =IFERROR(VLOOKUP(D13,'Product Master'!B:E,4,FALSE),0) -> 700 | J13: =IFERROR(Table3[[#This Row],[QTY SOLD]]*Table3[[#This Row],[Selling Price]],0) -> 7000 | L13: =Table3[[#This Row],[Total Sales]]-Table3[[#This Row],[Discount]] -> 7000 | M13: =Table3[[#This Row],[Net Sales]]-Table3[[#This Row],[Cost Price]]*Table3[[#This Row],[QTY SOLD]] -> 2100
A14: 46255 | B14: 5 | C14: Cashier 3 | D14: Beef Roll | E14: =IF(D14="","",VLOOKUP(D14,'Product Master'!$B:$C,2,FALSE)) -> Snacks | F14: =IF(D14="","",IFERROR(VLOOKUP(D14,'Product Master'!$B:$G,3,FALSE),"")) -> Piece | G14: 5 | H14: =IF(D14="","",VLOOKUP(D14,'Product Master'!$B:$F,5,FALSE)) -> 700 | I14: =IFERROR(VLOOKUP(D14,'Product Master'!B:E,4,FALSE),0) -> 400 | J14: =IFERROR(Table3[[#This Row],[QTY SOLD]]*Table3[[#This Row],[Selling Price]],0) -> 3500 | L14: =Table3[[#This Row],[Total Sales]]-Table3[[#This Row],[Discount]] -> 3500 | M14: =Table3[[#This Row],[Net Sales]]-Table3[[#This Row],[Cost Price]]*Table3[[#This Row],[QTY SOLD]] -> 1500
A15: 46258 | B15: 6 | C15: Cashier 1 | D15: Pet Lucozade Boost | E15: =IF(D15="","",VLOOKUP(D15,'Product Master'!$B:$C,2,FALSE)) -> Drinks | F15: =IF(D15="","",IFERROR(VLOOKUP(D15,'Product Master'!$B:$G,3,FALSE),"")) -> Pack | G15: 5 | H15: =IF(D15="","",VLOOKUP(D15,'Product Master'!$B:$F,5,FALSE)) -> 20000 | I15: =IFERROR(VLOOKUP(D15,'Product Master'!B:E,4,FALSE),0) -> 17000 | J15: =IFERROR(Table3[[#This Row],[QTY SOLD]]*Table3[[#This Row],[Selling Price]],0) -> 100000 | L15: =Table3[[#This Row],[Total Sales]]-Table3[[#This Row],[Discount]] -> 100000 | M15: =Table3[[#This Row],[Net Sales]]-Table3[[#This Row],[Cost Price]]*Table3[[#This Row],[QTY SOLD]] -> 15000
A16: 46258 | B16: 6 | C16: Cashier 1 | D16: Eva Water 0.75Cl | E16: =IF(D16="","",VLOOKUP(D16,'Product Master'!$B:$C,2,FALSE)) -> Drinks | F16: =IF(D16="","",IFERROR(VLOOKUP(D16,'Product Master'!$B:$G,3,FALSE),"")) -> Pack | G16: 7 | H16: =IF(D16="","",VLOOKUP(D16,'Product Master'!$B:$F,5,FALSE)) -> 8500 | I16: =IFERROR(VLOOKUP(D16,'Product Master'!B:E,4,FALSE),0) -> 5000 | J16: =IFERROR(Table3[[#This Row],[QTY SOLD]]*Table3[[#This Row],[Selling Price]],0) -> 59500 | L16: =Table3[[#This Row],[Total Sales]]-Table3[[#This Row],[Discount]] -> 59500 | M16: =Table3[[#This Row],[Net Sales]]-Table3[[#This Row],[Cost Price]]*Table3[[#This Row],[QTY SOLD]] -> 24500
A17: =A16+1 -> 46259 | B17: 6 | C17: Cashier 2 | D17: Beef | E17: =IF(D17="","",VLOOKUP(D17,'Product Master'!$B:$C,2,FALSE)) -> Food | F17: =IF(D17="","",IFERROR(VLOOKUP(D17,'Product Master'!$B:$G,3,FALSE),"")) -> Piece | G17: 5 | H17: =IF(D17="","",VLOOKUP(D17,'Product Master'!$B:$F,5,FALSE)) -> 1000 | I17: =IFERROR(VLOOKUP(D17,'Product Master'!B:E,4,FALSE),0) -> 700 | J17: =IFERROR(Table3[[#This Row],[QTY SOLD]]*Table3[[#This Row],[Selling Price]],0) -> 5000 | L17: =Table3[[#This Row],[Total Sales]]-Table3[[#This Row],[Discount]] -> 5000 | M17: =Table3[[#This Row],[Net Sales]]-Table3[[#This Row],[Cost Price]]*Table3[[#This Row],[QTY SOLD]] -> 1500
A18: =A17+1 -> 46260 | B18: 6 | C18: Cashier 1 | D18: Shaki | E18: =IF(D18="","",VLOOKUP(D18,'Product Master'!$B:$C,2,FALSE)) -> Food | F18: =IF(D18="","",IFERROR(VLOOKUP(D18,'Product Master'!$B:$G,3,FALSE),"")) -> Piece | G18: 8 | H18: =IF(D18="","",VLOOKUP(D18,'Product Master'!$B:$F,5,FALSE)) -> 1200 | I18: =IFERROR(VLOOKUP(D18,'Product Master'!B:E,4,FALSE),0) -> 900 | J18: =IFERROR(Table3[[#This Row],[QTY SOLD]]*Table3[[#This Row],[Selling Price]],0) -> 9600 | L18: =Table3[[#This Row],[Total Sales]]-Table3[[#This Row],[Discount]] -> 9600 | M18: =Table3[[#This Row],[Net Sales]]-Table3[[#This Row],[Cost Price]]*Table3[[#This Row],[QTY SOLD]] -> 2400
A19: 46265 | B19: 7 | C19: Cashier 2 | D19: Lucozade Sport Pet 50cl | E19: =IF(D19="","",VLOOKUP(D19,'Product Master'!$B:$C,2,FALSE)) -> Drinks | F19: =IF(D19="","",IFERROR(VLOOKUP(D19,'Product Master'!$B:$G,3,FALSE),"")) -> Pack | G19: 5 | H19: =IF(D19="","",VLOOKUP(D19,'Product Master'!$B:$F,5,FALSE)) -> 1500 | I19: =IFERROR(VLOOKUP(D19,'Product Master'!B:E,4,FALSE),0) -> 900 | J19: =IFERROR(Table3[[#This Row],[QTY SOLD]]*Table3[[#This Row],[Selling Price]],0) -> 7500 | L19: =Table3[[#This Row],[Total Sales]]-Table3[[#This Row],[Discount]] -> 7500 | M19: =Table3[[#This Row],[Net Sales]]-Table3[[#This Row],[Cost Price]]*Table3[[#This Row],[QTY SOLD]] -> 3000
A20: 46265 | B20: 7 | C20: Cashier 2 | D20: FAB Energy Drinks | E20: =IF(D20="","",VLOOKUP(D20,'Product Master'!$B:$C,2,FALSE)) -> Drinks | F20: =IF(D20="","",IFERROR(VLOOKUP(D20,'Product Master'!$B:$G,3,FALSE),"")) -> Pack | G20: 5 | H20: =IF(D20="","",VLOOKUP(D20,'Product Master'!$B:$F,5,FALSE)) -> 1500 | I20: =IFERROR(VLOOKUP(D20,'Product Master'!B:E,4,FALSE),0) -> 1000 | J20: =IFERROR(Table3[[#This Row],[QTY SOLD]]*Table3[[#This Row],[Selling Price]],0) -> 7500 | L20: =Table3[[#This Row],[Total Sales]]-Table3[[#This Row],[Discount]] -> 7500 | M20: =Table3[[#This Row],[Net Sales]]-Table3[[#This Row],[Cost Price]]*Table3[[#This Row],[QTY SOLD]] -> 2500
A21: 46265 | B21: 7 | C21: Cashier 2 | D21: Chin Chin 224 gms | E21: =IF(D21="","",VLOOKUP(D21,'Product Master'!$B:$C,2,FALSE)) -> Snacks | F21: =IF(D21="","",IFERROR(VLOOKUP(D21,'Product Master'!$B:$G,3,FALSE),"")) -> Piece | G21: 5 | H21: =IF(D21="","",VLOOKUP(D21,'Product Master'!$B:$F,5,FALSE)) -> 1500 | I21: =IFERROR(VLOOKUP(D21,'Product Master'!B:E,4,FALSE),0) -> 800 | J21: =IFERROR(Table3[[#This Row],[QTY SOLD]]*Table3[[#This Row],[Selling Price]],0) -> 7500 | L21: =Table3[[#This Row],[Total Sales]]-Table3[[#This Row],[Discount]] -> 7500 | M21: =Table3[[#This Row],[Net Sales]]-Table3[[#This Row],[Cost Price]]*Table3[[#This Row],[QTY SOLD]] -> 3500
A22: 46265 | B22: 7 | C22: Cashier 2 | D22: Malta Guinness 33cl Cans | E22: =IF(D22="","",VLOOKUP(D22,'Product Master'!$B:$C,2,FALSE)) -> Drinks | F22: =IF(D22="","",IFERROR(VLOOKUP(D22,'Product Master'!$B:$G,3,FALSE),"")) -> Pack | G22: 5 | H22: =IF(D22="","",VLOOKUP(D22,'Product Master'!$B:$F,5,FALSE)) -> 1500 | I22: =IFERROR(VLOOKUP(D22,'Product Master'!B:E,4,FALSE),0) -> 900 | J22: =IFERROR(Table3[[#This Row],[QTY SOLD]]*Table3[[#This Row],[Selling Price]],0) -> 7500 | L22: =Table3[[#This Row],[Total Sales]]-Table3[[#This Row],[Discount]] -> 7500 | M22: =Table3[[#This Row],[Net Sales]]-Table3[[#This Row],[Cost Price]]*Table3[[#This Row],[QTY SOLD]] -> 3000
A23: =A22+1 -> 46266 | E23: =IF(D23="","",VLOOKUP(D23,'Product Master'!$B:$C,2,FALSE)) | F23: =IF(D23="","",IFERROR(VLOOKUP(D23,'Product Master'!$B:$G,3,FALSE),"")) | H23: =IF(D23="","",VLOOKUP(D23,'Product Master'!$B:$F,5,FALSE)) | I23: =IFERROR(VLOOKUP(D23,'Product Master'!B:E,4,FALSE),0) -> 0 | J23: =IFERROR(Table3[[#This Row],[QTY SOLD]]*Table3[[#This Row],[Selling Price]],0) -> 0 | L23: =Table3[[#This Row],[Total Sales]]-Table3[[#This Row],[Discount]] -> 0 | M23: =Table3[[#This Row],[Net Sales]]-Table3[[#This Row],[Cost Price]]*Table3[[#This Row],[QTY SOLD]] -> 0
A24: =A23+1 -> 46267 | E24: =IF(D24="","",VLOOKUP(D24,'Product Master'!$B:$C,2,FALSE)) | F24: =IF(D24="","",IFERROR(VLOOKUP(D24,'Product Master'!$B:$G,3,FALSE),"")) | H24: =IF(D24="","",VLOOKUP(D24,'Product Master'!$B:$F,5,FALSE)) | I24: =IFERROR(VLOOKUP(D24,'Product Master'!B:E,4,FALSE),0) -> 0 | J24: =IFERROR(Table3[[#This Row],[QTY SOLD]]*Table3[[#This Row],[Selling Price]],0) -> 0 | L24: =Table3[[#This Row],[Total Sales]]-Table3[[#This Row],[Discount]] -> 0 | M24: =Table3[[#This Row],[Net Sales]]-Table3[[#This Row],[Cost Price]]*Table3[[#This Row],[QTY SOLD]] -> 0
A25: =A24+1 -> 46268 | E25: =IF(D25="","",VLOOKUP(D25,'Product Master'!$B:$C,2,FALSE)) | F25: =IF(D25="","",IFERROR(VLOOKUP(D25,'Product Master'!$B:$G,3,FALSE),"")) | H25: =IF(D25="","",VLOOKUP(D25,'Product Master'!$B:$F,5,FALSE)) | I25: =IFERROR(VLOOKUP(D25,'Product Master'!B:E,4,FALSE),0) -> 0 | J25: =IFERROR(Table3[[#This Row],[QTY SOLD]]*Table3[[#This Row],[Selling Price]],0) -> 0 | L25: =Table3[[#This Row],[Total Sales]]-Table3[[#This Row],[Discount]] -> 0 | M25: =Table3[[#This Row],[Net Sales]]-Table3[[#This Row],[Cost Price]]*Table3[[#This Row],[QTY SOLD]] -> 0
A26: =A25+1 -> 46269 | E26: =IF(D26="","",VLOOKUP(D26,'Product Master'!$B:$C,2,FALSE)) | F26: =IF(D26="","",IFERROR(VLOOKUP(D26,'Product Master'!$B:$G,3,FALSE),"")) | H26: =IF(D26="","",VLOOKUP(D26,'Product Master'!$B:$F,5,FALSE)) | I26: =IFERROR(VLOOKUP(D26,'Product Master'!B:E,4,FALSE),0) -> 0 | J26: =IFERROR(Table3[[#This Row],[QTY SOLD]]*Table3[[#This Row],[Selling Price]],0) -> 0 | L26: =Table3[[#This Row],[Total Sales]]-Table3[[#This Row],[Discount]] -> 0 | M26: =Table3[[#This Row],[Net Sales]]-Table3[[#This Row],[Cost Price]]*Table3[[#This Row],[QTY SOLD]] -> 0
A27: =A26+1 -> 46270 | E27: =IF(D27="","",VLOOKUP(D27,'Product Master'!$B:$C,2,FALSE)) | F27: =IF(D27="","",IFERROR(VLOOKUP(D27,'Product Master'!$B:$G,3,FALSE),"")) | H27: =IF(D27="","",VLOOKUP(D27,'Product Master'!$B:$F,5,FALSE)) | I27: =IFERROR(VLOOKUP(D27,'Product Master'!B:E,4,FALSE),0) -> 0 | J27: =IFERROR(Table3[[#This Row],[QTY SOLD]]*Table3[[#This Row],[Selling Price]],0) -> 0 | L27: =Table3[[#This Row],[Total Sales]]-Table3[[#This Row],[Discount]] -> 0 | M27: =Table3[[#This Row],[Net Sales]]-Table3[[#This Row],[Cost Price]]*Table3[[#This Row],[QTY SOLD]] -> 0
A28: =A27+1 -> 46271 | E28: =IF(D28="","",VLOOKUP(D28,'Product Master'!$B:$C,2,FALSE)) | F28: =IF(D28="","",IFERROR(VLOOKUP(D28,'Product Master'!$B:$G,3,FALSE),"")) | H28: =IF(D28="","",VLOOKUP(D28,'Product Master'!$B:$F,5,FALSE)) | I28: =IFERROR(VLOOKUP(D28,'Product Master'!B:E,4,FALSE),0) -> 0 | J28: =IFERROR(Table3[[#This Row],[QTY SOLD]]*Table3[[#This Row],[Selling Price]],0) -> 0 | L28: =Table3[[#This Row],[Total Sales]]-Table3[[#This Row],[Discount]] -> 0 | M28: =Table3[[#This Row],[Net Sales]]-Table3[[#This Row],[Cost Price]]*Table3[[#This Row],[QTY SOLD]] -> 0
A29: =A28+1 -> 46272 | E29: =IF(D29="","",VLOOKUP(D29,'Product Master'!$B:$C,2,FALSE)) | F29: =IF(D29="","",IFERROR(VLOOKUP(D29,'Product Master'!$B:$G,3,FALSE),"")) | H29: =IF(D29="","",VLOOKUP(D29,'Product Master'!$B:$F,5,FALSE)) | I29: =IFERROR(VLOOKUP(D29,'Product Master'!B:E,4,FALSE),0) -> 0 | J29: =IFERROR(Table3[[#This Row],[QTY SOLD]]*Table3[[#This Row],[Selling Price]],0) -> 0 | L29: =Table3[[#This Row],[Total Sales]]-Table3[[#This Row],[Discount]] -> 0 | M29: =Table3[[#This Row],[Net Sales]]-Table3[[#This Row],[Cost Price]]*Table3[[#This Row],[QTY SOLD]] -> 0
A30: =A29+1 -> 46273 | E30: =IF(D30="","",VLOOKUP(D30,'Product Master'!$B:$C,2,FALSE)) | F30: =IF(D30="","",IFERROR(VLOOKUP(D30,'Product Master'!$B:$G,3,FALSE),"")) | H30: =IF(D30="","",VLOOKUP(D30,'Product Master'!$B:$F,5,FALSE)) | I30: =IFERROR(VLOOKUP(D30,'Product Master'!B:E,4,FALSE),0) -> 0 | J30: =IFERROR(Table3[[#This Row],[QTY SOLD]]*Table3[[#This Row],[Selling Price]],0) -> 0 | L30: =Table3[[#This Row],[Total Sales]]-Table3[[#This Row],[Discount]] -> 0 | M30: =Table3[[#This Row],[Net Sales]]-Table3[[#This Row],[Cost Price]]*Table3[[#This Row],[QTY SOLD]] -> 0
A31: =A30+1 -> 46274 | E31: =IF(D31="","",VLOOKUP(D31,'Product Master'!$B:$C,2,FALSE)) | F31: =IF(D31="","",IFERROR(VLOOKUP(D31,'Product Master'!$B:$G,3,FALSE),"")) | H31: =IF(D31="","",VLOOKUP(D31,'Product Master'!$B:$F,5,FALSE)) | I31: =IFERROR(VLOOKUP(D31,'Product Master'!B:E,4,FALSE),0) -> 0 | J31: =IFERROR(Table3[[#This Row],[QTY SOLD]]*Table3[[#This Row],[Selling Price]],0) -> 0 | L31: =Table3[[#This Row],[Total Sales]]-Table3[[#This Row],[Discount]] -> 0 | M31: =Table3[[#This Row],[Net Sales]]-Table3[[#This Row],[Cost Price]]*Table3[[#This Row],[QTY SOLD]] -> 0
A32: =A31+1 -> 46275 | E32: =IF(D32="","",VLOOKUP(D32,'Product Master'!$B:$C,2,FALSE)) | F32: =IF(D32="","",IFERROR(VLOOKUP(D32,'Product Master'!$B:$G,3,FALSE),"")) | H32: =IF(D32="","",VLOOKUP(D32,'Product Master'!$B:$F,5,FALSE)) | I32: =IFERROR(VLOOKUP(D32,'Product Master'!B:E,4,FALSE),0) -> 0 | J32: =IFERROR(Table3[[#This Row],[QTY SOLD]]*Table3[[#This Row],[Selling Price]],0) -> 0 | L32: =Table3[[#This Row],[Total Sales]]-Table3[[#This Row],[Discount]] -> 0 | M32: =Table3[[#This Row],[Net Sales]]-Table3[[#This Row],[Cost Price]]*Table3[[#This Row],[QTY SOLD]] -> 0
E33: =IF(D33="","",VLOOKUP(D33,'Product Master'!$B:$C,2,FALSE)) | F33: =IF(D33="","",IFERROR(VLOOKUP(D33,'Product Master'!$B:$G,3,FALSE),"")) | H33: =IF(D33="","",VLOOKUP(D33,'Product Master'!$B:$F,5,FALSE)) | I33: =IFERROR(VLOOKUP(D33,'Product Master'!B:E,4,FALSE),0) -> 0 | J33: =IFERROR(Table3[[#This Row],[QTY SOLD]]*Table3[[#This Row],[Selling Price]],0) -> 0 | L33: =Table3[[#This Row],[Total Sales]]-Table3[[#This Row],[Discount]] -> 0 | M33: =Table3[[#This Row],[Net Sales]]-Table3[[#This Row],[Cost Price]]*Table3[[#This Row],[QTY SOLD]] -> 0
E34: =IF(D34="","",VLOOKUP(D34,'Product Master'!$B:$C,2,FALSE)) | F34: =IF(D34="","",IFERROR(VLOOKUP(D34,'Product Master'!$B:$G,3,FALSE),"")) | H34: =IF(D34="","",VLOOKUP(D34,'Product Master'!$B:$F,5,FALSE)) | I34: =IFERROR(VLOOKUP(D34,'Product Master'!B:E,4,FALSE),0) -> 0 | J34: =IFERROR(Table3[[#This Row],[QTY SOLD]]*Table3[[#This Row],[Selling Price]],0) -> 0 | L34: =Table3[[#This Row],[Total Sales]]-Table3[[#This Row],[Discount]] -> 0 | M34: =Table3[[#This Row],[Net Sales]]-Table3[[#This Row],[Cost Price]]*Table3[[#This Row],[QTY SOLD]] -> 0
E35: =IF(D35="","",VLOOKUP(D35,'Product Master'!$B:$C,2,FALSE)) | F35: =IF(D35="","",IFERROR(VLOOKUP(D35,'Product Master'!$B:$G,3,FALSE),"")) | H35: =IF(D35="","",VLOOKUP(D35,'Product Master'!$B:$F,5,FALSE)) | I35: =IFERROR(VLOOKUP(D35,'Product Master'!B:E,4,FALSE),0) -> 0 | J35: =IFERROR(Table3[[#This Row],[QTY SOLD]]*Table3[[#This Row],[Selling Price]],0) -> 0 | L35: =Table3[[#This Row],[Total Sales]]-Table3[[#This Row],[Discount]] -> 0 | M35: =Table3[[#This Row],[Net Sales]]-Table3[[#This Row],[Cost Price]]*Table3[[#This Row],[QTY SOLD]] -> 0
E36: =IF(D36="","",VLOOKUP(D36,'Product Master'!$B:$C,2,FALSE)) | F36: =IF(D36="","",IFERROR(VLOOKUP(D36,'Product Master'!$B:$G,3,FALSE),"")) | H36: =IF(D36="","",VLOOKUP(D36,'Product Master'!$B:$F,5,FALSE)) | I36: =IFERROR(VLOOKUP(D36,'Product Master'!B:E,4,FALSE),0) -> 0 | J36: =IFERROR(Table3[[#This Row],[QTY SOLD]]*Table3[[#This Row],[Selling Price]],0) -> 0 | L36: =Table3[[#This Row],[Total Sales]]-Table3[[#This Row],[Discount]] -> 0 | M36: =Table3[[#This Row],[Net Sales]]-Table3[[#This Row],[Cost Price]]*Table3[[#This Row],[QTY SOLD]] -> 0
E37: =IF(D37="","",VLOOKUP(D37,'Product Master'!$B:$C,2,FALSE)) | F37: =IF(D37="","",IFERROR(VLOOKUP(D37,'Product Master'!$B:$G,3,FALSE),"")) | H37: =IF(D37="","",VLOOKUP(D37,'Product Master'!$B:$F,5,FALSE)) | I37: =IFERROR(VLOOKUP(D37,'Product Master'!B:E,4,FALSE),0) -> 0 | J37: =IFERROR(Table3[[#This Row],[QTY SOLD]]*Table3[[#This Row],[Selling Price]],0) -> 0 | L37: =Table3[[#This Row],[Total Sales]]-Table3[[#This Row],[Discount]] -> 0 | M37: =Table3[[#This Row],[Net Sales]]-Table3[[#This Row],[Cost Price]]*Table3[[#This Row],[QTY SOLD]] -> 0
E38: =IF(D38="","",VLOOKUP(D38,'Product Master'!$B:$C,2,FALSE)) | F38: =IF(D38="","",IFERROR(VLOOKUP(D38,'Product Master'!$B:$G,3,FALSE),"")) | H38: =IF(D38="","",VLOOKUP(D38,'Product Master'!$B:$F,5,FALSE)) | I38: =IFERROR(VLOOKUP(D38,'Product Master'!B:E,4,FALSE),0) -> 0 | J38: =IFERROR(Table3[[#This Row],[QTY SOLD]]*Table3[[#This Row],[Selling Price]],0) -> 0 | L38: =Table3[[#This Row],[Total Sales]]-Table3[[#This Row],[Discount]] -> 0 | M38: =Table3[[#This Row],[Net Sales]]-Table3[[#This Row],[Cost Price]]*Table3[[#This Row],[QTY SOLD]] -> 0
E39: =IF(D39="","",VLOOKUP(D39,'Product Master'!$B:$C,2,FALSE)) | F39: =IF(D39="","",IFERROR(VLOOKUP(D39,'Product Master'!$B:$G,3,FALSE),"")) | H39: =IF(D39="","",VLOOKUP(D39,'Product Master'!$B:$F,5,FALSE)) | I39: =IFERROR(VLOOKUP(D39,'Product Master'!B:E,4,FALSE),0) -> 0 | J39: =IFERROR(Table3[[#This Row],[QTY SOLD]]*Table3[[#This Row],[Selling Price]],0) -> 0 | L39: =Table3[[#This Row],[Total Sales]]-Table3[[#This Row],[Discount]] -> 0 | M39: =Table3[[#This Row],[Net Sales]]-Table3[[#This Row],[Cost Price]]*Table3[[#This Row],[QTY SOLD]] -> 0
E40: =IF(D40="","",VLOOKUP(D40,'Product Master'!$B:$C,2,FALSE)) | F40: =IF(D40="","",IFERROR(VLOOKUP(D40,'Product Master'!$B:$G,3,FALSE),"")) | H40: =IF(D40="","",VLOOKUP(D40,'Product Master'!$B:$F,5,FALSE)) | I40: =IFERROR(VLOOKUP(D40,'Product Master'!B:E,4,FALSE),0) -> 0 | J40: =IFERROR(Table3[[#This Row],[QTY SOLD]]*Table3[[#This Row],[Selling Price]],0) -> 0 | L40: =Table3[[#This Row],[Total Sales]]-Table3[[#This Row],[Discount]] -> 0 | M40: =Table3[[#This Row],[Net Sales]]-Table3[[#This Row],[Cost Price]]*Table3[[#This Row],[QTY SOLD]] -> 0
E41: =IF(D41="","",VLOOKUP(D41,'Product Master'!$B:$C,2,FALSE)) | F41: =IF(D41="","",IFERROR(VLOOKUP(D41,'Product Master'!$B:$G,3,FALSE),"")) | H41: =IF(D41="","",VLOOKUP(D41,'Product Master'!$B:$F,5,FALSE)) | I41: =IFERROR(VLOOKUP(D41,'Product Master'!B:E,4,FALSE),0) -> 0 | J41: =IFERROR(Table3[[#This Row],[QTY SOLD]]*Table3[[#This Row],[Selling Price]],0) -> 0 | L41: =Table3[[#This Row],[Total Sales]]-Table3[[#This Row],[Discount]] -> 0 | M41: =Table3[[#This Row],[Net Sales]]-Table3[[#This Row],[Cost Price]]*Table3[[#This Row],[QTY SOLD]] -> 0
E42: =IF(D42="","",VLOOKUP(D42,'Product Master'!$B:$C,2,FALSE)) | F42: =IF(D42="","",IFERROR(VLOOKUP(D42,'Product Master'!$B:$G,3,FALSE),"")) | H42: =IF(D42="","",VLOOKUP(D42,'Product Master'!$B:$F,5,FALSE)) | I42: =IFERROR(VLOOKUP(D42,'Product Master'!B:E,4,FALSE),0) -> 0 | J42: =IFERROR(Table3[[#This Row],[QTY SOLD]]*Table3[[#This Row],[Selling Price]],0) -> 0 | L42: =Table3[[#This Row],[Total Sales]]-Table3[[#This Row],[Discount]] -> 0 | M42: =Table3[[#This Row],[Net Sales]]-Table3[[#This Row],[Cost Price]]*Table3[[#This Row],[QTY SOLD]] -> 0
E43: =IF(D43="","",VLOOKUP(D43,'Product Master'!$B:$C,2,FALSE)) | F43: =IF(D43="","",IFERROR(VLOOKUP(D43,'Product Master'!$B:$G,3,FALSE),"")) | H43: =IF(D43="","",VLOOKUP(D43,'Product Master'!$B:$F,5,FALSE)) | I43: =IFERROR(VLOOKUP(D43,'Product Master'!B:E,4,FALSE),0) -> 0 | J43: =IFERROR(Table3[[#This Row],[QTY SOLD]]*Table3[[#This Row],[Selling Price]],0) -> 0 | L43: =Table3[[#This Row],[Total Sales]]-Table3[[#This Row],[Discount]] -> 0 | M43: =Table3[[#This Row],[Net Sales]]-Table3[[#This Row],[Cost Price]]*Table3[[#This Row],[QTY SOLD]] -> 0
E44: =IF(D44="","",VLOOKUP(D44,'Product Master'!$B:$C,2,FALSE)) | F44: =IF(D44="","",IFERROR(VLOOKUP(D44,'Product Master'!$B:$G,3,FALSE),"")) | H44: =IF(D44="","",VLOOKUP(D44,'Product Master'!$B:$F,5,FALSE)) | I44: =IFERROR(VLOOKUP(D44,'Product Master'!B:E,4,FALSE),0) -> 0 | J44: =IFERROR(Table3[[#This Row],[QTY SOLD]]*Table3[[#This Row],[Selling Price]],0) -> 0 | L44: =Table3[[#This Row],[Total Sales]]-Table3[[#This Row],[Discount]] -> 0 | M44: =Table3[[#This Row],[Net Sales]]-Table3[[#This Row],[Cost Price]]*Table3[[#This Row],[QTY SOLD]] -> 0
... E1000: =IF(D1000="","",VLOOKUP(D1000,'Product Master'!$B:$C,2,FALSE)) | F1000: =IF(D1000="","",IFERROR(VLOOKUP(D1000,'Product Master'!$B:$G,3,FALSE),"")) | H1000: =IF(D1000="","",VLOOKUP(D1000,'Product Master'!$B:$F,5,FALSE)) | I1000: =IFERROR(VLOOKUP(D1000,'Product Master'!B:E,4,FALSE),0) -> 0 | J1000: =IFERROR(Table3[[#This Row],[QTY SOLD]]*Table3[[#This Row],[Selling Price]],0) -> 0 | L1000: =Table3[[#This Row],[Total Sales]]-Table3[[#This Row],[Discount]] -> 0 | M1000: =Table3[[#This Row],[Net Sales]]-Table3[[#This Row],[Cost Price]]*Table3[[#This Row],[QTY SOLD]] -> 0

Sheet Stock Purchase
A1: Date | B1: Purchase ID | C1: Supplier | D1: Product Name | E1: Unit | F1: QTY Purchased | G1: Unit Cost | H1: Total Purchase Cost
A2: 46235 | B2: ="PUR"&TEXT(ROW()-1,"0000") -> PUR0001 | C2: Supplier 1 | D2: Beef | E2: =IF(D2="","",VLOOKUP(D2,'Product Master'!$B:$G,3,FALSE)) -> Piece | F2: 50 | G2: =IF(D2="","",VLOOKUP(D2,'Product Master'!$B:$G,4,FALSE)) -> 700 | H2: =IF(OR(F2="",G2=""),"",F2*G2) -> 35000
A3: 46236 | B3: ="PUR"&TEXT(ROW()-1,"0000") -> PUR0002 | C3: Supplier 1 | D3: Shaki | E3: =IF(D3="","",VLOOKUP(D3,'Product Master'!$B:$G,3,FALSE)) -> Piece | F3: 50 | G3: =IF(D3="","",VLOOKUP(D3,'Product Master'!$B:$G,4,FALSE)) -> 900 | H3: =IF(OR(F3="",G3=""),"",F3*G3) -> 45000
A4: 46237 | B4: ="PUR"&TEXT(ROW()-1,"0000") -> PUR0003 | C4: Supplier 1 | D4: Cow leg | E4: =IF(D4="","",VLOOKUP(D4,'Product Master'!$B:$G,3,FALSE)) -> Piece | F4: 50 | G4: =IF(D4="","",VLOOKUP(D4,'Product Master'!$B:$G,4,FALSE)) -> 1200 | H4: =IF(OR(F4="",G4=""),"",F4*G4) -> 60000
A5: 46238 | B5: ="PUR"&TEXT(ROW()-1,"0000") -> PUR0004 | C5: Supplier 1 | D5: Semovita | E5: =IF(D5="","",VLOOKUP(D5,'Product Master'!$B:$G,3,FALSE)) -> Piece | F5: 50 | G5: =IF(D5="","",VLOOKUP(D5,'Product Master'!$B:$G,4,FALSE)) -> 400 | H5: =IF(OR(F5="",G5=""),"",F5*G5) -> 20000
A6: 46239 | B6: ="PUR"&TEXT(ROW()-1,"0000") -> PUR0005 | C6: Supplier 1 | D6: Eba | E6: =IF(D6="","",VLOOKUP(D6,'Product Master'!$B:$G,3,FALSE)) -> Piece | F6: 50 | G6: =IF(D6="","",VLOOKUP(D6,'Product Master'!$B:$G,4,FALSE)) -> 200 | H6: =IF(OR(F6="",G6=""),"",F6*G6) -> 10000
A7: 46240 | B7: ="PUR"&TEXT(ROW()-1,"0000") -> PUR0006 | C7: Supplier 1 | D7: Moin Moin | E7: =IF(D7="","",VLOOKUP(D7,'Product Master'!$B:$G,3,FALSE)) -> Piece | F7: 50 | G7: =IF(D7="","",VLOOKUP(D7,'Product Master'!$B:$G,4,FALSE)) -> 500 | H7: =IF(OR(F7="",G7=""),"",F7*G7) -> 25000
A8: 46255 | B8: ="PUR"&TEXT(ROW()-1,"0000") -> PUR0007 | C8: Supplier 3 | D8: Meat Pie | E8: =IF(D8="","",VLOOKUP(D8,'Product Master'!$B:$G,3,FALSE)) -> Piece | F8: 50 | G8: =IF(D8="","",VLOOKUP(D8,'Product Master'!$B:$G,4,FALSE)) -> 500 | H8: =IF(OR(F8="",G8=""),"",F8*G8) -> 25000
A9: 46242 | B9: ="PUR"&TEXT(ROW()-1,"0000") -> PUR0008 | C9: Supplier 3 | D9: Chicken Pie | E9: =IF(D9="","",VLOOKUP(D9,'Product Master'!$B:$G,3,FALSE)) -> Piece | F9: 50 | G9: =IF(D9="","",VLOOKUP(D9,'Product Master'!$B:$G,4,FALSE)) -> 700 | H9: =IF(OR(F9="",G9=""),"",F9*G9) -> 35000
A10: 46243 | B10: ="PUR"&TEXT(ROW()-1,"0000") -> PUR0009 | C10: Supplier 3 | D10: Beef Roll | E10: =IF(D10="","",VLOOKUP(D10,'Product Master'!$B:$G,3,FALSE)) -> Piece | F10: 50 | G10: =IF(D10="","",VLOOKUP(D10,'Product Master'!$B:$G,4,FALSE)) -> 400 | H10: =IF(OR(F10="",G10=""),"",F10*G10) -> 20000
A11: 46244 | B11: ="PUR"&TEXT(ROW()-1,"0000") -> PUR0010 | C11: Supplier 1 | D11: Pet Lucozade Boost | E11: =IF(D11="","",VLOOKUP(D11,'Product Master'!$B:$G,3,FALSE)) -> Pack | F11: 70 | G11: =IF(D11="","",VLOOKUP(D11,'Product Master'!$B:$G,4,FALSE)) -> 17000 | H11: =IF(OR(F11="",G11=""),"",F11*G11) -> 1190000
A12: 46245 | B12: ="PUR"&TEXT(ROW()-1,"0000") -> PUR0011 | C12: Supplier 1 | D12: Eva Water 0.75Cl | E12: =IF(D12="","",VLOOKUP(D12,'Product Master'!$B:$G,3,FALSE)) -> Pack | F12: 70 | G12: =IF(D12="","",VLOOKUP(D12,'Product Master'!$B:$G,4,FALSE)) -> 5000 | H12: =IF(OR(F12="",G12=""),"",F12*G12) -> 350000
A13: 46265 | B13: ="PUR"&TEXT(ROW()-1,"0000") -> PUR0012 | C13: Supplier 3 | D13: Lucozade Sport Pet 50cl | E13: =IF(D13="","",VLOOKUP(D13,'Product Master'!$B:$G,3,FALSE)) -> Pack | F13: 50 | G13: =IF(D13="","",VLOOKUP(D13,'Product Master'!$B:$G,4,FALSE)) -> 900 | H13: =IF(OR(F13="",G13=""),"",F13*G13) -> 45000
... A16: 46265 | B16: ="PUR"&TEXT(ROW()-1,"0000") -> PUR0015 | C16: Supplier 3 | D16: Malta Guinness 33cl Cans | E16: =IF(D16="","",VLOOKUP(D16,'Product Master'!$B:$G,3,FALSE)) -> Pack | F16: 50 | G16: =IF(D16="","",VLOOKUP(D16,'Product Master'!$B:$G,4,FALSE)) -> 900 | H16: =IF(OR(F16="",G16=""),"",F16*G16) -> 45000
B17: ="PUR"&TEXT(ROW()-1,"0000") -> PUR0016 | E17: =IF(D17="","",VLOOKUP(D17,'Product Master'!$B:$G,3,FALSE)) | G17: =IF(D17="","",VLOOKUP(D17,'Product Master'!$B:$G,4,FALSE)) | H17: =IF(OR(F17="",G17=""),"",F17*G17)
B18: ="PUR"&TEXT(ROW()-1,"0000") -> PUR0017 | E18: =IF(D18="","",VLOOKUP(D18,'Product Master'!$B:$G,3,FALSE)) | G18: =IF(D18="","",VLOOKUP(D18,'Product Master'!$B:$G,4,FALSE)) | H18: =IF(OR(F18="",G18=""),"",F18*G18)
B19: ="PUR"&TEXT(ROW()-1,"0000") -> PUR0018 | E19: =IF(D19="","",VLOOKUP(D19,'Product Master'!$B:$G,3,FALSE)) | G19: =IF(D19="","",VLOOKUP(D19,'Product Master'!$B:$G,4,FALSE)) | H19: =IF(OR(F19="",G19=""),"",F19*G19)
B20: ="PUR"&TEXT(ROW()-1,"0000") -> PUR0019 | E20: =IF(D20="","",VLOOKUP(D20,'Product Master'!$B:$G,3,FALSE)) | G20: =IF(D20="","",VLOOKUP(D20,'Product Master'!$B:$G,4,FALSE)) | H20: =IF(OR(F20="",G20=""),"",F20*G20)
B21: ="PUR"&TEXT(ROW()-1,"0000") -> PUR0020 | E21: =IF(D21="","",VLOOKUP(D21,'Product Master'!$B:$G,3,FALSE)) | G21: =IF(D21="","",VLOOKUP(D21,'Product Master'!$B:$G,4,FALSE)) | H21: =IF(OR(F21="",G21=""),"",F21*G21)
B22: ="PUR"&TEXT(ROW()-1,"0000") -> PUR0021 | E22: =IF(D22="","",VLOOKUP(D22,'Product Master'!$B:$G,3,FALSE)) | G22: =IF(D22="","",VLOOKUP(D22,'Product Master'!$B:$G,4,FALSE)) | H22: =IF(OR(F22="",G22=""),"",F22*G22)
B23: ="PUR"&TEXT(ROW()-1,"0000") -> PUR0022 | E23: =IF(D23="","",VLOOKUP(D23,'Product Master'!$B:$G,3,FALSE)) | G23: =IF(D23="","",VLOOKUP(D23,'Product Master'!$B:$G,4,FALSE)) | H23: =IF(OR(F23="",G23=""),"",F23*G23)
B24: ="PUR"&TEXT(ROW()-1,"0000") -> PUR0023 | E24: =IF(D24="","",VLOOKUP(D24,'Product Master'!$B:$G,3,FALSE)) | G24: =IF(D24="","",VLOOKUP(D24,'Product Master'!$B:$G,4,FALSE)) | H24: =IF(OR(F24="",G24=""),"",F24*G24)
B25: ="PUR"&TEXT(ROW()-1,"0000") -> PUR0024 | E25: =IF(D25="","",VLOOKUP(D25,'Product Master'!$B:$G,3,FALSE)) | G25: =IF(D25="","",VLOOKUP(D25,'Product Master'!$B:$G,4,FALSE)) | H25: =IF(OR(F25="",G25=""),"",F25*G25)
B26: ="PUR"&TEXT(ROW()-1,"0000") -> PUR0025 | E26: =IF(D26="","",VLOOKUP(D26,'Product Master'!$B:$G,3,FALSE)) | G26: =IF(D26="","",VLOOKUP(D26,'Product Master'!$B:$G,4,FALSE)) | H26: =IF(OR(F26="",G26=""),"",F26*G26)
B27: ="PUR"&TEXT(ROW()-1,"0000") -> PUR0026 | E27: =IF(D27="","",VLOOKUP(D27,'Product Master'!$B:$G,3,FALSE)) | G27: =IF(D27="","",VLOOKUP(D27,'Product Master'!$B:$G,4,FALSE)) | H27: =IF(OR(F27="",G27=""),"",F27*G27)
B28: ="PUR"&TEXT(ROW()-1,"0000") -> PUR0027 | E28: =IF(D28="","",VLOOKUP(D28,'Product Master'!$B:$G,3,FALSE)) | G28: =IF(D28="","",VLOOKUP(D28,'Product Master'!$B:$G,4,FALSE)) | H28: =IF(OR(F28="",G28=""),"",F28*G28)
... B502: ="PUR"&TEXT(ROW()-1,"0000") -> PUR0501 | E502: =IF(D502="","",VLOOKUP(D502,'Product Master'!$B:$G,3,FALSE)) | G502: =IF(D502="","",VLOOKUP(D502,'Product Master'!$B:$G,4,FALSE)) | H502: =IF(OR(F502="",G502=""),"",F502*G502)

Sheet Inventory
A1: Product ID | B1: Product Name | C1: Category | D1: Unit | E1: Opening Stock | F1: Total Purchased | G1: Customer Returned | H1: Total Sold | I1: Staff Consumption | J1: Damaged | K1: Expired | L1: Supplier Returned | M1: Closing Stock | N1: Cost Price | O1: Selling Price | P1: Reorder Level | Q1: Inventory Value | R1: Stock Status
A2: P0001 | B2: Beef | C2: =IF(B2="","",VLOOKUP(B2,'Product Master'!$B:$G,2,FALSE)) -> Food | D2: =IF(B2="","",VLOOKUP(B2,'Product Master'!$B:$G,3,FALSE)) -> Piece | E2: 50 | F2: =SUMIF('Stock Purchase'!$D:$D,B2,'Stock Purchase'!$F:$F) -> 50 | G2: =SUMIFS('Stock Adjustment'!$E:$E,'Stock Adjustment'!$B:$B,$A2,'Stock Adjustment'!$D:$D,"Customer Returned") -> 0 | H2: =SUMIF('Daily Sales Entry'!$D:$D,B2,'Daily Sales Entry'!$G:$G) -> 16 | I2: =SUMIFS('Stock Adjustment'!$E:$E,'Stock Adjustment'!$B:$B,$A2,'Stock Adjustment'!$D:$D,"Staff Consumption") -> 0 | J2: =SUMIFS('Stock Adjustment'!$E:$E,'Stock Adjustment'!$B:$B,$A2,'Stock Adjustment'!$D:$D,"Damaged") -> 15 | K2: =SUMIFS('Stock Adjustment'!$E:$E,'Stock Adjustment'!$B:$B,$A2,'Stock Adjustment'!$D:$D,"Expired") -> 0 | L2: =SUMIFS('Stock Adjustment'!$E:$E,'Stock Adjustment'!$B:$B,$A2,'Stock Adjustment'!$D:$D,"Supplier Returned") -> 0 | M2: =Table4[[#This Row],[Opening Stock]]+Table4[[#This Row],[Total Purchased]]+Table4[[#This Row],[Customer Returned]]-Table4[[#This Row],[Total Sold]]-Table4[[#This Row],[Damaged]]-Table4[[#This Row],[Expired]]-Table4[[#This Row],[Supplier Returned]]-Table4[[#This Row],[Staff Consumption]] -> 69 | N2: =IF(B2="","",VLOOKUP(B2,'Product Master'!$B:$G,4,FALSE)) -> 700 | O2: =IF(B2="","",VLOOKUP(B2,'Product Master'!$B:$G,5,FALSE)) -> 1000 | P2: =IF(B2="","",VLOOKUP(B2,'Product Master'!$B:$I,7,FALSE)) -> 20 | Q2: =IFERROR(Table4[[#This Row],[Closing Stock]]*Table4[[#This Row],[Cost Price]],0) -> 48300 | R2: =IF(B2="","",IF(M2=0,"Out of Stock",IF(M2<=10,"Low Stock","In Stock"))) -> In Stock
A3: P0002 | B3: Shaki | C3: =IF(B3="","",VLOOKUP(B3,'Product Master'!$B:$G,2,FALSE)) -> Food | D3: =IF(B3="","",VLOOKUP(B3,'Product Master'!$B:$G,3,FALSE)) -> Piece | F3: =SUMIF('Stock Purchase'!$D:$D,B3,'Stock Purchase'!$F:$F) -> 50 | G3: =SUMIFS('Stock Adjustment'!$E:$E,'Stock Adjustment'!$B:$B,$A3,'Stock Adjustment'!$D:$D,"Customer Returned") -> 0 | H3: =SUMIF('Daily Sales Entry'!$D:$D,B3,'Daily Sales Entry'!$G:$G) -> 27 | I3: =SUMIFS('Stock Adjustment'!$E:$E,'Stock Adjustment'!$B:$B,$A3,'Stock Adjustment'!$D:$D,"Staff Consumption") -> 2 | J3: =SUMIFS('Stock Adjustment'!$E:$E,'Stock Adjustment'!$B:$B,$A3,'Stock Adjustment'!$D:$D,"Damaged") -> 0 | K3: =SUMIFS('Stock Adjustment'!$E:$E,'Stock Adjustment'!$B:$B,$A3,'Stock Adjustment'!$D:$D,"Expired") -> 0 | L3: =SUMIFS('Stock Adjustment'!$E:$E,'Stock Adjustment'!$B:$B,$A3,'Stock Adjustment'!$D:$D,"Supplier Returned") -> 0 | M3: =Table4[[#This Row],[Opening Stock]]+Table4[[#This Row],[Total Purchased]]+Table4[[#This Row],[Customer Returned]]-Table4[[#This Row],[Total Sold]]-Table4[[#This Row],[Damaged]]-Table4[[#This Row],[Expired]]-Table4[[#This Row],[Supplier Returned]]-Table4[[#This Row],[Staff Consumption]] -> 21 | N3: =IF(B3="","",VLOOKUP(B3,'Product Master'!$B:$G,4,FALSE)) -> 900 | O3: =IF(B3="","",VLOOKUP(B3,'Product Master'!$B:$G,5,FALSE)) -> 1200 | P3: =IF(B3="","",VLOOKUP(B3,'Product Master'!$B:$I,7,FALSE)) -> 20 | Q3: =IFERROR(Table4[[#This Row],[Closing Stock]]*Table4[[#This Row],[Cost Price]],0) -> 18900 | R3: =IF(B3="","",IF(M3=0,"Out of Stock",IF(M3<=10,"Low Stock","In Stock"))) -> In Stock
A4: P0003 | B4: Cow leg | C4: =IF(B4="","",VLOOKUP(B4,'Product Master'!$B:$G,2,FALSE)) -> Food | D4: =IF(B4="","",VLOOKUP(B4,'Product Master'!$B:$G,3,FALSE)) -> Piece | F4: =SUMIF('Stock Purchase'!$D:$D,B4,'Stock Purchase'!$F:$F) -> 50 | G4: =SUMIFS('Stock Adjustment'!$E:$E,'Stock Adjustment'!$B:$B,$A4,'Stock Adjustment'!$D:$D,"Customer Returned") -> 0 | H4: =SUMIF('Daily Sales Entry'!$D:$D,B4,'Daily Sales Entry'!$G:$G) -> 8 | I4: =SUMIFS('Stock Adjustment'!$E:$E,'Stock Adjustment'!$B:$B,$A4,'Stock Adjustment'!$D:$D,"Staff Consumption") -> 0 | J4: =SUMIFS('Stock Adjustment'!$E:$E,'Stock Adjustment'!$B:$B,$A4,'Stock Adjustment'!$D:$D,"Damaged") -> 0 | K4: =SUMIFS('Stock Adjustment'!$E:$E,'Stock Adjustment'!$B:$B,$A4,'Stock Adjustment'!$D:$D,"Expired") -> 0 | L4: =SUMIFS('Stock Adjustment'!$E:$E,'Stock Adjustment'!$B:$B,$A4,'Stock Adjustment'!$D:$D,"Supplier Returned") -> 0 | M4: =Table4[[#This Row],[Opening Stock]]+Table4[[#This Row],[Total Purchased]]+Table4[[#This Row],[Customer Returned]]-Table4[[#This Row],[Total Sold]]-Table4[[#This Row],[Damaged]]-Table4[[#This Row],[Expired]]-Table4[[#This Row],[Supplier Returned]]-Table4[[#This Row],[Staff Consumption]] -> 42 | N4: =IF(B4="","",VLOOKUP(B4,'Product Master'!$B:$G,4,FALSE)) -> 1200 | O4: =IF(B4="","",VLOOKUP(B4,'Product Master'!$B:$G,5,FALSE)) -> 1500 | P4: =IF(B4="","",VLOOKUP(B4,'Product Master'!$B:$I,7,FALSE)) -> 20 | Q4: =IFERROR(Table4[[#This Row],[Closing Stock]]*Table4[[#This Row],[Cost Price]],0) -> 50400 | R4: =IF(B4="","",IF(M4=0,"Out of Stock",IF(M4<=10,"Low Stock","In Stock"))) -> In Stock
A5: P0004 | B5: Semovita | C5: =IF(B5="","",VLOOKUP(B5,'Product Master'!$B:$G,2,FALSE)) -> Food | D5: =IF(B5="","",VLOOKUP(B5,'Product Master'!$B:$G,3,FALSE)) -> Piece | F5: =SUMIF('Stock Purchase'!$D:$D,B5,'Stock Purchase'!$F:$F) -> 50 | G5: =SUMIFS('Stock Adjustment'!$E:$E,'Stock Adjustment'!$B:$B,$A5,'Stock Adjustment'!$D:$D,"Customer Returned") -> 0 | H5: =SUMIF('Daily Sales Entry'!$D:$D,B5,'Daily Sales Entry'!$G:$G) -> 7 | I5: =SUMIFS('Stock Adjustment'!$E:$E,'Stock Adjustment'!$B:$B,$A5,'Stock Adjustment'!$D:$D,"Staff Consumption") -> 0 | J5: =SUMIFS('Stock Adjustment'!$E:$E,'Stock Adjustment'!$B:$B,$A5,'Stock Adjustment'!$D:$D,"Damaged") -> 0 | K5: =SUMIFS('Stock Adjustment'!$E:$E,'Stock Adjustment'!$B:$B,$A5,'Stock Adjustment'!$D:$D,"Expired") -> 0 | L5: =SUMIFS('Stock Adjustment'!$E:$E,'Stock Adjustment'!$B:$B,$A5,'Stock Adjustment'!$D:$D,"Supplier Returned") -> 0 | M5: =Table4[[#This Row],[Opening Stock]]+Table4[[#This Row],[Total Purchased]]+Table4[[#This Row],[Customer Returned]]-Table4[[#This Row],[Total Sold]]-Table4[[#This Row],[Damaged]]-Table4[[#This Row],[Expired]]-Table4[[#This Row],[Supplier Returned]]-Table4[[#This Row],[Staff Consumption]] -> 43 | N5: =IF(B5="","",VLOOKUP(B5,'Product Master'!$B:$G,4,FALSE)) -> 400 | O5: =IF(B5="","",VLOOKUP(B5,'Product Master'!$B:$G,5,FALSE)) -> 700 | P5: =IF(B5="","",VLOOKUP(B5,'Product Master'!$B:$I,7,FALSE)) -> 20 | Q5: =IFERROR(Table4[[#This Row],[Closing Stock]]*Table4[[#This Row],[Cost Price]],0) -> 17200 | R5: =IF(B5="","",IF(M5=0,"Out of Stock",IF(M5<=10,"Low Stock","In Stock"))) -> In Stock
A6: P0005 | B6: Eba | C6: =IF(B6="","",VLOOKUP(B6,'Product Master'!$B:$G,2,FALSE)) -> Food | D6: =IF(B6="","",VLOOKUP(B6,'Product Master'!$B:$G,3,FALSE)) -> Piece | F6: =SUMIF('Stock Purchase'!$D:$D,B6,'Stock Purchase'!$F:$F) -> 50 | G6: =SUMIFS('Stock Adjustment'!$E:$E,'Stock Adjustment'!$B:$B,$A6,'Stock Adjustment'!$D:$D,"Customer Returned") -> 0 | H6: =SUMIF('Daily Sales Entry'!$D:$D,B6,'Daily Sales Entry'!$G:$G) -> 3 | I6: =SUMIFS('Stock Adjustment'!$E:$E,'Stock Adjustment'!$B:$B,$A6,'Stock Adjustment'!$D:$D,"Staff Consumption") -> 0 | J6: =SUMIFS('Stock Adjustment'!$E:$E,'Stock Adjustment'!$B:$B,$A6,'Stock Adjustment'!$D:$D,"Damaged") -> 0 | K6: =SUMIFS('Stock Adjustment'!$E:$E,'Stock Adjustment'!$B:$B,$A6,'Stock Adjustment'!$D:$D,"Expired") -> 0 | L6: =SUMIFS('Stock Adjustment'!$E:$E,'Stock Adjustment'!$B:$B,$A6,'Stock Adjustment'!$D:$D,"Supplier Returned") -> 0 | M6: =Table4[[#This Row],[Opening Stock]]+Table4[[#This Row],[Total Purchased]]+Table4[[#This Row],[Customer Returned]]-Table4[[#This Row],[Total Sold]]-Table4[[#This Row],[Damaged]]-Table4[[#This Row],[Expired]]-Table4[[#This Row],[Supplier Returned]]-Table4[[#This Row],[Staff Consumption]] -> 47 | N6: =IF(B6="","",VLOOKUP(B6,'Product Master'!$B:$G,4,FALSE)) -> 200 | O6: =IF(B6="","",VLOOKUP(B6,'Product Master'!$B:$G,5,FALSE)) -> 500 | P6: =IF(B6="","",VLOOKUP(B6,'Product Master'!$B:$I,7,FALSE)) -> 20 | Q6: =IFERROR(Table4[[#This Row],[Closing Stock]]*Table4[[#This Row],[Cost Price]],0) -> 9400 | R6: =IF(B6="","",IF(M6=0,"Out of Stock",IF(M6<=10,"Low Stock","In Stock"))) -> In Stock
A7: P0006 | B7: Moin Moin | C7: =IF(B7="","",VLOOKUP(B7,'Product Master'!$B:$G,2,FALSE)) -> Food | D7: =IF(B7="","",VLOOKUP(B7,'Product Master'!$B:$G,3,FALSE)) -> Piece | F7: =SUMIF('Stock Purchase'!$D:$D,B7,'Stock Purchase'!$F:$F) -> 50 | G7: =SUMIFS('Stock Adjustment'!$E:$E,'Stock Adjustment'!$B:$B,$A7,'Stock Adjustment'!$D:$D,"Customer Returned") -> 0 | H7: =SUMIF('Daily Sales Entry'!$D:$D,B7,'Daily Sales Entry'!$G:$G) -> 19 | I7: =SUMIFS('Stock Adjustment'!$E:$E,'Stock Adjustment'!$B:$B,$A7,'Stock Adjustment'!$D:$D,"Staff Consumption") -> 0 | J7: =SUMIFS('Stock Adjustment'!$E:$E,'Stock Adjustment'!$B:$B,$A7,'Stock Adjustment'!$D:$D,"Damaged") -> 0 | K7: =SUMIFS('Stock Adjustment'!$E:$E,'Stock Adjustment'!$B:$B,$A7,'Stock Adjustment'!$D:$D,"Expired") -> 0 | L7: =SUMIFS('Stock Adjustment'!$E:$E,'Stock Adjustment'!$B:$B,$A7,'Stock Adjustment'!$D:$D,"Supplier Returned") -> 0 | M7: =Table4[[#This Row],[Opening Stock]]+Table4[[#This Row],[Total Purchased]]+Table4[[#This Row],[Customer Returned]]-Table4[[#This Row],[Total Sold]]-Table4[[#This Row],[Damaged]]-Table4[[#This Row],[Expired]]-Table4[[#This Row],[Supplier Returned]]-Table4[[#This Row],[Staff Consumption]] -> 31 | N7: =IF(B7="","",VLOOKUP(B7,'Product Master'!$B:$G,4,FALSE)) -> 500 | O7: =IF(B7="","",VLOOKUP(B7,'Product Master'!$B:$G,5,FALSE)) -> 800 | P7: =IF(B7="","",VLOOKUP(B7,'Product Master'!$B:$I,7,FALSE)) -> 20 | Q7: =IFERROR(Table4[[#This Row],[Closing Stock]]*Table4[[#This Row],[Cost Price]],0) -> 15500 | R7: =IF(B7="","",IF(M7=0,"Out of Stock",IF(M7<=10,"Low Stock","In Stock"))) -> In Stock
A8: P0007 | B8: Meat Pie | C8: =IF(B8="","",VLOOKUP(B8,'Product Master'!$B:$G,2,FALSE)) -> Snacks | D8: =IF(B8="","",VLOOKUP(B8,'Product Master'!$B:$G,3,FALSE)) -> Piece | F8: =SUMIF('Stock Purchase'!$D:$D,B8,'Stock Purchase'!$F:$F) -> 50 | G8: =SUMIFS('Stock Adjustment'!$E:$E,'Stock Adjustment'!$B:$B,$A8,'Stock Adjustment'!$D:$D,"Customer Returned") -> 0 | H8: =SUMIF('Daily Sales Entry'!$D:$D,B8,'Daily Sales Entry'!$G:$G) -> 3 | I8: =SUMIFS('Stock Adjustment'!$E:$E,'Stock Adjustment'!$B:$B,$A8,'Stock Adjustment'!$D:$D,"Staff Consumption") -> 0 | J8: =SUMIFS('Stock Adjustment'!$E:$E,'Stock Adjustment'!$B:$B,$A8,'Stock Adjustment'!$D:$D,"Damaged") -> 0 | K8: =SUMIFS('Stock Adjustment'!$E:$E,'Stock Adjustment'!$B:$B,$A8,'Stock Adjustment'!$D:$D,"Expired") -> 0 | L8: =SUMIFS('Stock Adjustment'!$E:$E,'Stock Adjustment'!$B:$B,$A8,'Stock Adjustment'!$D:$D,"Supplier Returned") -> 0 | M8: =Table4[[#This Row],[Opening Stock]]+Table4[[#This Row],[Total Purchased]]+Table4[[#This Row],[Customer Returned]]-Table4[[#This Row],[Total Sold]]-Table4[[#This Row],[Damaged]]-Table4[[#This Row],[Expired]]-Table4[[#This Row],[Supplier Returned]]-Table4[[#This Row],[Staff Consumption]] -> 47 | N8: =IF(B8="","",VLOOKUP(B8,'Product Master'!$B:$G,4,FALSE)) -> 500 | O8: =IF(B8="","",VLOOKUP(B8,'Product Master'!$B:$G,5,FALSE)) -> 900 | P8: =IF(B8="","",VLOOKUP(B8,'Product Master'!$B:$I,7,FALSE)) -> 20 | Q8: =IFERROR(Table4[[#This Row],[Closing Stock]]*Table4[[#This Row],[Cost Price]],0) -> 23500 | R8: =IF(B8="","",IF(M8=0,"Out of Stock",IF(M8<=10,"Low Stock","In Stock"))) -> In Stock
A9: P0008 | B9: Chicken Pie | C9: =IF(B9="","",VLOOKUP(B9,'Product Master'!$B:$G,2,FALSE)) -> Snacks | D9: =IF(B9="","",VLOOKUP(B9,'Product Master'!$B:$G,3,FALSE)) -> Piece | F9: =SUMIF('Stock Purchase'!$D:$D,B9,'Stock Purchase'!$F:$F) -> 50 | G9: =SUMIFS('Stock Adjustment'!$E:$E,'Stock Adjustment'!$B:$B,$A9,'Stock Adjustment'!$D:$D,"Customer Returned") -> 0 | H9: =SUMIF('Daily Sales Entry'!$D:$D,B9,'Daily Sales Entry'!$G:$G) -> 7 | I9: =SUMIFS('Stock Adjustment'!$E:$E,'Stock Adjustment'!$B:$B,$A9,'Stock Adjustment'!$D:$D,"Staff Consumption") -> 0 | J9: =SUMIFS('Stock Adjustment'!$E:$E,'Stock Adjustment'!$B:$B,$A9,'Stock Adjustment'!$D:$D,"Damaged") -> 0 | K9: =SUMIFS('Stock Adjustment'!$E:$E,'Stock Adjustment'!$B:$B,$A9,'Stock Adjustment'!$D:$D,"Expired") -> 0 | L9: =SUMIFS('Stock Adjustment'!$E:$E,'Stock Adjustment'!$B:$B,$A9,'Stock Adjustment'!$D:$D,"Supplier Returned") -> 0 | M9: =Table4[[#This Row],[Opening Stock]]+Table4[[#This Row],[Total Purchased]]+Table4[[#This Row],[Customer Returned]]-Table4[[#This Row],[Total Sold]]-Table4[[#This Row],[Damaged]]-Table4[[#This Row],[Expired]]-Table4[[#This Row],[Supplier Returned]]-Table4[[#This Row],[Staff Consumption]] -> 43 | N9: =IF(B9="","",VLOOKUP(B9,'Product Master'!$B:$G,4,FALSE)) -> 700 | O9: =IF(B9="","",VLOOKUP(B9,'Product Master'!$B:$G,5,FALSE)) -> 1000 | P9: =IF(B9="","",VLOOKUP(B9,'Product Master'!$B:$I,7,FALSE)) -> 20 | Q9: =IFERROR(Table4[[#This Row],[Closing Stock]]*Table4[[#This Row],[Cost Price]],0) -> 30100 | R9: =IF(B9="","",IF(M9=0,"Out of Stock",IF(M9<=10,"Low Stock","In Stock"))) -> In Stock
A10: P0009 | B10: Beef Roll | C10: =IF(B10="","",VLOOKUP(B10,'Product Master'!$B:$G,2,FALSE)) -> Snacks | D10: =IF(B10="","",VLOOKUP(B10,'Product Master'!$B:$G,3,FALSE)) -> Piece | F10: =SUMIF('Stock Purchase'!$D:$D,B10,'Stock Purchase'!$F:$F) -> 50 | G10: =SUMIFS('Stock Adjustment'!$E:$E,'Stock Adjustment'!$B:$B,$A10,'Stock Adjustment'!$D:$D,"Customer Returned") -> 0 | H10: =SUMIF('Daily Sales Entry'!$D:$D,B10,'Daily Sales Entry'!$G:$G) -> 5 | I10: =SUMIFS('Stock Adjustment'!$E:$E,'Stock Adjustment'!$B:$B,$A10,'Stock Adjustment'!$D:$D,"Staff Consumption") -> 0 | J10: =SUMIFS('Stock Adjustment'!$E:$E,'Stock Adjustment'!$B:$B,$A10,'Stock Adjustment'!$D:$D,"Damaged") -> 0 | K10: =SUMIFS('Stock Adjustment'!$E:$E,'Stock Adjustment'!$B:$B,$A10,'Stock Adjustment'!$D:$D,"Expired") -> 0 | L10: =SUMIFS('Stock Adjustment'!$E:$E,'Stock Adjustment'!$B:$B,$A10,'Stock Adjustment'!$D:$D,"Supplier Returned") -> 0 | M10: =Table4[[#This Row],[Opening Stock]]+Table4[[#This Row],[Total Purchased]]+Table4[[#This Row],[Customer Returned]]-Table4[[#This Row],[Total Sold]]-Table4[[#This Row],[Damaged]]-Table4[[#This Row],[Expired]]-Table4[[#This Row],[Supplier Returned]]-Table4[[#This Row],[Staff Consumption]] -> 45 | N10: =IF(B10="","",VLOOKUP(B10,'Product Master'!$B:$G,4,FALSE)) -> 400 | O10: =IF(B10="","",VLOOKUP(B10,'Product Master'!$B:$G,5,FALSE)) -> 700 | P10: =IF(B10="","",VLOOKUP(B10,'Product Master'!$B:$I,7,FALSE)) -> 20 | Q10: =IFERROR(Table4[[#This Row],[Closing Stock]]*Table4[[#This Row],[Cost Price]],0) -> 18000 | R10: =IF(B10="","",IF(M10=0,"Out of Stock",IF(M10<=10,"Low Stock","In Stock"))) -> In Stock
A11: P0010 | B11: Pet Lucozade Boost | C11: =IF(B11="","",VLOOKUP(B11,'Product Master'!$B:$G,2,FALSE)) -> Drinks | D11: =IF(B11="","",VLOOKUP(B11,'Product Master'!$B:$G,3,FALSE)) -> Pack | F11: =SUMIF('Stock Purchase'!$D:$D,B11,'Stock Purchase'!$F:$F) -> 70 | G11: =SUMIFS('Stock Adjustment'!$E:$E,'Stock Adjustment'!$B:$B,$A11,'Stock Adjustment'!$D:$D,"Customer Returned") -> 0 | H11: =SUMIF('Daily Sales Entry'!$D:$D,B11,'Daily Sales Entry'!$G:$G) -> 5 | I11: =SUMIFS('Stock Adjustment'!$E:$E,'Stock Adjustment'!$B:$B,$A11,'Stock Adjustment'!$D:$D,"Staff Consumption") -> 0 | J11: =SUMIFS('Stock Adjustment'!$E:$E,'Stock Adjustment'!$B:$B,$A11,'Stock Adjustment'!$D:$D,"Damaged") -> 0 | K11: =SUMIFS('Stock Adjustment'!$E:$E,'Stock Adjustment'!$B:$B,$A11,'Stock Adjustment'!$D:$D,"Expired") -> 0 | L11: =SUMIFS('Stock Adjustment'!$E:$E,'Stock Adjustment'!$B:$B,$A11,'Stock Adjustment'!$D:$D,"Supplier Returned") -> 0 | M11: =Table4[[#This Row],[Opening Stock]]+Table4[[#This Row],[Total Purchased]]+Table4[[#This Row],[Customer Returned]]-Table4[[#This Row],[Total Sold]]-Table4[[#This Row],[Damaged]]-Table4[[#This Row],[Expired]]-Table4[[#This Row],[Supplier Returned]]-Table4[[#This Row],[Staff Consumption]] -> 65 | N11: =IF(B11="","",VLOOKUP(B11,'Product Master'!$B:$G,4,FALSE)) -> 17000 | O11: =IF(B11="","",VLOOKUP(B11,'Product Master'!$B:$G,5,FALSE)) -> 20000 | P11: =IF(B11="","",VLOOKUP(B11,'Product Master'!$B:$I,7,FALSE)) -> 10 | Q11: =IFERROR(Table4[[#This Row],[Closing Stock]]*Table4[[#This Row],[Cost Price]],0) -> 1105000 | R11: =IF(B11="","",IF(M11=0,"Out of Stock",IF(M11<=10,"Low Stock","In Stock"))) -> In Stock
A12: P0011 | B12: Eva Water 0.75Cl | C12: =IF(B12="","",VLOOKUP(B12,'Product Master'!$B:$G,2,FALSE)) -> Drinks | D12: =IF(B12="","",VLOOKUP(B12,'Product Master'!$B:$G,3,FALSE)) -> Pack | F12: =SUMIF('Stock Purchase'!$D:$D,B12,'Stock Purchase'!$F:$F) -> 70 | G12: =SUMIFS('Stock Adjustment'!$E:$E,'Stock Adjustment'!$B:$B,$A12,'Stock Adjustment'!$D:$D,"Customer Returned") -> 0 | H12: =SUMIF('Daily Sales Entry'!$D:$D,B12,'Daily Sales Entry'!$G:$G) -> 7 | I12: =SUMIFS('Stock Adjustment'!$E:$E,'Stock Adjustment'!$B:$B,$A12,'Stock Adjustment'!$D:$D,"Staff Consumption") -> 0 | J12: =SUMIFS('Stock Adjustment'!$E:$E,'Stock Adjustment'!$B:$B,$A12,'Stock Adjustment'!$D:$D,"Damaged") -> 0 | K12: =SUMIFS('Stock Adjustment'!$E:$E,'Stock Adjustment'!$B:$B,$A12,'Stock Adjustment'!$D:$D,"Expired") -> 0 | L12: =SUMIFS('Stock Adjustment'!$E:$E,'Stock Adjustment'!$B:$B,$A12,'Stock Adjustment'!$D:$D,"Supplier Returned") -> 0 | M12: =Table4[[#This Row],[Opening Stock]]+Table4[[#This Row],[Total Purchased]]+Table4[[#This Row],[Customer Returned]]-Table4[[#This Row],[Total Sold]]-Table4[[#This Row],[Damaged]]-Table4[[#This Row],[Expired]]-Table4[[#This Row],[Supplier Returned]]-Table4[[#This Row],[Staff Consumption]] -> 63 | N12: =IF(B12="","",VLOOKUP(B12,'Product Master'!$B:$G,4,FALSE)) -> 5000 | O12: =IF(B12="","",VLOOKUP(B12,'Product Master'!$B:$G,5,FALSE)) -> 8500 | P12: =IF(B12="","",VLOOKUP(B12,'Product Master'!$B:$I,7,FALSE)) -> 10 | Q12: =IFERROR(Table4[[#This Row],[Closing Stock]]*Table4[[#This Row],[Cost Price]],0) -> 315000 | R12: =IF(B12="","",IF(M12=0,"Out of Stock",IF(M12<=10,"Low Stock","In Stock"))) -> In Stock
A13: P0012 | B13: Lucozade Sport Pet 50cl | C13: =IF(B13="","",VLOOKUP(B13,'Product Master'!$B:$G,2,FALSE)) -> Drinks | D13: =IF(B13="","",VLOOKUP(B13,'Product Master'!$B:$G,3,FALSE)) -> Pack | F13: =SUMIF('Stock Purchase'!$D:$D,B13,'Stock Purchase'!$F:$F) -> 50 | G13: =SUMIFS('Stock Adjustment'!$E:$E,'Stock Adjustment'!$B:$B,$A13,'Stock Adjustment'!$D:$D,"Customer Returned") -> 0 | H13: =SUMIF('Daily Sales Entry'!$D:$D,B13,'Daily Sales Entry'!$G:$G) -> 5 | I13: =SUMIFS('Stock Adjustment'!$E:$E,'Stock Adjustment'!$B:$B,$A13,'Stock Adjustment'!$D:$D,"Staff Consumption") -> 0 | J13: =SUMIFS('Stock Adjustment'!$E:$E,'Stock Adjustment'!$B:$B,$A13,'Stock Adjustment'!$D:$D,"Damaged") -> 0 | K13: =SUMIFS('Stock Adjustment'!$E:$E,'Stock Adjustment'!$B:$B,$A13,'Stock Adjustment'!$D:$D,"Expired") -> 0 | L13: =SUMIFS('Stock Adjustment'!$E:$E,'Stock Adjustment'!$B:$B,$A13,'Stock Adjustment'!$D:$D,"Supplier Returned") -> 0 | M13: =Table4[[#This Row],[Opening Stock]]+Table4[[#This Row],[Total Purchased]]+Table4[[#This Row],[Customer Returned]]-Table4[[#This Row],[Total Sold]]-Table4[[#This Row],[Damaged]]-Table4[[#This Row],[Expired]]-Table4[[#This Row],[Supplier Returned]]-Table4[[#This Row],[Staff Consumption]] -> 45 | N13: =IF(B13="","",VLOOKUP(B13,'Product Master'!$B:$G,4,FALSE)) -> 900 | O13: =IF(B13="","",VLOOKUP(B13,'Product Master'!$B:$G,5,FALSE)) -> 1500 | P13: =IF(B13="","",VLOOKUP(B13,'Product Master'!$B:$I,7,FALSE)) -> 20 | Q13: =IFERROR(Table4[[#This Row],[Closing Stock]]*Table4[[#This Row],[Cost Price]],0) -> 40500 | R13: =IF(B13="","",IF(M13=0,"Out of Stock",IF(M13<=10,"Low Stock","In Stock"))) -> In Stock
A14: P0013 | B14: FAB Energy Drinks | C14: =IF(B14="","",VLOOKUP(B14,'Product Master'!$B:$G,2,FALSE)) -> Drinks | D14: =IF(B14="","",VLOOKUP(B14,'Product Master'!$B:$G,3,FALSE)) -> Pack | F14: =SUMIF('Stock Purchase'!$D:$D,B14,'Stock Purchase'!$F:$F) -> 50 | G14: =SUMIFS('Stock Adjustment'!$E:$E,'Stock Adjustment'!$B:$B,$A14,'Stock Adjustment'!$D:$D,"Customer Returned") -> 0 | H14: =SUMIF('Daily Sales Entry'!$D:$D,B14,'Daily Sales Entry'!$G:$G) -> 5 | I14: =SUMIFS('Stock Adjustment'!$E:$E,'Stock Adjustment'!$B:$B,$A14,'Stock Adjustment'!$D:$D,"Staff Consumption") -> 0 | J14: =SUMIFS('Stock Adjustment'!$E:$E,'Stock Adjustment'!$B:$B,$A14,'Stock Adjustment'!$D:$D,"Damaged") -> 0 | K14: =SUMIFS('Stock Adjustment'!$E:$E,'Stock Adjustment'!$B:$B,$A14,'Stock Adjustment'!$D:$D,"Expired") -> 0 | L14: =SUMIFS('Stock Adjustment'!$E:$E,'Stock Adjustment'!$B:$B,$A14,'Stock Adjustment'!$D:$D,"Supplier Returned") -> 0 | M14: =Table4[[#This Row],[Opening Stock]]+Table4[[#This Row],[Total Purchased]]+Table4[[#This Row],[Customer Returned]]-Table4[[#This Row],[Total Sold]]-Table4[[#This Row],[Damaged]]-Table4[[#This Row],[Expired]]-Table4[[#This Row],[Supplier Returned]]-Table4[[#This Row],[Staff Consumption]] -> 45 | N14: =IF(B14="","",VLOOKUP(B14,'Product Master'!$B:$G,4,FALSE)) -> 1000 | O14: =IF(B14="","",VLOOKUP(B14,'Product Master'!$B:$G,5,FALSE)) -> 1500 | P14: =IF(B14="","",VLOOKUP(B14,'Product Master'!$B:$I,7,FALSE)) -> 20 | Q14: =IFERROR(Table4[[#This Row],[Closing Stock]]*Table4[[#This Row],[Cost Price]],0) -> 45000 | R14: =IF(B14="","",IF(M14=0,"Out of Stock",IF(M14<=10,"Low Stock","In Stock"))) -> In Stock
... A16: P0015 | B16: Malta Guinness 33cl Cans | C16: =IF(B16="","",VLOOKUP(B16,'Product Master'!$B:$G,2,FALSE)) -> Drinks | D16: =IF(B16="","",VLOOKUP(B16,'Product Master'!$B:$G,3,FALSE)) -> Pack | F16: =SUMIF('Stock Purchase'!$D:$D,B16,'Stock Purchase'!$F:$F) -> 50 | G16: =SUMIFS('Stock Adjustment'!$E:$E,'Stock Adjustment'!$B:$B,$A16,'Stock Adjustment'!$D:$D,"Customer Returned") -> 0 | H16: =SUMIF('Daily Sales Entry'!$D:$D,B16,'Daily Sales Entry'!$G:$G) -> 5 | I16: =SUMIFS('Stock Adjustment'!$E:$E,'Stock Adjustment'!$B:$B,$A16,'Stock Adjustment'!$D:$D,"Staff Consumption") -> 0 | J16: =SUMIFS('Stock Adjustment'!$E:$E,'Stock Adjustment'!$B:$B,$A16,'Stock Adjustment'!$D:$D,"Damaged") -> 0 | K16: =SUMIFS('Stock Adjustment'!$E:$E,'Stock Adjustment'!$B:$B,$A16,'Stock Adjustment'!$D:$D,"Expired") -> 0 | L16: =SUMIFS('Stock Adjustment'!$E:$E,'Stock Adjustment'!$B:$B,$A16,'Stock Adjustment'!$D:$D,"Supplier Returned") -> 0 | M16: =Table4[[#This Row],[Opening Stock]]+Table4[[#This Row],[Total Purchased]]+Table4[[#This Row],[Customer Returned]]-Table4[[#This Row],[Total Sold]]-Table4[[#This Row],[Damaged]]-Table4[[#This Row],[Expired]]-Table4[[#This Row],[Supplier Returned]]-Table4[[#This Row],[Staff Consumption]] -> 45 | N16: =IF(B16="","",VLOOKUP(B16,'Product Master'!$B:$G,4,FALSE)) -> 900 | O16: =IF(B16="","",VLOOKUP(B16,'Product Master'!$B:$G,5,FALSE)) -> 1500 | P16: =IF(B16="","",VLOOKUP(B16,'Product Master'!$B:$I,7,FALSE)) -> 20 | Q16: =IFERROR(Table4[[#This Row],[Closing Stock]]*Table4[[#This Row],[Cost Price]],0) -> 40500 | R16: =IF(B16="","",IF(M16=0,"Out of Stock",IF(M16<=10,"Low Stock","In Stock"))) -> In Stock
A17: P0016 | C17: =IF(B17="","",VLOOKUP(B17,'Product Master'!$B:$G,2,FALSE)) | D17: =IF(B17="","",VLOOKUP(B17,'Product Master'!$B:$G,3,FALSE)) | F17: =SUMIF('Stock Purchase'!$D:$D,B17,'Stock Purchase'!$F:$F) -> 0 | G17: =SUMIFS('Stock Adjustment'!$E:$E,'Stock Adjustment'!$B:$B,$A17,'Stock Adjustment'!$D:$D,"Customer Returned") -> 0 | H17: =SUMIF('Daily Sales Entry'!$D:$D,B17,'Daily Sales Entry'!$G:$G) -> 0 | I17: =SUMIFS('Stock Adjustment'!$E:$E,'Stock Adjustment'!$B:$B,$A17,'Stock Adjustment'!$D:$D,"Staff Consumption") -> 0 | J17: =SUMIFS('Stock Adjustment'!$E:$E,'Stock Adjustment'!$B:$B,$A17,'Stock Adjustment'!$D:$D,"Damaged") -> 0 | K17: =SUMIFS('Stock Adjustment'!$E:$E,'Stock Adjustment'!$B:$B,$A17,'Stock Adjustment'!$D:$D,"Expired") -> 0 | L17: =SUMIFS('Stock Adjustment'!$E:$E,'Stock Adjustment'!$B:$B,$A17,'Stock Adjustment'!$D:$D,"Supplier Returned") -> 0 | M17: =Table4[[#This Row],[Opening Stock]]+Table4[[#This Row],[Total Purchased]]+Table4[[#This Row],[Customer Returned]]-Table4[[#This Row],[Total Sold]]-Table4[[#This Row],[Damaged]]-Table4[[#This Row],[Expired]]-Table4[[#This Row],[Supplier Returned]]-Table4[[#This Row],[Staff Consumption]] -> 0 | N17: =IF(B17="","",VLOOKUP(B17,'Product Master'!$B:$G,4,FALSE)) | O17: =IF(B17="","",VLOOKUP(B17,'Product Master'!$B:$G,5,FALSE)) | P17: =IF(B17="","",VLOOKUP(B17,'Product Master'!$B:$I,7,FALSE)) | Q17: =IFERROR(Table4[[#This Row],[Closing Stock]]*Table4[[#This Row],[Cost Price]],0) -> 0 | R17: =IF(B17="","",IF(M17=0,"Out of Stock",IF(M17<=10,"Low Stock","In Stock")))
A18: P0017 | C18: =IF(B18="","",VLOOKUP(B18,'Product Master'!$B:$G,2,FALSE)) | D18: =IF(B18="","",VLOOKUP(B18,'Product Master'!$B:$G,3,FALSE)) | F18: =SUMIF('Stock Purchase'!$D:$D,B18,'Stock Purchase'!$F:$F) -> 0 | G18: =SUMIFS('Stock Adjustment'!$E:$E,'Stock Adjustment'!$B:$B,$A18,'Stock Adjustment'!$D:$D,"Customer Returned") -> 0 | H18: =SUMIF('Daily Sales Entry'!$D:$D,B18,'Daily Sales Entry'!$G:$G) -> 0 | I18: =SUMIFS('Stock Adjustment'!$E:$E,'Stock Adjustment'!$B:$B,$A18,'Stock Adjustment'!$D:$D,"Staff Consumption") -> 0 | J18: =SUMIFS('Stock Adjustment'!$E:$E,'Stock Adjustment'!$B:$B,$A18,'Stock Adjustment'!$D:$D,"Damaged") -> 0 | K18: =SUMIFS('Stock Adjustment'!$E:$E,'Stock Adjustment'!$B:$B,$A18,'Stock Adjustment'!$D:$D,"Expired") -> 0 | L18: =SUMIFS('Stock Adjustment'!$E:$E,'Stock Adjustment'!$B:$B,$A18,'Stock Adjustment'!$D:$D,"Supplier Returned") -> 0 | M18: =Table4[[#This Row],[Opening Stock]]+Table4[[#This Row],[Total Purchased]]+Table4[[#This Row],[Customer Returned]]-Table4[[#This Row],[Total Sold]]-Table4[[#This Row],[Damaged]]-Table4[[#This Row],[Expired]]-Table4[[#This Row],[Supplier Returned]]-Table4[[#This Row],[Staff Consumption]] -> 0 | N18: =IF(B18="","",VLOOKUP(B18,'Product Master'!$B:$G,4,FALSE)) | O18: =IF(B18="","",VLOOKUP(B18,'Product Master'!$B:$G,5,FALSE)) | P18: =IF(B18="","",VLOOKUP(B18,'Product Master'!$B:$I,7,FALSE)) | Q18: =IFERROR(Table4[[#This Row],[Closing Stock]]*Table4[[#This Row],[Cost Price]],0) -> 0 | R18: =IF(B18="","",IF(M18=0,"Out of Stock",IF(M18<=10,"Low Stock","In Stock")))
A19: P0018 | C19: =IF(B19="","",VLOOKUP(B19,'Product Master'!$B:$G,2,FALSE)) | D19: =IF(B19="","",VLOOKUP(B19,'Product Master'!$B:$G,3,FALSE)) | F19: =SUMIF('Stock Purchase'!$D:$D,B19,'Stock Purchase'!$F:$F) -> 0 | G19: =SUMIFS('Stock Adjustment'!$E:$E,'Stock Adjustment'!$B:$B,$A19,'Stock Adjustment'!$D:$D,"Customer Returned") -> 0 | H19: =SUMIF('Daily Sales Entry'!$D:$D,B19,'Daily Sales Entry'!$G:$G) -> 0 | I19: =SUMIFS('Stock Adjustment'!$E:$E,'Stock Adjustment'!$B:$B,$A19,'Stock Adjustment'!$D:$D,"Staff Consumption") -> 0 | J19: =SUMIFS('Stock Adjustment'!$E:$E,'Stock Adjustment'!$B:$B,$A19,'Stock Adjustment'!$D:$D,"Damaged") -> 0 | K19: =SUMIFS('Stock Adjustment'!$E:$E,'Stock Adjustment'!$B:$B,$A19,'Stock Adjustment'!$D:$D,"Expired") -> 0 | L19: =SUMIFS('Stock Adjustment'!$E:$E,'Stock Adjustment'!$B:$B,$A19,'Stock Adjustment'!$D:$D,"Supplier Returned") -> 0 | M19: =Table4[[#This Row],[Opening Stock]]+Table4[[#This Row],[Total Purchased]]+Table4[[#This Row],[Customer Returned]]-Table4[[#This Row],[Total Sold]]-Table4[[#This Row],[Damaged]]-Table4[[#This Row],[Expired]]-Table4[[#This Row],[Supplier Returned]]-Table4[[#This Row],[Staff Consumption]] -> 0 | N19: =IF(B19="","",VLOOKUP(B19,'Product Master'!$B:$G,4,FALSE)) | O19: =IF(B19="","",VLOOKUP(B19,'Product Master'!$B:$G,5,FALSE)) | P19: =IF(B19="","",VLOOKUP(B19,'Product Master'!$B:$I,7,FALSE)) | Q19: =IFERROR(Table4[[#This Row],[Closing Stock]]*Table4[[#This Row],[Cost Price]],0) -> 0 | R19: =IF(B19="","",IF(M19=0,"Out of Stock",IF(M19<=10,"Low Stock","In Stock")))
A20: P0019 | C20: =IF(B20="","",VLOOKUP(B20,'Product Master'!$B:$G,2,FALSE)) | D20: =IF(B20="","",VLOOKUP(B20,'Product Master'!$B:$G,3,FALSE)) | F20: =SUMIF('Stock Purchase'!$D:$D,B20,'Stock Purchase'!$F:$F) -> 0 | G20: =SUMIFS('Stock Adjustment'!$E:$E,'Stock Adjustment'!$B:$B,$A20,'Stock Adjustment'!$D:$D,"Customer Returned") -> 0 | H20: =SUMIF('Daily Sales Entry'!$D:$D,B20,'Daily Sales Entry'!$G:$G) -> 0 | I20: =SUMIFS('Stock Adjustment'!$E:$E,'Stock Adjustment'!$B:$B,$A20,'Stock Adjustment'!$D:$D,"Staff Consumption") -> 0 | J20: =SUMIFS('Stock Adjustment'!$E:$E,'Stock Adjustment'!$B:$B,$A20,'Stock Adjustment'!$D:$D,"Damaged") -> 0 | K20: =SUMIFS('Stock Adjustment'!$E:$E,'Stock Adjustment'!$B:$B,$A20,'Stock Adjustment'!$D:$D,"Expired") -> 0 | L20: =SUMIFS('Stock Adjustment'!$E:$E,'Stock Adjustment'!$B:$B,$A20,'Stock Adjustment'!$D:$D,"Supplier Returned") -> 0 | M20: =Table4[[#This Row],[Opening Stock]]+Table4[[#This Row],[Total Purchased]]+Table4[[#This Row],[Customer Returned]]-Table4[[#This Row],[Total Sold]]-Table4[[#This Row],[Damaged]]-Table4[[#This Row],[Expired]]-Table4[[#This Row],[Supplier Returned]]-Table4[[#This Row],[Staff Consumption]] -> 0 | N20: =IF(B20="","",VLOOKUP(B20,'Product Master'!$B:$G,4,FALSE)) | O20: =IF(B20="","",VLOOKUP(B20,'Product Master'!$B:$G,5,FALSE)) | P20: =IF(B20="","",VLOOKUP(B20,'Product Master'!$B:$I,7,FALSE)) | Q20: =IFERROR(Table4[[#This Row],[Closing Stock]]*Table4[[#This Row],[Cost Price]],0) -> 0 | R20: =IF(B20="","",IF(M20=0,"Out of Stock",IF(M20<=10,"Low Stock","In Stock")))
A21: P0020 | C21: =IF(B21="","",VLOOKUP(B21,'Product Master'!$B:$G,2,FALSE)) | D21: =IF(B21="","",VLOOKUP(B21,'Product Master'!$B:$G,3,FALSE)) | F21: =SUMIF('Stock Purchase'!$D:$D,B21,'Stock Purchase'!$F:$F) -> 0 | G21: =SUMIFS('Stock Adjustment'!$E:$E,'Stock Adjustment'!$B:$B,$A21,'Stock Adjustment'!$D:$D,"Customer Returned") -> 0 | H21: =SUMIF('Daily Sales Entry'!$D:$D,B21,'Daily Sales Entry'!$G:$G) -> 0 | I21: =SUMIFS('Stock Adjustment'!$E:$E,'Stock Adjustment'!$B:$B,$A21,'Stock Adjustment'!$D:$D,"Staff Consumption") -> 0 | J21: =SUMIFS('Stock Adjustment'!$E:$E,'Stock Adjustment'!$B:$B,$A21,'Stock Adjustment'!$D:$D,"Damaged") -> 0 | K21: =SUMIFS('Stock Adjustment'!$E:$E,'Stock Adjustment'!$B:$B,$A21,'Stock Adjustment'!$D:$D,"Expired") -> 0 | L21: =SUMIFS('Stock Adjustment'!$E:$E,'Stock Adjustment'!$B:$B,$A21,'Stock Adjustment'!$D:$D,"Supplier Returned") -> 0 | M21: =Table4[[#This Row],[Opening Stock]]+Table4[[#This Row],[Total Purchased]]+Table4[[#This Row],[Customer Returned]]-Table4[[#This Row],[Total Sold]]-Table4[[#This Row],[Damaged]]-Table4[[#This Row],[Expired]]-Table4[[#This Row],[Supplier Returned]]-Table4[[#This Row],[Staff Consumption]] -> 0 | N21: =IF(B21="","",VLOOKUP(B21,'Product Master'!$B:$G,4,FALSE)) | O21: =IF(B21="","",VLOOKUP(B21,'Product Master'!$B:$G,5,FALSE)) | P21: =IF(B21="","",VLOOKUP(B21,'Product Master'!$B:$I,7,FALSE)) | Q21: =IFERROR(Table4[[#This Row],[Closing Stock]]*Table4[[#This Row],[Cost Price]],0) -> 0 | R21: =IF(B21="","",IF(M21=0,"Out of Stock",IF(M21<=10,"Low Stock","In Stock")))
A22: P0021 | C22: =IF(B22="","",VLOOKUP(B22,'Product Master'!$B:$G,2,FALSE)) | D22: =IF(B22="","",VLOOKUP(B22,'Product Master'!$B:$G,3,FALSE)) | F22: =SUMIF('Stock Purchase'!$D:$D,B22,'Stock Purchase'!$F:$F) -> 0 | G22: =SUMIFS('Stock Adjustment'!$E:$E,'Stock Adjustment'!$B:$B,$A22,'Stock Adjustment'!$D:$D,"Customer Returned") -> 0 | H22: =SUMIF('Daily Sales Entry'!$D:$D,B22,'Daily Sales Entry'!$G:$G) -> 0 | I22: =SUMIFS('Stock Adjustment'!$E:$E,'Stock Adjustment'!$B:$B,$A22,'Stock Adjustment'!$D:$D,"Staff Consumption") -> 0 | J22: =SUMIFS('Stock Adjustment'!$E:$E,'Stock Adjustment'!$B:$B,$A22,'Stock Adjustment'!$D:$D,"Damaged") -> 0 | K22: =SUMIFS('Stock Adjustment'!$E:$E,'Stock Adjustment'!$B:$B,$A22,'Stock Adjustment'!$D:$D,"Expired") -> 0 | L22: =SUMIFS('Stock Adjustment'!$E:$E,'Stock Adjustment'!$B:$B,$A22,'Stock Adjustment'!$D:$D,"Supplier Returned") -> 0 | M22: =Table4[[#This Row],[Opening Stock]]+Table4[[#This Row],[Total Purchased]]+Table4[[#This Row],[Customer Returned]]-Table4[[#This Row],[Total Sold]]-Table4[[#This Row],[Damaged]]-Table4[[#This Row],[Expired]]-Table4[[#This Row],[Supplier Returned]]-Table4[[#This Row],[Staff Consumption]] -> 0 | N22: =IF(B22="","",VLOOKUP(B22,'Product Master'!$B:$G,4,FALSE)) | O22: =IF(B22="","",VLOOKUP(B22,'Product Master'!$B:$G,5,FALSE)) | P22: =IF(B22="","",VLOOKUP(B22,'Product Master'!$B:$I,7,FALSE)) | Q22: =IFERROR(Table4[[#This Row],[Closing Stock]]*Table4[[#This Row],[Cost Price]],0) -> 0 | R22: =IF(B22="","",IF(M22=0,"Out of Stock",IF(M22<=10,"Low Stock","In Stock")))
A23: P0022 | C23: =IF(B23="","",VLOOKUP(B23,'Product Master'!$B:$G,2,FALSE)) | D23: =IF(B23="","",VLOOKUP(B23,'Product Master'!$B:$G,3,FALSE)) | F23: =SUMIF('Stock Purchase'!$D:$D,B23,'Stock Purchase'!$F:$F) -> 0 | G23: =SUMIFS('Stock Adjustment'!$E:$E,'Stock Adjustment'!$B:$B,$A23,'Stock Adjustment'!$D:$D,"Customer Returned") -> 0 | H23: =SUMIF('Daily Sales Entry'!$D:$D,B23,'Daily Sales Entry'!$G:$G) -> 0 | I23: =SUMIFS('Stock Adjustment'!$E:$E,'Stock Adjustment'!$B:$B,$A23,'Stock Adjustment'!$D:$D,"Staff Consumption") -> 0 | J23: =SUMIFS('Stock Adjustment'!$E:$E,'Stock Adjustment'!$B:$B,$A23,'Stock Adjustment'!$D:$D,"Damaged") -> 0 | K23: =SUMIFS('Stock Adjustment'!$E:$E,'Stock Adjustment'!$B:$B,$A23,'Stock Adjustment'!$D:$D,"Expired") -> 0 | L23: =SUMIFS('Stock Adjustment'!$E:$E,'Stock Adjustment'!$B:$B,$A23,'Stock Adjustment'!$D:$D,"Supplier Returned") -> 0 | M23: =Table4[[#This Row],[Opening Stock]]+Table4[[#This Row],[Total Purchased]]+Table4[[#This Row],[Customer Returned]]-Table4[[#This Row],[Total Sold]]-Table4[[#This Row],[Damaged]]-Table4[[#This Row],[Expired]]-Table4[[#This Row],[Supplier Returned]]-Table4[[#This Row],[Staff Consumption]] -> 0 | N23: =IF(B23="","",VLOOKUP(B23,'Product Master'!$B:$G,4,FALSE)) | O23: =IF(B23="","",VLOOKUP(B23,'Product Master'!$B:$G,5,FALSE)) | P23: =IF(B23="","",VLOOKUP(B23,'Product Master'!$B:$I,7,FALSE)) | Q23: =IFERROR(Table4[[#This Row],[Closing Stock]]*Table4[[#This Row],[Cost Price]],0) -> 0 | R23: =IF(B23="","",IF(M23=0,"Out of Stock",IF(M23<=10,"Low Stock","In Stock")))
A24: P0023 | C24: =IF(B24="","",VLOOKUP(B24,'Product Master'!$B:$G,2,FALSE)) | D24: =IF(B24="","",VLOOKUP(B24,'Product Master'!$B:$G,3,FALSE)) | F24: =SUMIF('Stock Purchase'!$D:$D,B24,'Stock Purchase'!$F:$F) -> 0 | G24: =SUMIFS('Stock Adjustment'!$E:$E,'Stock Adjustment'!$B:$B,$A24,'Stock Adjustment'!$D:$D,"Customer Returned") -> 0 | H24: =SUMIF('Daily Sales Entry'!$D:$D,B24,'Daily Sales Entry'!$G:$G) -> 0 | I24: =SUMIFS('Stock Adjustment'!$E:$E,'Stock Adjustment'!$B:$B,$A24,'Stock Adjustment'!$D:$D,"Staff Consumption") -> 0 | J24: =SUMIFS('Stock Adjustment'!$E:$E,'Stock Adjustment'!$B:$B,$A24,'Stock Adjustment'!$D:$D,"Damaged") -> 0 | K24: =SUMIFS('Stock Adjustment'!$E:$E,'Stock Adjustment'!$B:$B,$A24,'Stock Adjustment'!$D:$D,"Expired") -> 0 | L24: =SUMIFS('Stock Adjustment'!$E:$E,'Stock Adjustment'!$B:$B,$A24,'Stock Adjustment'!$D:$D,"Supplier Returned") -> 0 | M24: =Table4[[#This Row],[Opening Stock]]+Table4[[#This Row],[Total Purchased]]+Table4[[#This Row],[Customer Returned]]-Table4[[#This Row],[Total Sold]]-Table4[[#This Row],[Damaged]]-Table4[[#This Row],[Expired]]-Table4[[#This Row],[Supplier Returned]]-Table4[[#This Row],[Staff Consumption]] -> 0 | N24: =IF(B24="","",VLOOKUP(B24,'Product Master'!$B:$G,4,FALSE)) | O24: =IF(B24="","",VLOOKUP(B24,'Product Master'!$B:$G,5,FALSE)) | P24: =IF(B24="","",VLOOKUP(B24,'Product Master'!$B:$I,7,FALSE)) | Q24: =IFERROR(Table4[[#This Row],[Closing Stock]]*Table4[[#This Row],[Cost Price]],0) -> 0 | R24: =IF(B24="","",IF(M24=0,"Out of Stock",IF(M24<=10,"Low Stock","In Stock")))
A25: P0024 | C25: =IF(B25="","",VLOOKUP(B25,'Product Master'!$B:$G,2,FALSE)) | D25: =IF(B25="","",VLOOKUP(B25,'Product Master'!$B:$G,3,FALSE)) | F25: =SUMIF('Stock Purchase'!$D:$D,B25,'Stock Purchase'!$F:$F) -> 0 | G25: =SUMIFS('Stock Adjustment'!$E:$E,'Stock Adjustment'!$B:$B,$A25,'Stock Adjustment'!$D:$D,"Customer Returned") -> 0 | H25: =SUMIF('Daily Sales Entry'!$D:$D,B25,'Daily Sales Entry'!$G:$G) -> 0 | I25: =SUMIFS('Stock Adjustment'!$E:$E,'Stock Adjustment'!$B:$B,$A25,'Stock Adjustment'!$D:$D,"Staff Consumption") -> 0 | J25: =SUMIFS('Stock Adjustment'!$E:$E,'Stock Adjustment'!$B:$B,$A25,'Stock Adjustment'!$D:$D,"Damaged") -> 0 | K25: =SUMIFS('Stock Adjustment'!$E:$E,'Stock Adjustment'!$B:$B,$A25,'Stock Adjustment'!$D:$D,"Expired") -> 0 | L25: =SUMIFS('Stock Adjustment'!$E:$E,'Stock Adjustment'!$B:$B,$A25,'Stock Adjustment'!$D:$D,"Supplier Returned") -> 0 | M25: =Table4[[#This Row],[Opening Stock]]+Table4[[#This Row],[Total Purchased]]+Table4[[#This Row],[Customer Returned]]-Table4[[#This Row],[Total Sold]]-Table4[[#This Row],[Damaged]]-Table4[[#This Row],[Expired]]-Table4[[#This Row],[Supplier Returned]]-Table4[[#This Row],[Staff Consumption]] -> 0 | N25: =IF(B25="","",VLOOKUP(B25,'Product Master'!$B:$G,4,FALSE)) | O25: =IF(B25="","",VLOOKUP(B25,'Product Master'!$B:$G,5,FALSE)) | P25: =IF(B25="","",VLOOKUP(B25,'Product Master'!$B:$I,7,FALSE)) | Q25: =IFERROR(Table4[[#This Row],[Closing Stock]]*Table4[[#This Row],[Cost Price]],0) -> 0 | R25: =IF(B25="","",IF(M25=0,"Out of Stock",IF(M25<=10,"Low Stock","In Stock")))
A26: P0025 | C26: =IF(B26="","",VLOOKUP(B26,'Product Master'!$B:$G,2,FALSE)) | D26: =IF(B26="","",VLOOKUP(B26,'Product Master'!$B:$G,3,FALSE)) | F26: =SUMIF('Stock Purchase'!$D:$D,B26,'Stock Purchase'!$F:$F) -> 0 | G26: =SUMIFS('Stock Adjustment'!$E:$E,'Stock Adjustment'!$B:$B,$A26,'Stock Adjustment'!$D:$D,"Customer Returned") -> 0 | H26: =SUMIF('Daily Sales Entry'!$D:$D,B26,'Daily Sales Entry'!$G:$G) -> 0 | I26: =SUMIFS('Stock Adjustment'!$E:$E,'Stock Adjustment'!$B:$B,$A26,'Stock Adjustment'!$D:$D,"Staff Consumption") -> 0 | J26: =SUMIFS('Stock Adjustment'!$E:$E,'Stock Adjustment'!$B:$B,$A26,'Stock Adjustment'!$D:$D,"Damaged") -> 0 | K26: =SUMIFS('Stock Adjustment'!$E:$E,'Stock Adjustment'!$B:$B,$A26,'Stock Adjustment'!$D:$D,"Expired") -> 0 | L26: =SUMIFS('Stock Adjustment'!$E:$E,'Stock Adjustment'!$B:$B,$A26,'Stock Adjustment'!$D:$D,"Supplier Returned") -> 0 | M26: =Table4[[#This Row],[Opening Stock]]+Table4[[#This Row],[Total Purchased]]+Table4[[#This Row],[Customer Returned]]-Table4[[#This Row],[Total Sold]]-Table4[[#This Row],[Damaged]]-Table4[[#This Row],[Expired]]-Table4[[#This Row],[Supplier Returned]]-Table4[[#This Row],[Staff Consumption]] -> 0 | N26: =IF(B26="","",VLOOKUP(B26,'Product Master'!$B:$G,4,FALSE)) | O26: =IF(B26="","",VLOOKUP(B26,'Product Master'!$B:$G,5,FALSE)) | P26: =IF(B26="","",VLOOKUP(B26,'Product Master'!$B:$I,7,FALSE)) | Q26: =IFERROR(Table4[[#This Row],[Closing Stock]]*Table4[[#This Row],[Cost Price]],0) -> 0 | R26: =IF(B26="","",IF(M26=0,"Out of Stock",IF(M26<=10,"Low Stock","In Stock")))
A27: P0026 | C27: =IF(B27="","",VLOOKUP(B27,'Product Master'!$B:$G,2,FALSE)) | D27: =IF(B27="","",VLOOKUP(B27,'Product Master'!$B:$G,3,FALSE)) | F27: =SUMIF('Stock Purchase'!$D:$D,B27,'Stock Purchase'!$F:$F) -> 0 | G27: =SUMIFS('Stock Adjustment'!$E:$E,'Stock Adjustment'!$B:$B,$A27,'Stock Adjustment'!$D:$D,"Customer Returned") -> 0 | H27: =SUMIF('Daily Sales Entry'!$D:$D,B27,'Daily Sales Entry'!$G:$G) -> 0 | I27: =SUMIFS('Stock Adjustment'!$E:$E,'Stock Adjustment'!$B:$B,$A27,'Stock Adjustment'!$D:$D,"Staff Consumption") -> 0 | J27: =SUMIFS('Stock Adjustment'!$E:$E,'Stock Adjustment'!$B:$B,$A27,'Stock Adjustment'!$D:$D,"Damaged") -> 0 | K27: =SUMIFS('Stock Adjustment'!$E:$E,'Stock Adjustment'!$B:$B,$A27,'Stock Adjustment'!$D:$D,"Expired") -> 0 | L27: =SUMIFS('Stock Adjustment'!$E:$E,'Stock Adjustment'!$B:$B,$A27,'Stock Adjustment'!$D:$D,"Supplier Returned") -> 0 | M27: =Table4[[#This Row],[Opening Stock]]+Table4[[#This Row],[Total Purchased]]+Table4[[#This Row],[Customer Returned]]-Table4[[#This Row],[Total Sold]]-Table4[[#This Row],[Damaged]]-Table4[[#This Row],[Expired]]-Table4[[#This Row],[Supplier Returned]]-Table4[[#This Row],[Staff Consumption]] -> 0 | N27: =IF(B27="","",VLOOKUP(B27,'Product Master'!$B:$G,4,FALSE)) | O27: =IF(B27="","",VLOOKUP(B27,'Product Master'!$B:$G,5,FALSE)) | P27: =IF(B27="","",VLOOKUP(B27,'Product Master'!$B:$I,7,FALSE)) | Q27: =IFERROR(Table4[[#This Row],[Closing Stock]]*Table4[[#This Row],[Cost Price]],0) -> 0 | R27: =IF(B27="","",IF(M27=0,"Out of Stock",IF(M27<=10,"Low Stock","In Stock")))
A28: P0027 | C28: =IF(B28="","",VLOOKUP(B28,'Product Master'!$B:$G,2,FALSE)) | D28: =IF(B28="","",VLOOKUP(B28,'Product Master'!$B:$G,3,FALSE)) | F28: =SUMIF('Stock Purchase'!$D:$D,B28,'Stock Purchase'!$F:$F) -> 0 | G28: =SUMIFS('Stock Adjustment'!$E:$E,'Stock Adjustment'!$B:$B,$A28,'Stock Adjustment'!$D:$D,"Customer Returned") -> 0 | H28: =SUMIF('Daily Sales Entry'!$D:$D,B28,'Daily Sales Entry'!$G:$G) -> 0 | I28: =SUMIFS('Stock Adjustment'!$E:$E,'Stock Adjustment'!$B:$B,$A28,'Stock Adjustment'!$D:$D,"Staff Consumption") -> 0 | J28: =SUMIFS('Stock Adjustment'!$E:$E,'Stock Adjustment'!$B:$B,$A28,'Stock Adjustment'!$D:$D,"Damaged") -> 0 | K28: =SUMIFS('Stock Adjustment'!$E:$E,'Stock Adjustment'!$B:$B,$A28,'Stock Adjustment'!$D:$D,"Expired") -> 0 | L28: =SUMIFS('Stock Adjustment'!$E:$E,'Stock Adjustment'!$B:$B,$A28,'Stock Adjustment'!$D:$D,"Supplier Returned") -> 0 | M28: =Table4[[#This Row],[Opening Stock]]+Table4[[#This Row],[Total Purchased]]+Table4[[#This Row],[Customer Returned]]-Table4[[#This Row],[Total Sold]]-Table4[[#This Row],[Damaged]]-Table4[[#This Row],[Expired]]-Table4[[#This Row],[Supplier Returned]]-Table4[[#This Row],[Staff Consumption]] -> 0 | N28: =IF(B28="","",VLOOKUP(B28,'Product Master'!$B:$G,4,FALSE)) | O28: =IF(B28="","",VLOOKUP(B28,'Product Master'!$B:$G,5,FALSE)) | P28: =IF(B28="","",VLOOKUP(B28,'Product Master'!$B:$I,7,FALSE)) | Q28: =IFERROR(Table4[[#This Row],[Closing Stock]]*Table4[[#This Row],[Cost Price]],0) -> 0 | R28: =IF(B28="","",IF(M28=0,"Out of Stock",IF(M28<=10,"Low Stock","In Stock")))
... A103: P0102 | C103: =IF(B103="","",VLOOKUP(B103,'Product Master'!$B:$G,2,FALSE)) | D103: =IF(B103="","",VLOOKUP(B103,'Product Master'!$B:$G,3,FALSE)) | F103: =SUMIF('Stock Purchase'!$D:$D,B103,'Stock Purchase'!$F:$F) -> 0 | G103: =SUMIFS('Stock Adjustment'!$E:$E,'Stock Adjustment'!$B:$B,$A103,'Stock Adjustment'!$D:$D,"Customer Returned") -> 0 | H103: =SUMIF('Daily Sales Entry'!$D:$D,B103,'Daily Sales Entry'!$G:$G) -> 0 | I103: =SUMIFS('Stock Adjustment'!$E:$E,'Stock Adjustment'!$B:$B,$A103,'Stock Adjustment'!$D:$D,"Staff Consumption") -> 0 | J103: =SUMIFS('Stock Adjustment'!$E:$E,'Stock Adjustment'!$B:$B,$A103,'Stock Adjustment'!$D:$D,"Damaged") -> 0 | K103: =SUMIFS('Stock Adjustment'!$E:$E,'Stock Adjustment'!$B:$B,$A103,'Stock Adjustment'!$D:$D,"Expired") -> 0 | L103: =SUMIFS('Stock Adjustment'!$E:$E,'Stock Adjustment'!$B:$B,$A103,'Stock Adjustment'!$D:$D,"Supplier Returned") -> 0 | M103: =Table4[[#This Row],[Opening Stock]]+Table4[[#This Row],[Total Purchased]]+Table4[[#This Row],[Customer Returned]]-Table4[[#This Row],[Total Sold]]-Table4[[#This Row],[Damaged]]-Table4[[#This Row],[Expired]]-Table4[[#This Row],[Supplier Returned]]-Table4[[#This Row],[Staff Consumption]] -> 0 | N103: =IF(B103="","",VLOOKUP(B103,'Product Master'!$B:$G,4,FALSE)) | O103: =IF(B103="","",VLOOKUP(B103,'Product Master'!$B:$G,5,FALSE)) | P103: =IF(B103="","",VLOOKUP(B103,'Product Master'!$B:$I,7,FALSE)) | Q103: =IFERROR(Table4[[#This Row],[Closing Stock]]*Table4[[#This Row],[Cost Price]],0) -> 0 | R103: =IF(B103="","",IF(M103=0,"Out of Stock",IF(M103<=10,"Low Stock","In Stock")))
A104: P0103 | C104: =IF(B104="","",VLOOKUP(B104,'Product Master'!$B:$G,2,FALSE)) | D104: =IF(B104="","",VLOOKUP(B104,'Product Master'!$B:$G,3,FALSE)) | F104: =SUMIF('Stock Purchase'!$D:$D,B104,'Stock Purchase'!$F:$F) -> 0 | G104: =SUMIFS('Stock Adjustment'!$E:$E,'Stock Adjustment'!$B:$B,$A104,'Stock Adjustment'!$D:$D,"Customer Returned") -> 0 | H104: =SUMIF('Daily Sales Entry'!$D:$D,B104,'Daily Sales Entry'!$G:$G) -> 0 | I104: =SUMIFS('Stock Adjustment'!$E:$E,'Stock Adjustment'!$B:$B,$A104,'Stock Adjustment'!$D:$D,"Staff Consumption") -> 0 | J104: =SUMIFS('Stock Adjustment'!$E:$E,'Stock Adjustment'!$B:$B,$A104,'Stock Adjustment'!$D:$D,"Damaged") -> 0 | K104: =SUMIFS('Stock Adjustment'!$E:$E,'Stock Adjustment'!$B:$B,$A104,'Stock Adjustment'!$D:$D,"Expired") -> 0 | L104: =SUMIFS('Stock Adjustment'!$E:$E,'Stock Adjustment'!$B:$B,$A104,'Stock Adjustment'!$D:$D,"Supplier Returned") -> 0 | M104: =Table4[[#This Row],[Opening Stock]]+Table4[[#This Row],[Total Purchased]]+Table4[[#This Row],[Customer Returned]]-Table4[[#This Row],[Total Sold]]-Table4[[#This Row],[Damaged]]-Table4[[#This Row],[Expired]]-Table4[[#This Row],[Supplier Returned]]-Table4[[#This Row],[Staff Consumption]] -> 0 | N104: =IF(B104="","",VLOOKUP(B104,'Product Master'!$B:$G,4,FALSE)) | O104: =IF(B104="","",VLOOKUP(B104,'Product Master'!$B:$G,5,FALSE)) | P104: =IF(B104="","",VLOOKUP(B104,'Product Master'!$B:$I,7,FALSE)) | R104: =IF(B104="","",IF(M104=0,"Out of Stock",IF(M104<=10,"Low Stock","In Stock")))
A105: P0104 | C105: =IF(B105="","",VLOOKUP(B105,'Product Master'!$B:$G,2,FALSE)) | D105: =IF(B105="","",VLOOKUP(B105,'Product Master'!$B:$G,3,FALSE)) | F105: =SUMIF('Stock Purchase'!$D:$D,B105,'Stock Purchase'!$F:$F) -> 0 | G105: =SUMIFS('Stock Adjustment'!$E:$E,'Stock Adjustment'!$B:$B,$A105,'Stock Adjustment'!$D:$D,"Customer Returned") -> 0 | H105: =SUMIF('Daily Sales Entry'!$D:$D,B105,'Daily Sales Entry'!$G:$G) -> 0 | I105: =SUMIFS('Stock Adjustment'!$E:$E,'Stock Adjustment'!$B:$B,$A105,'Stock Adjustment'!$D:$D,"Staff Consumption") -> 0 | J105: =SUMIFS('Stock Adjustment'!$E:$E,'Stock Adjustment'!$B:$B,$A105,'Stock Adjustment'!$D:$D,"Damaged") -> 0 | K105: =SUMIFS('Stock Adjustment'!$E:$E,'Stock Adjustment'!$B:$B,$A105,'Stock Adjustment'!$D:$D,"Expired") -> 0 | L105: =SUMIFS('Stock Adjustment'!$E:$E,'Stock Adjustment'!$B:$B,$A105,'Stock Adjustment'!$D:$D,"Supplier Returned") -> 0 | M105: =Table4[[#This Row],[Opening Stock]]+Table4[[#This Row],[Total Purchased]]+Table4[[#This Row],[Customer Returned]]-Table4[[#This Row],[Total Sold]]-Table4[[#This Row],[Damaged]]-Table4[[#This Row],[Expired]]-Table4[[#This Row],[Supplier Returned]]-Table4[[#This Row],[Staff Consumption]] -> 0 | N105: =IF(B105="","",VLOOKUP(B105,'Product Master'!$B:$G,4,FALSE)) | O105: =IF(B105="","",VLOOKUP(B105,'Product Master'!$B:$G,5,FALSE)) | P105: =IF(B105="","",VLOOKUP(B105,'Product Master'!$B:$I,7,FALSE)) | R105: =IF(B105="","",IF(M105=0,"Out of Stock",IF(M105<=10,"Low Stock","In Stock")))
A106: P0105 | C106: =IF(B106="","",VLOOKUP(B106,'Product Master'!$B:$G,2,FALSE)) | D106: =IF(B106="","",VLOOKUP(B106,'Product Master'!$B:$G,3,FALSE)) | F106: =SUMIF('Stock Purchase'!$D:$D,B106,'Stock Purchase'!$F:$F) -> 0 | G106: =SUMIFS('Stock Adjustment'!$E:$E,'Stock Adjustment'!$B:$B,$A106,'Stock Adjustment'!$D:$D,"Customer Returned") -> 0 | H106: =SUMIF('Daily Sales Entry'!$D:$D,B106,'Daily Sales Entry'!$G:$G) -> 0 | I106: =SUMIFS('Stock Adjustment'!$E:$E,'Stock Adjustment'!$B:$B,$A106,'Stock Adjustment'!$D:$D,"Staff Consumption") -> 0 | J106: =SUMIFS('Stock Adjustment'!$E:$E,'Stock Adjustment'!$B:$B,$A106,'Stock Adjustment'!$D:$D,"Damaged") -> 0 | K106: =SUMIFS('Stock Adjustment'!$E:$E,'Stock Adjustment'!$B:$B,$A106,'Stock Adjustment'!$D:$D,"Expired") -> 0 | L106: =SUMIFS('Stock Adjustment'!$E:$E,'Stock Adjustment'!$B:$B,$A106,'Stock Adjustment'!$D:$D,"Supplier Returned") -> 0 | M106: =Table4[[#This Row],[Opening Stock]]+Table4[[#This Row],[Total Purchased]]+Table4[[#This Row],[Customer Returned]]-Table4[[#This Row],[Total Sold]]-Table4[[#This Row],[Damaged]]-Table4[[#This Row],[Expired]]-Table4[[#This Row],[Supplier Returned]]-Table4[[#This Row],[Staff Consumption]] -> 0 | N106: =IF(B106="","",VLOOKUP(B106,'Product Master'!$B:$G,4,FALSE)) | O106: =IF(B106="","",VLOOKUP(B106,'Product Master'!$B:$G,5,FALSE)) | P106: =IF(B106="","",VLOOKUP(B106,'Product Master'!$B:$I,7,FALSE)) | R106: =IF(B106="","",IF(M106=0,"Out of Stock",IF(M106<=10,"Low Stock","In Stock")))
A107: P0106 | C107: =IF(B107="","",VLOOKUP(B107,'Product Master'!$B:$G,2,FALSE)) | D107: =IF(B107="","",VLOOKUP(B107,'Product Master'!$B:$G,3,FALSE)) | F107: =SUMIF('Stock Purchase'!$D:$D,B107,'Stock Purchase'!$F:$F) -> 0 | G107: =SUMIFS('Stock Adjustment'!$E:$E,'Stock Adjustment'!$B:$B,$A107,'Stock Adjustment'!$D:$D,"Customer Returned") -> 0 | H107: =SUMIF('Daily Sales Entry'!$D:$D,B107,'Daily Sales Entry'!$G:$G) -> 0 | I107: =SUMIFS('Stock Adjustment'!$E:$E,'Stock Adjustment'!$B:$B,$A107,'Stock Adjustment'!$D:$D,"Staff Consumption") -> 0 | J107: =SUMIFS('Stock Adjustment'!$E:$E,'Stock Adjustment'!$B:$B,$A107,'Stock Adjustment'!$D:$D,"Damaged") -> 0 | K107: =SUMIFS('Stock Adjustment'!$E:$E,'Stock Adjustment'!$B:$B,$A107,'Stock Adjustment'!$D:$D,"Expired") -> 0 | L107: =SUMIFS('Stock Adjustment'!$E:$E,'Stock Adjustment'!$B:$B,$A107,'Stock Adjustment'!$D:$D,"Supplier Returned") -> 0 | M107: =Table4[[#This Row],[Opening Stock]]+Table4[[#This Row],[Total Purchased]]+Table4[[#This Row],[Customer Returned]]-Table4[[#This Row],[Total Sold]]-Table4[[#This Row],[Damaged]]-Table4[[#This Row],[Expired]]-Table4[[#This Row],[Supplier Returned]]-Table4[[#This Row],[Staff Consumption]] -> 0 | N107: =IF(B107="","",VLOOKUP(B107,'Product Master'!$B:$G,4,FALSE)) | O107: =IF(B107="","",VLOOKUP(B107,'Product Master'!$B:$G,5,FALSE)) | P107: =IF(B107="","",VLOOKUP(B107,'Product Master'!$B:$I,7,FALSE)) | R107: =IF(B107="","",IF(M107=0,"Out of Stock",IF(M107<=10,"Low Stock","In Stock")))
A108: P0107 | C108: =IF(B108="","",VLOOKUP(B108,'Product Master'!$B:$G,2,FALSE)) | D108: =IF(B108="","",VLOOKUP(B108,'Product Master'!$B:$G,3,FALSE)) | F108: =SUMIF('Stock Purchase'!$D:$D,B108,'Stock Purchase'!$F:$F) -> 0 | G108: =SUMIFS('Stock Adjustment'!$E:$E,'Stock Adjustment'!$B:$B,$A108,'Stock Adjustment'!$D:$D,"Customer Returned") -> 0 | H108: =SUMIF('Daily Sales Entry'!$D:$D,B108,'Daily Sales Entry'!$G:$G) -> 0 | I108: =SUMIFS('Stock Adjustment'!$E:$E,'Stock Adjustment'!$B:$B,$A108,'Stock Adjustment'!$D:$D,"Staff Consumption") -> 0 | J108: =SUMIFS('Stock Adjustment'!$E:$E,'Stock Adjustment'!$B:$B,$A108,'Stock Adjustment'!$D:$D,"Damaged") -> 0 | K108: =SUMIFS('Stock Adjustment'!$E:$E,'Stock Adjustment'!$B:$B,$A108,'Stock Adjustment'!$D:$D,"Expired") -> 0 | L108: =SUMIFS('Stock Adjustment'!$E:$E,'Stock Adjustment'!$B:$B,$A108,'Stock Adjustment'!$D:$D,"Supplier Returned") -> 0 | M108: =Table4[[#This Row],[Opening Stock]]+Table4[[#This Row],[Total Purchased]]+Table4[[#This Row],[Customer Returned]]-Table4[[#This Row],[Total Sold]]-Table4[[#This Row],[Damaged]]-Table4[[#This Row],[Expired]]-Table4[[#This Row],[Supplier Returned]]-Table4[[#This Row],[Staff Consumption]] -> 0 | N108: =IF(B108="","",VLOOKUP(B108,'Product Master'!$B:$G,4,FALSE)) | O108: =IF(B108="","",VLOOKUP(B108,'Product Master'!$B:$G,5,FALSE)) | P108: =IF(B108="","",VLOOKUP(B108,'Product Master'!$B:$I,7,FALSE)) | R108: =IF(B108="","",IF(M108=0,"Out of Stock",IF(M108<=10,"Low Stock","In Stock")))
A109: P0108 | C109: =IF(B109="","",VLOOKUP(B109,'Product Master'!$B:$G,2,FALSE)) | D109: =IF(B109="","",VLOOKUP(B109,'Product Master'!$B:$G,3,FALSE)) | F109: =SUMIF('Stock Purchase'!$D:$D,B109,'Stock Purchase'!$F:$F) -> 0 | G109: =SUMIFS('Stock Adjustment'!$E:$E,'Stock Adjustment'!$B:$B,$A109,'Stock Adjustment'!$D:$D,"Customer Returned") -> 0 | H109: =SUMIF('Daily Sales Entry'!$D:$D,B109,'Daily Sales Entry'!$G:$G) -> 0 | I109: =SUMIFS('Stock Adjustment'!$E:$E,'Stock Adjustment'!$B:$B,$A109,'Stock Adjustment'!$D:$D,"Staff Consumption") -> 0 | J109: =SUMIFS('Stock Adjustment'!$E:$E,'Stock Adjustment'!$B:$B,$A109,'Stock Adjustment'!$D:$D,"Damaged") -> 0 | K109: =SUMIFS('Stock Adjustment'!$E:$E,'Stock Adjustment'!$B:$B,$A109,'Stock Adjustment'!$D:$D,"Expired") -> 0 | L109: =SUMIFS('Stock Adjustment'!$E:$E,'Stock Adjustment'!$B:$B,$A109,'Stock Adjustment'!$D:$D,"Supplier Returned") -> 0 | M109: =Table4[[#This Row],[Opening Stock]]+Table4[[#This Row],[Total Purchased]]+Table4[[#This Row],[Customer Returned]]-Table4[[#This Row],[Total Sold]]-Table4[[#This Row],[Damaged]]-Table4[[#This Row],[Expired]]-Table4[[#This Row],[Supplier Returned]]-Table4[[#This Row],[Staff Consumption]] -> 0 | N109: =IF(B109="","",VLOOKUP(B109,'Product Master'!$B:$G,4,FALSE)) | O109: =IF(B109="","",VLOOKUP(B109,'Product Master'!$B:$G,5,FALSE)) | P109: =IF(B109="","",VLOOKUP(B109,'Product Master'!$B:$I,7,FALSE)) | R109: =IF(B109="","",IF(M109=0,"Out of Stock",IF(M109<=10,"Low Stock","In Stock")))
A110: P0109 | C110: =IF(B110="","",VLOOKUP(B110,'Product Master'!$B:$G,2,FALSE)) | D110: =IF(B110="","",VLOOKUP(B110,'Product Master'!$B:$G,3,FALSE)) | F110: =SUMIF('Stock Purchase'!$D:$D,B110,'Stock Purchase'!$F:$F) -> 0 | G110: =SUMIFS('Stock Adjustment'!$E:$E,'Stock Adjustment'!$B:$B,$A110,'Stock Adjustment'!$D:$D,"Customer Returned") -> 0 | H110: =SUMIF('Daily Sales Entry'!$D:$D,B110,'Daily Sales Entry'!$G:$G) -> 0 | I110: =SUMIFS('Stock Adjustment'!$E:$E,'Stock Adjustment'!$B:$B,$A110,'Stock Adjustment'!$D:$D,"Staff Consumption") -> 0 | J110: =SUMIFS('Stock Adjustment'!$E:$E,'Stock Adjustment'!$B:$B,$A110,'Stock Adjustment'!$D:$D,"Damaged") -> 0 | K110: =SUMIFS('Stock Adjustment'!$E:$E,'Stock Adjustment'!$B:$B,$A110,'Stock Adjustment'!$D:$D,"Expired") -> 0 | L110: =SUMIFS('Stock Adjustment'!$E:$E,'Stock Adjustment'!$B:$B,$A110,'Stock Adjustment'!$D:$D,"Supplier Returned") -> 0 | M110: =Table4[[#This Row],[Opening Stock]]+Table4[[#This Row],[Total Purchased]]+Table4[[#This Row],[Customer Returned]]-Table4[[#This Row],[Total Sold]]-Table4[[#This Row],[Damaged]]-Table4[[#This Row],[Expired]]-Table4[[#This Row],[Supplier Returned]]-Table4[[#This Row],[Staff Consumption]] -> 0 | N110: =IF(B110="","",VLOOKUP(B110,'Product Master'!$B:$G,4,FALSE)) | O110: =IF(B110="","",VLOOKUP(B110,'Product Master'!$B:$G,5,FALSE)) | P110: =IF(B110="","",VLOOKUP(B110,'Product Master'!$B:$I,7,FALSE)) | R110: =IF(B110="","",IF(M110=0,"Out of Stock",IF(M110<=10,"Low Stock","In Stock")))
A111: P0110 | C111: =IF(B111="","",VLOOKUP(B111,'Product Master'!$B:$G,2,FALSE)) | D111: =IF(B111="","",VLOOKUP(B111,'Product Master'!$B:$G,3,FALSE)) | F111: =SUMIF('Stock Purchase'!$D:$D,B111,'Stock Purchase'!$F:$F) -> 0 | G111: =SUMIFS('Stock Adjustment'!$E:$E,'Stock Adjustment'!$B:$B,$A111,'Stock Adjustment'!$D:$D,"Customer Returned") -> 0 | H111: =SUMIF('Daily Sales Entry'!$D:$D,B111,'Daily Sales Entry'!$G:$G) -> 0 | I111: =SUMIFS('Stock Adjustment'!$E:$E,'Stock Adjustment'!$B:$B,$A111,'Stock Adjustment'!$D:$D,"Staff Consumption") -> 0 | J111: =SUMIFS('Stock Adjustment'!$E:$E,'Stock Adjustment'!$B:$B,$A111,'Stock Adjustment'!$D:$D,"Damaged") -> 0 | K111: =SUMIFS('Stock Adjustment'!$E:$E,'Stock Adjustment'!$B:$B,$A111,'Stock Adjustment'!$D:$D,"Expired") -> 0 | L111: =SUMIFS('Stock Adjustment'!$E:$E,'Stock Adjustment'!$B:$B,$A111,'Stock Adjustment'!$D:$D,"Supplier Returned") -> 0 | M111: =Table4[[#This Row],[Opening Stock]]+Table4[[#This Row],[Total Purchased]]+Table4[[#This Row],[Customer Returned]]-Table4[[#This Row],[Total Sold]]-Table4[[#This Row],[Damaged]]-Table4[[#This Row],[Expired]]-Table4[[#This Row],[Supplier Returned]]-Table4[[#This Row],[Staff Consumption]] -> 0 | N111: =IF(B111="","",VLOOKUP(B111,'Product Master'!$B:$G,4,FALSE)) | O111: =IF(B111="","",VLOOKUP(B111,'Product Master'!$B:$G,5,FALSE)) | P111: =IF(B111="","",VLOOKUP(B111,'Product Master'!$B:$I,7,FALSE)) | R111: =IF(B111="","",IF(M111=0,"Out of Stock",IF(M111<=10,"Low Stock","In Stock")))
A112: P0111 | C112: =IF(B112="","",VLOOKUP(B112,'Product Master'!$B:$G,2,FALSE)) | D112: =IF(B112="","",VLOOKUP(B112,'Product Master'!$B:$G,3,FALSE)) | F112: =SUMIF('Stock Purchase'!$D:$D,B112,'Stock Purchase'!$F:$F) -> 0 | G112: =SUMIFS('Stock Adjustment'!$E:$E,'Stock Adjustment'!$B:$B,$A112,'Stock Adjustment'!$D:$D,"Customer Returned") -> 0 | H112: =SUMIF('Daily Sales Entry'!$D:$D,B112,'Daily Sales Entry'!$G:$G) -> 0 | I112: =SUMIFS('Stock Adjustment'!$E:$E,'Stock Adjustment'!$B:$B,$A112,'Stock Adjustment'!$D:$D,"Staff Consumption") -> 0 | J112: =SUMIFS('Stock Adjustment'!$E:$E,'Stock Adjustment'!$B:$B,$A112,'Stock Adjustment'!$D:$D,"Damaged") -> 0 | K112: =SUMIFS('Stock Adjustment'!$E:$E,'Stock Adjustment'!$B:$B,$A112,'Stock Adjustment'!$D:$D,"Expired") -> 0 | L112: =SUMIFS('Stock Adjustment'!$E:$E,'Stock Adjustment'!$B:$B,$A112,'Stock Adjustment'!$D:$D,"Supplier Returned") -> 0 | M112: =Table4[[#This Row],[Opening Stock]]+Table4[[#This Row],[Total Purchased]]+Table4[[#This Row],[Customer Returned]]-Table4[[#This Row],[Total Sold]]-Table4[[#This Row],[Damaged]]-Table4[[#This Row],[Expired]]-Table4[[#This Row],[Supplier Returned]]-Table4[[#This Row],[Staff Consumption]] -> 0 | N112: =IF(B112="","",VLOOKUP(B112,'Product Master'!$B:$G,4,FALSE)) | O112: =IF(B112="","",VLOOKUP(B112,'Product Master'!$B:$G,5,FALSE)) | P112: =IF(B112="","",VLOOKUP(B112,'Product Master'!$B:$I,7,FALSE)) | R112: =IF(B112="","",IF(M112=0,"Out of Stock",IF(M112<=10,"Low Stock","In Stock")))
A113: P0112 | C113: =IF(B113="","",VLOOKUP(B113,'Product Master'!$B:$G,2,FALSE)) | D113: =IF(B113="","",VLOOKUP(B113,'Product Master'!$B:$G,3,FALSE)) | F113: =SUMIF('Stock Purchase'!$D:$D,B113,'Stock Purchase'!$F:$F) -> 0 | G113: =SUMIFS('Stock Adjustment'!$E:$E,'Stock Adjustment'!$B:$B,$A113,'Stock Adjustment'!$D:$D,"Customer Returned") -> 0 | H113: =SUMIF('Daily Sales Entry'!$D:$D,B113,'Daily Sales Entry'!$G:$G) -> 0 | I113: =SUMIFS('Stock Adjustment'!$E:$E,'Stock Adjustment'!$B:$B,$A113,'Stock Adjustment'!$D:$D,"Staff Consumption") -> 0 | J113: =SUMIFS('Stock Adjustment'!$E:$E,'Stock Adjustment'!$B:$B,$A113,'Stock Adjustment'!$D:$D,"Damaged") -> 0 | K113: =SUMIFS('Stock Adjustment'!$E:$E,'Stock Adjustment'!$B:$B,$A113,'Stock Adjustment'!$D:$D,"Expired") -> 0 | L113: =SUMIFS('Stock Adjustment'!$E:$E,'Stock Adjustment'!$B:$B,$A113,'Stock Adjustment'!$D:$D,"Supplier Returned") -> 0 | M113: =Table4[[#This Row],[Opening Stock]]+Table4[[#This Row],[Total Purchased]]+Table4[[#This Row],[Customer Returned]]-Table4[[#This Row],[Total Sold]]-Table4[[#This Row],[Damaged]]-Table4[[#This Row],[Expired]]-Table4[[#This Row],[Supplier Returned]]-Table4[[#This Row],[Staff Consumption]] -> 0 | N113: =IF(B113="","",VLOOKUP(B113,'Product Master'!$B:$G,4,FALSE)) | O113: =IF(B113="","",VLOOKUP(B113,'Product Master'!$B:$G,5,FALSE)) | P113: =IF(B113="","",VLOOKUP(B113,'Product Master'!$B:$I,7,FALSE)) | R113: =IF(B113="","",IF(M113=0,"Out of Stock",IF(M113<=10,"Low Stock","In Stock")))
A114: P0113 | C114: =IF(B114="","",VLOOKUP(B114,'Product Master'!$B:$G,2,FALSE)) | D114: =IF(B114="","",VLOOKUP(B114,'Product Master'!$B:$G,3,FALSE)) | F114: =SUMIF('Stock Purchase'!$D:$D,B114,'Stock Purchase'!$F:$F) -> 0 | G114: =SUMIFS('Stock Adjustment'!$E:$E,'Stock Adjustment'!$B:$B,$A114,'Stock Adjustment'!$D:$D,"Customer Returned") -> 0 | H114: =SUMIF('Daily Sales Entry'!$D:$D,B114,'Daily Sales Entry'!$G:$G) -> 0 | I114: =SUMIFS('Stock Adjustment'!$E:$E,'Stock Adjustment'!$B:$B,$A114,'Stock Adjustment'!$D:$D,"Staff Consumption") -> 0 | J114: =SUMIFS('Stock Adjustment'!$E:$E,'Stock Adjustment'!$B:$B,$A114,'Stock Adjustment'!$D:$D,"Damaged") -> 0 | K114: =SUMIFS('Stock Adjustment'!$E:$E,'Stock Adjustment'!$B:$B,$A114,'Stock Adjustment'!$D:$D,"Expired") -> 0 | L114: =SUMIFS('Stock Adjustment'!$E:$E,'Stock Adjustment'!$B:$B,$A114,'Stock Adjustment'!$D:$D,"Supplier Returned") -> 0 | M114: =Table4[[#This Row],[Opening Stock]]+Table4[[#This Row],[Total Purchased]]+Table4[[#This Row],[Customer Returned]]-Table4[[#This Row],[Total Sold]]-Table4[[#This Row],[Damaged]]-Table4[[#This Row],[Expired]]-Table4[[#This Row],[Supplier Returned]]-Table4[[#This Row],[Staff Consumption]] -> 0 | N114: =IF(B114="","",VLOOKUP(B114,'Product Master'!$B:$G,4,FALSE)) | O114: =IF(B114="","",VLOOKUP(B114,'Product Master'!$B:$G,5,FALSE)) | P114: =IF(B114="","",VLOOKUP(B114,'Product Master'!$B:$I,7,FALSE)) | R114: =IF(B114="","",IF(M114=0,"Out of Stock",IF(M114<=10,"Low Stock","In Stock")))
A115: P0114 | C115: =IF(B115="","",VLOOKUP(B115,'Product Master'!$B:$G,2,FALSE)) | D115: =IF(B115="","",VLOOKUP(B115,'Product Master'!$B:$G,3,FALSE)) | F115: =SUMIF('Stock Purchase'!$D:$D,B115,'Stock Purchase'!$F:$F) -> 0 | G115: =SUMIFS('Stock Adjustment'!$E:$E,'Stock Adjustment'!$B:$B,$A115,'Stock Adjustment'!$D:$D,"Customer Returned") -> 0 | H115: =SUMIF('Daily Sales Entry'!$D:$D,B115,'Daily Sales Entry'!$G:$G) -> 0 | I115: =SUMIFS('Stock Adjustment'!$E:$E,'Stock Adjustment'!$B:$B,$A115,'Stock Adjustment'!$D:$D,"Staff Consumption") -> 0 | J115: =SUMIFS('Stock Adjustment'!$E:$E,'Stock Adjustment'!$B:$B,$A115,'Stock Adjustment'!$D:$D,"Damaged") -> 0 | K115: =SUMIFS('Stock Adjustment'!$E:$E,'Stock Adjustment'!$B:$B,$A115,'Stock Adjustment'!$D:$D,"Expired") -> 0 | L115: =SUMIFS('Stock Adjustment'!$E:$E,'Stock Adjustment'!$B:$B,$A115,'Stock Adjustment'!$D:$D,"Supplier Returned") -> 0 | M115: =Table4[[#This Row],[Opening Stock]]+Table4[[#This Row],[Total Purchased]]+Table4[[#This Row],[Customer Returned]]-Table4[[#This Row],[Total Sold]]-Table4[[#This Row],[Damaged]]-Table4[[#This Row],[Expired]]-Table4[[#This Row],[Supplier Returned]]-Table4[[#This Row],[Staff Consumption]] -> 0 | N115: =IF(B115="","",VLOOKUP(B115,'Product Master'!$B:$G,4,FALSE)) | O115: =IF(B115="","",VLOOKUP(B115,'Product Master'!$B:$G,5,FALSE)) | P115: =IF(B115="","",VLOOKUP(B115,'Product Master'!$B:$I,7,FALSE)) | R115: =IF(B115="","",IF(M115=0,"Out of Stock",IF(M115<=10,"Low Stock","In Stock")))
... A1039: P1038 | C1039: =IF(B1039="","",VLOOKUP(B1039,'Product Master'!$B:$G,2,FALSE)) | D1039: =IF(B1039="","",VLOOKUP(B1039,'Product Master'!$B:$G,3,FALSE)) | F1039: =SUMIF('Stock Purchase'!$D:$D,B1039,'Stock Purchase'!$F:$F) -> 0 | G1039: =SUMIFS('Stock Adjustment'!$E:$E,'Stock Adjustment'!$B:$B,$A1039,'Stock Adjustment'!$D:$D,"Customer Returned") -> 0 | H1039: =SUMIF('Daily Sales Entry'!$D:$D,B1039,'Daily Sales Entry'!$G:$G) -> 0 | I1039: =SUMIFS('Stock Adjustment'!$E:$E,'Stock Adjustment'!$B:$B,$A1039,'Stock Adjustment'!$D:$D,"Staff Consumption") -> 0 | J1039: =SUMIFS('Stock Adjustment'!$E:$E,'Stock Adjustment'!$B:$B,$A1039,'Stock Adjustment'!$D:$D,"Damaged") -> 0 | K1039: =SUMIFS('Stock Adjustment'!$E:$E,'Stock Adjustment'!$B:$B,$A1039,'Stock Adjustment'!$D:$D,"Expired") -> 0 | L1039: =SUMIFS('Stock Adjustment'!$E:$E,'Stock Adjustment'!$B:$B,$A1039,'Stock Adjustment'!$D:$D,"Supplier Returned") -> 0 | M1039: =Table4[[#This Row],[Opening Stock]]+Table4[[#This Row],[Total Purchased]]+Table4[[#This Row],[Customer Returned]]-Table4[[#This Row],[Total Sold]]-Table4[[#This Row],[Damaged]]-Table4[[#This Row],[Expired]]-Table4[[#This Row],[Supplier Returned]]-Table4[[#This Row],[Staff Consumption]] -> 0 | N1039: =IF(B1039="","",VLOOKUP(B1039,'Product Master'!$B:$G,4,FALSE)) | O1039: =IF(B1039="","",VLOOKUP(B1039,'Product Master'!$B:$G,5,FALSE)) | P1039: =IF(B1039="","",VLOOKUP(B1039,'Product Master'!$B:$I,7,FALSE)) | R1039: =IF(B1039="","",IF(M1039=0,"Out of Stock",IF(M1039<=10,"Low Stock","In Stock")))
A1040: Total | R1040: =SUBTOTAL(103,Table4[Stock Status]) -> 1038

Sheet Stock Adjustment
A1: Date | B1: Product ID | C1: Product Name | D1: Adjustment Type | E1: Quantity | F1: Reason
A2: 46235 | B2: P0001 | C2: =IFERROR(VLOOKUP(B2,'Product Master'!$A:$B,2,FALSE),"") -> Beef | D2: Damaged | E2: 10
A3: 46236 | B3: P0001 | C3: =IFERROR(VLOOKUP(B3,'Product Master'!$A:$B,2,FALSE),"") -> Beef | D3: Damaged | E3: 5
A4: 46237 | B4: P0002 | C4: =IFERROR(VLOOKUP(B4,'Product Master'!$A:$B,2,FALSE),"") -> Shaki | D4: Staff Consumption | E4: 2
A5: 46238 | B5: P0007 | C5: =IFERROR(VLOOKUP(B5,'Product Master'!$A:$B,2,FALSE),"") -> Meat Pie
A6: 46239 | C6: =IFERROR(VLOOKUP(B6,'Product Master'!$A:$B,2,FALSE),"")
A7: 46240 | C7: =IFERROR(VLOOKUP(B7,'Product Master'!$A:$B,2,FALSE),"")
A8: 46241 | C8: =IFERROR(VLOOKUP(B8,'Product Master'!$A:$B,2,FALSE),"")
A9: 46242 | C9: =IFERROR(VLOOKUP(B9,'Product Master'!$A:$B,2,FALSE),"")
A10: 46243 | C10: =IFERROR(VLOOKUP(B10,'Product Master'!$A:$B,2,FALSE),"")
A11: 46244 | C11: =IFERROR(VLOOKUP(B11,'Product Master'!$A:$B,2,FALSE),"")
A12: 46245 | C12: =IFERROR(VLOOKUP(B12,'Product Master'!$A:$B,2,FALSE),"")
A13: 46246 | C13: =IFERROR(VLOOKUP(B13,'Product Master'!$A:$B,2,FALSE),"")
A14: 46247 | C14: =IFERROR(VLOOKUP(B14,'Product Master'!$A:$B,2,FALSE),"")
A15: 46248 | C15: =IFERROR(VLOOKUP(B15,'Product Master'!$A:$B,2,FALSE),"")
A16: 46249 | C16: =IFERROR(VLOOKUP(B16,'Product Master'!$A:$B,2,FALSE),"")
A17: 46250 | C17: =IFERROR(VLOOKUP(B17,'Product Master'!$A:$B,2,FALSE),"")
... A32: 46265 | C32: =IFERROR(VLOOKUP(B32,'Product Master'!$A:$B,2,FALSE),"")

Sheet Expenses
A1: Expenses ID | B1: Date | C1: Expenses Category | D1: Description | E1: Amount | F1: Payment Method
A2: E001 | B2: 46204 | C2: Transportation | D2: To get some raw materials at the market | E2: 2500 | F2: Cash
A3: E002 | B3: 46205 | C3: Salary | D3: Payment of staff salary | E3: 30000 | F3: Transfer
A4: E003 | B4: 46206 | C4: Electricity | D4: NEPA | E4: 10000 | F4: Transfer
A5: E004 | B5: 46207
A6: E005 | B6: 46208
A7: E006 | B7: 46209
A8: E007 | B8: 46210
A9: E008 | B9: 46211
A10: E009 | B10: 46212
A11: E010 | B11: 46213
A12: E011 | B12: 46214
A13: E012 | B13: 46215
A14: E013 | B14: 46216
A15: E014 | B15: 46217
A16: E015 | B16: 46218
... A32: E031 | B32: 46234

Sheet Budget
A1: Budget ID | B1: Budget Category | C1: Budget Amount | D1: Actual Amount | E1: Variance | F1: Status
A2: B001 | B2: Salary | C2: 100000 | D2: =SUMIF(Expenses!$C:$C,B2,Expenses!$E:$E) -> 30000 | E2: =C2-D2 -> 70000 | F2: =IF(E2>=0,"Within Budget","Over Budget") -> Within Budget
A3: B002 | B3: Electricity | C3: 10000 | D3: =SUMIF(Expenses!$C:$C,B3,Expenses!$E:$E) -> 10000 | E3: =C3-D3 -> 0 | F3: =IF(E3>=0,"Within Budget","Over Budget") -> Within Budget
A4: B003 | D4: =SUMIF(Expenses!$C:$C,B4,Expenses!$E:$E) -> 0 | E4: =C4-D4 -> 0 | F4: =IF(E4>=0,"Within Budget","Over Budget") -> Within Budget
A5: B004 | D5: =SUMIF(Expenses!$C:$C,B5,Expenses!$E:$E) -> 0 | E5: =C5-D5 -> 0 | F5: =IF(E5>=0,"Within Budget","Over Budget") -> Within Budget
A6: B005 | D6: =SUMIF(Expenses!$C:$C,B6,Expenses!$E:$E) -> 0 | E6: =C6-D6 -> 0 | F6: =IF(E6>=0,"Within Budget","Over Budget") -> Within Budget
A7: B006 | D7: =SUMIF(Expenses!$C:$C,B7,Expenses!$E:$E) -> 0 | E7: =C7-D7 -> 0 | F7: =IF(E7>=0,"Within Budget","Over Budget") -> Within Budget
A8: B007 | D8: =SUMIF(Expenses!$C:$C,B8,Expenses!$E:$E) -> 0 | E8: =C8-D8 -> 0 | F8: =IF(E8>=0,"Within Budget","Over Budget") -> Within Budget
A9: B008 | D9: =SUMIF(Expenses!$C:$C,B9,Expenses!$E:$E) -> 0 | E9: =C9-D9 -> 0 | F9: =IF(E9>=0,"Within Budget","Over Budget") -> Within Budget
A10: B009 | D10: =SUMIF(Expenses!$C:$C,B10,Expenses!$E:$E) -> 0 | E10: =C10-D10 -> 0 | F10: =IF(E10>=0,"Within Budget","Over Budget") -> Within Budget
A11: B010 | D11: =SUMIF(Expenses!$C:$C,B11,Expenses!$E:$E) -> 0 | E11: =C11-D11 -> 0 | F11: =IF(E11>=0,"Within Budget","Over Budget") -> Within Budget
A12: B011 | D12: =SUMIF(Expenses!$C:$C,B12,Expenses!$E:$E) -> 0 | E12: =C12-D12 -> 0 | F12: =IF(E12>=0,"Within Budget","Over Budget") -> Within Budget
A13: B012 | D13: =SUMIF(Expenses!$C:$C,B13,Expenses!$E:$E) -> 0 | E13: =C13-D13 -> 0 | F13: =IF(E13>=0,"Within Budget","Over Budget") -> Within Budget
A14: B013 | D14: =SUMIF(Expenses!$C:$C,B14,Expenses!$E:$E) -> 0 | E14: =C14-D14 -> 0 | F14: =IF(E14>=0,"Within Budget","Over Budget") -> Within Budget
A15: B014 | D15: =SUMIF(Expenses!$C:$C,B15,Expenses!$E:$E) -> 0 | E15: =C15-D15 -> 0 | F15: =IF(E15>=0,"Within Budget","Over Budget") -> Within Budget
... A200: B199 | D200: =SUMIF(Expenses!$C:$C,B200,Expenses!$E:$E) -> 0 | E200: =C200-D200 -> 0 | F200: =IF(E200>=0,"Within Budget","Over Budget") -> Within Budget

Sheet Suppliers
A1: Supplier ID | B1: Supplier Name | C1: Phone Number | D1: Address | E1: Products Supplied | F1: Contact Person | G1: Email | H1: Status
A2: ="SUP"&TEXT(ROW()-1,"000") -> SUP001 | B2: Supplier 1 | C2: 9120475646 | D2: No 4, Igando road | E2: Chicken | F2: Kola | G2: Tundesulaimon50@gmail.com | H2: Active
A3: ="SUP"&TEXT(ROW()-1,"000") -> SUP002
A4: ="SUP"&TEXT(ROW()-1,"000") -> SUP003
A5: ="SUP"&TEXT(ROW()-1,"000") -> SUP004
A6: ="SUP"&TEXT(ROW()-1,"000") -> SUP005
A7: ="SUP"&TEXT(ROW()-1,"000") -> SUP006
A8: ="SUP"&TEXT(ROW()-1,"000") -> SUP007
A9: ="SUP"&TEXT(ROW()-1,"000") -> SUP008
A10: ="SUP"&TEXT(ROW()-1,"000") -> SUP009
A11: ="SUP"&TEXT(ROW()-1,"000") -> SUP010
A12: ="SUP"&TEXT(ROW()-1,"000") -> SUP011
A13: ="SUP"&TEXT(ROW()-1,"000") -> SUP012
A14: ="SUP"&TEXT(ROW()-1,"000") -> SUP013
... A101: ="SUP"&TEXT(ROW()-1,"000") -> SUP100

Sheet REPORTS
A1: TOTAL SALES | B1: TOTAL PURCHASES | C1: TOTAL PROFIT | D1: TOTAL EXPENSES | E1: Inventory Value
A2: =Dashboard!D5 -> 284700 | B2: =Dashboard!F5 -> 1995000 | C2: =Dashboard!P5 -> 242200 | D2: =Dashboard!N5 -> 42500 | E2: =Dashboard!H5 -> 1813300

Sheet Product Search
B2: SEARCH PRODUCT
B4: Product Names
B6: Product ID | C6: =IFERROR(INDEX(Inventory!$A:$A,MATCH($C$4,Inventory!$B:$B,0)),"")
B7: Category | C7: =IFERROR(VLOOKUP($C$4,Inventory!$B:$R,2,FALSE),"")
B8: Current Stock | C8: =IFERROR(VLOOKUP($C$4,Inventory!$B:$R,6,FALSE),"")
B9: Cost Price | C9: =IFERROR(VLOOKUP($C$4,Inventory!$B:$R,7,FALSE),"")
B10: Selling Price | C10: =IFERROR(VLOOKUP($C$4,Inventory!$B:$R,8,FALSE),"")
B11: Inventory Value | C11: =IFERROR(VLOOKUP($C$4,Inventory!$B:$R,10,FALSE),"")
B12: Status | C12: =IFERROR(VLOOKUP($C$4,Inventory!$B:$R,11,FALSE),"")

Sheet List
A1: Category | B1: Product Name | C1: Unit of Measure | D1: Supplier | E1: Status | F1: Expenses Category | G1: Admin | H1: Expenses Payment Method | I1: Budget Category | J1: Date | K1: Date2 | L1: Adjustment Type | M1: Sales
A2: Beverages | B2: Beef | C2: Piece | D2: Supplier 1 | E2: Active | F2: Transportation | G2: Cashier 1 | H2: Cash | I2: Transportation | J2: =DATE(2026,8,1) -> 46235 | K2: P0001 | L2: Damaged
A3: Clothing | B3: Shaki | C3: Pack | D3: Supplier 2 | E3: Inactive | F3: Salary | G3: Cashier 2 | H3: Transfer | I3: Salary | J3: =J2+1 -> 46236 | K3: P0002 | L3: Expired
A4: Cosmetics | B4: Cow leg | C4: Carton | D4: Supplier 3 | F4: Rent | G4: Cashier 3 | H4: POS | I4: Rent | J4: =J3+1 -> 46237 | K4: P0003 | L4: Supplier Returned
A5: Electronics | B5: Semovita | C5: Bottle | D5: Local Market | F5: Electricity | G5: Cashier 4 | H5: Cheque | I5: Electricity | J5: =J4+1 -> 46238 | K5: P0004 | L5: Customer Returned
A6: Food | B6: Eba | C6: Box | D6: Walk-in Vendor | F6: Repairs | G6: Cashier 5 | I6: Repairs | J6: =J5+1 -> 46239 | K6: P0005 | L6: Staff Consumption
A7: Frozen Foods | B7: Moin Moin | C7: Kg | F7: Marketing | I7: Marketing | J7: =J6+1 -> 46240 | K7: P0006
A8: Furniture | B8: Meat Pie | C8: Gram | F8: Other Expenses | I8: Other Expenses | J8: =J7+1 -> 46241 | K8: P0007
A9: Groceries | B9: Chicken Pie | C9: Litre | F9: Water | I9: Water | J9: =J8+1 -> 46242 | K9: P0008
A10: Office Supplies | B10: Beef Roll | C10: Millilitre | F10: Maintenance | I10: Maintenance | J10: =J9+1 -> 46243 | K10: P0009
A11: Pharmaceuticals | B11: Tanta Roll | C11: Bag | F11: Internet | I11: Internet | J11: =J10+1 -> 46244 | K11: P0010
A12: Stationery | B12: Doughnut | C12: Roll | F12: Miscellaneous | I12: Miscellaneous | J12: =J11+1 -> 46245 | K12: P0011
A13: Household items | B13: Beef Burger | C13: Pair | F13: Fuel | I13: Fuel | J13: =J12+1 -> 46246 | K13: P0012
A14: Drinks | B14: Scotch Egg | C14: Dozen | F14: Office Supplies | I14: Office Supplies | J14: =J13+1 -> 46247 | K14: P0013
A15: Cakes | B15: Ppg Chicken | C15: Tin | J15: =J14+1 -> 46248 | K15: P0014
A16: Snacks | B16: Roasted Chicken | C16: Sachet | J16: =J15+1 -> 46249 | K16: P0015
A17: Soup | B17: Chicken Salad | C17: Bundle | J17: =J16+1 -> 46250 | K17: P0016
B18: Vegetable Salad | C18: Tray | J18: =J17+1 -> 46251 | K18: P0017
B19: Scramble Egg | C19: Portion | J19: =J18+1 -> 46252 | K19: P0018
B20: Cup Cake | J20: =J19+1 -> 46253 | K20: P0019
B21: Fruit Cake | J21: =J20+1 -> 46254 | K21: P0020
B22: 10 CELEBRATION CAKE | J22: =J21+1 -> 46255 | K22: P0021
B23: 8 CELEBRATION CAKE | J23: =J22+1 -> 46256 | K23: P0022
B24: 6 CELEBRATION CAKE | J24: =J23+1 -> 46257 | K24: P0023
B25: MoinMoin Elewe | J25: =J24+1 -> 46258 | K25: P0024
B26: Sunshine Loaf-Sliced | J26: =J25+1 -> 46259 | K26: P0025
B27: Fruit Bread Loaf | J27: =J26+1 -> 46260 | K27: P0026
B28: Efo-Riro Soup 2 | J28: =J27+1 -> 46261 | K28: P0027
B29: Egusi Soup 2 | J29: =J28+1 -> 46262 | K29: P0028
B30: Tantis Fish Ola | J30: =J29+1 -> 46263 | K30: P0029
B31: Ponmo | J31: =J30+1 -> 46264 | K31: P0030
B32: TURKEY (L) | J32: =J31+1 -> 46265 | K32: P0031
B33: Jollof Rice New | K33: P0032
B34: Fried Rice New | K34: P0033
B35: Efo-Riro Soup New | K35: P0034
B36: Egusi Soup New | K36: P0035
B37: Spaghetti Bolognaise New | K37: P0036
B38: Ofada Rice New | K38: P0037
B39: Ofada Sauce New | K39: P0038
B40: Vegetable Salad New | K40: P0039
B41: CHICKEN VARIANCE (RICE) | K41: P0040
B42: Salad Pack | K42: P0041
B43: T/Away Pack (Africana) | K43: P0042
B44: Ragolis Water .75 Cl | K44: P0043
... B51: Fanta PET 50Cl | K51: P0050
B52: Pepsi PET 50Cl
B53: Limca PET 50Cl
B54: Vitamilk 300Ml
B55: Hollandia Yoghurt Van 1 Ltr
B56: Hollandia Yoghurt Straw 500Ml
B57: Fayrouz Can Drink 33Cl
B58: Smoozy Yoghurt Plain 500Ml
B59: Sprite PET 50Cl
B60: 1 Litre- Vanilla
B61: 1 Litre- Peanut
B62: Double Pleasure -Vanilla/Straw
B63: Double Pleasure -Vanilla/Banan
... B78: Pet Lucozade Boost

Sheet Sheet1
A1: Product ID | B1: Product Name | C1: Price
A2: P001 | B2: Coca-Cola | C2: 500 | H2: P0002
A3: P002 | B3: Pepsi | C3: 450
A4: P003 | B4: Fanta | C4: 500
B6: =VLOOKUP("P001",A2:C4,2,FALSE) -> Coca-Cola
B7: =VLOOKUP("P002",A2:C4,2,FALSE) -> Pepsi
B8: =VLOOKUP("P003",A2:C4,3,FALSE) -> 500 | D8: =INDEX(A2:A4,MATCH("Fanta",B2:B4,0)) -> P003
B9: =VLOOKUP("P001",A2:C4,3,FALSE) -> 500
B10: =VLOOKUP("Fanta",A2:C4,1,FALSE) -> #N/A
B11: =MATCH("Fanta",B2:B4,0) -> 3
B12: =INDEX(A2:A4,3) -> P003
B13: =INDEX(A2:A4,MATCH("Fanta",B2:B4,0)) -> P003
B15: =INDEX(A2:A4,MATCH("Coca-Cola",B2:B4,0)) -> P001
B16: =INDEX(A2:A4,MATCH("Pepsi",B2:B4,0)) -> P002
B17: =INDEX(C2:C4,MATCH("Fanta",B2:B4,0)) -> 500
B18: =INDEX(C2:C4,MATCH("Pepsi",B2:B4,0)) -> 450
B19: =INDEX(B2:B4,MATCH("P001",A2:A4,0)) -> Coca-Cola
B20: =INDEX(C2:C4,MATCH("P002",A2:A4,0)) -> 450
B22: =INDEX(C2:C4,MATCH("Coca-Cola",B2:B4,0)) -> 500
B23: =INDEX(A2:A4,MATCH("Fanta",B2:B4,0)) -> P003
B24: =INDEX(B2:B4,MATCH("P002",A2:A4,0)) -> Pepsi
B26: =INDEX(B2:B4,MATCH("P003",A2:A4,0)) -> Fanta
B27: =INDEX(A2:A4,MATCH("Coca-Cola",B2:B4,0)) -> P001
B28: =INDEX(C2:C4,MATCH("Pepsi",B2:B4,0)) -> 450
B29: =INDEX(B2:B4,MATCH("P001",A2:A4,0)) -> Coca-Cola
A43: Product ID | B43: Product Name | C43: Category | D43: Current Stock | E43: Cost Price | F43: Selling Price
A44: P0001 | B44: Coca-Cola | C44: Beverages | D44: 50 | E44: 400 | F44: 500
A45: P0002 | B45: Pepsi | C45: Beverages | D45: 35 | E45: 350 | F45: 450
A46: P0003 | B46: Fanta | C46: Beverages | D46: 40 | E46: 400 | F46: 500
A47: P0004 | B47: Indomie | C47: Food | D47: 60 | E47: 450 | F47: 600
A48: P0005 | B48: Peak Milk | C48: Dairy | D48: 25 | E48: 700 | F48: 850
A50: 1 | B50: =INDEX(B44:B48,MATCH("P0004",A44:A48,0)) -> Indomie
A51: 2 | B51: =INDEX(D44:D48,MATCH("P0004",A44:A48,0)) -> 60 | D51: 1 | E51: =INDEX(F44:F48,MATCH("P0004",A44:A48,0)) -> 600
A52: 3 | B52: =INDEX(E44:E48,MATCH("P0002",A44:A48,0)) -> 350 | D52: 2 | E52: =INDEX(E44:E48,MATCH("Peak Milk",B44:B48,0)) -> 700
A53: 4 | B53: =INDEX(B44:B48,MATCH("P0005",A44:A48,0)) -> Peak Milk | D53: 3 | E53: =INDEX(D44:D48,MATCH("P0002",A44:A48,0)) -> 35
A54: 5 | B54: =INDEX(F44:F48,MATCH("P0003",A44:A48,0)) -> 500 | D54: 4 | E54: =INDEX(E44:E48,MATCH("Fanta",B44:B48,0)) -> 400
A55: 6 | D55: 5 | E55: =INDEX(F44:F48,MATCH("P0005",A44:A48,0)) -> 850
A56: 7 | D56: 6 | E56: =INDEX(D44:D48,MATCH("Indomie",B44:B48,0)) -> 60
A57: 8 | D57: 7 | E57: =INDEX(E44:E48,MATCH("P0004",A44:A48,0)) -> 450
A58: 9 | D58: 8 | E58: =INDEX(A44:A48,MATCH("Peak Milk",B44:B48,0)) -> P0005
A59: 10 | D59: 9 | E59: =INDEX(B44:B48,MATCH("P0003",A44:A48,0)) -> Fanta
D60: 10 | E60: =INDEX(F44:F48,MATCH(H2,A44:A48,0)) -> 450
E61: =INDEX(A44:A48,MATCH(H2,B44:B48,0)) -> #N/A
E62: =INDEX(E44:E48,MATCH(H2,A44:A48,0)) -> 350
